Workbook

Sheet MORELIA_RP
A3: ACTIVIDAD | B3: Cuenta de ACTIVIDAD | C3: Suma de Numero de Agentes Participantes: | D3: Suma de Cantidad de Unidades Oficiales de Seguridad Vial: | E3: Suma de Kilómetros recorridos. | F3: Suma de Cantidad de Personas alcanzadas.
A4: APOYO A EVENTOS PÚBLICOS | B4: 1 | C4: 1 | D4: 1 | E4: 4 | F4: 400
A5: APOYO A LA VIALIDAD | B5: 1 | C5: 2 | D5: 0 | E5: 0 | F5: 100
A6: APOYOS A OTRAS DEPENDENCIAS (Publicas o privadas) | B6: 1 | C6: 6 | D6: 1 | E6: 15 | F6: 40
A7: BANCOS | B7: 1 | C7: 2 | D7: 1 | E7: 14 | F7: 0
A8: CORTES DE CIRCULACIÓN | B8: 6 | C8: 13 | D8: 6 | E8: 124 | F8: 570
A9: DILIGENCIAS | B9: 1 | C9: 2 | D9: 1 | E9: 1 | F9: 130
A10: ESCUELAS | B10: 14 | C10: 22 | D10: 5 | E10: 48 | F10: 4330
A11: OFICINAS GUBERNAMENTALES | B11: 2 | C11: 4 | D11: 1 | E11: 14 | F11: 20
A12: PASOS PEATONALES | B12: 1 | C12: 2 | D12: 0 | E12: 0 | F12: 15
A13: PATRULLAJES | B13: 7 | C13: 14 | D13: 7 | E13: 190 | F13: 600
A14: RECORRIDOS DE PROXIMIDAD | B14: 1 | C14: 1 | D14: 1 | E14: 25 | F14: 0
A15: SEGURIDAD EN CARRETERAS - SALAMANCA - MORELIA | B15: 1 | C15: 3 | D15: 1 | E15: 40 | F15: 100
... A19: Suma total | B19: 41 | C19: 82 | D19: 29 | E19: 581 | F19: 6405

Sheet JIQUILPAN_RP
A3: ACTIVIDAD | B3: Cuenta de ACTIVIDAD | C3: Suma de Numero de Agentes Participantes: | D3: Suma de Cantidad de Unidades Oficiales de Seguridad Vial: | E3: Suma de Kilómetros recorridos. | F3: Suma de Cantidad de Personas alcanzadas.
A4: AVENIDAS | B4: 2 | C4: 4 | D4: 2 | E4: 36 | F4: 14
A5: BANCOS | B5: 1 | C5: 3 | D5: 1 | E5: 12 | F5: 8
A6: CONCIENTIZACIÓN Y PREVENCIÓN | B6: 1 | C6: 3 | D6: 1 | E6: 0 | F6: 25
A7: ESCUELAS | B7: 4 | C7: 9 | D7: 4 | E7: 58 | F7: 101
A8: GASOLINERAS | B8: 3 | C8: 6 | D8: 3 | E8: 47 | F8: 27
A9: OBRAS PÚBLICAS | B9: 1 | C9: 1 | D9: 1 | E9: 21 | F9: 16
A10: OFICINAS GUBERNAMENTALES | B10: 2 | C10: 3 | D10: 2 | E10: 15 | F10: 23
A11: PERIFÉRICOS | B11: 1 | C11: 1 | D11: 1 | E11: 11 | F11: 10
A12: RECORRIDOS DE PROXIMIDAD | B12: 1 | C12: 2 | D12: 1 | E12: 15 | F12: 15
A13: TIENDAS DEPARTAMENTALES | B13: 1 | C13: 1 | D13: 1 | E13: 15 | F13: 7
A14: Suma total | B14: 17 | C14: 33 | D14: 17 | E14: 230 | F14: 246

Sheet ZAMORA_RP
A3: ACTIVIDAD | B3: Cuenta de ACTIVIDAD | C3: Suma de Numero de Agentes Participantes: | D3: Suma de Cantidad de Unidades Oficiales de Seguridad Vial: | E3: Suma de Kilómetros recorridos. | F3: Suma de Cantidad de Personas alcanzadas.
A4: ACCIDENTES | B4: 1 | C4: 1 | D4: 0 | E4: 30 | F4: 10
A5: APOYO A LA VIALIDAD | B5: 2 | C5: 4 | D5: 2 | E5: 6 | F5: 230
A6: APOYOS A OTRAS DEPENDENCIAS (Publicas o privadas) | B6: 1 | C6: 2 | D6: 1 | E6: 4 | F6: 0
A7: BANCOS | B7: 1 | C7: 2 | D7: 0 | E7: 2 | F7: 5
A8: CONCIENTIZACIÓN Y PREVENCIÓN | B8: 2 | C8: 4 | D8: 0 | E8: 2 | F8: 16
A9: ESCUELAS | B9: 11 | C9: 18 | D9: 7 | E9: 57 | F9: 450
A10: GASOLINERAS | B10: 1 | C10: 2 | D10: 1 | E10: 6 | F10: 0
A11: OFICINAS GUBERNAMENTALES | B11: 6 | C11: 13 | D11: 5 | E11: 27 | F11: 85
A12: PASOS PEATONALES | B12: 3 | C12: 6 | D12: 0 | E12: 3 | F12: 5
A13: PATRULLAJES | B13: 4 | C13: 9 | D13: 4 | E13: 67 | F13: 50
A14: PERIFÉRICOS | B14: 1 | C14: 2 | D14: 0 | E14: 5 | F14: 10
A15: RECORRIDOS DE PROXIMIDAD | B15: 1 | C15: 2 | D15: 0 | E15: 2 | F15: 10
... A18: Suma total | B18: 36 | C18: 70 | D18: 21 | E18: 214 | F18: 921

Sheet LA_PIEDAD_RP
A3: ACTIVIDAD | B3: Cuenta de ACTIVIDAD | C3: Suma de Numero de Agentes Participantes: | D3: Suma de Cantidad de Unidades Oficiales de Seguridad Vial: | E3: Suma de Kilómetros recorridos. | F3: Suma de Cantidad de Personas alcanzadas.
A4: ACOMPAÑAMIENTO A CARAVANAS U OTROS | B4: 1 | C4: 2 | D4: 0 | E4: 10 | F4: 70
A5: AVENIDAS | B5: 3 | C5: 7 | D5: 3 | E5: 36 | F5: 0
A6: CONCIENTIZACIÓN Y PREVENCIÓN | B6: 2 | C6: 6 | D6: 2 | E6: 18 | F6: 40
A7: ESCUELAS | B7: 6 | C7: 14 | D7: 3 | E7: 39 | F7: 90
A8: OFICINAS GUBERNAMENTALES | B8: 4 | C8: 8 | D8: 2 | E8: 19 | F8: 40
A9: PASOS PEATONALES | B9: 4 | C9: 9 | D9: 3 | E9: 19 | F9: 20
A10: PATRULLAJES | B10: 2 | C10: 4 | D10: 1 | E10: 23 | F10: 10
A11: PERIFÉRICOS | B11: 2 | C11: 4 | D11: 0 | E11: 24 | F11: 25
A12: REPARTICIÓN DE TRÍPTICOS | B12: 1 | C12: 1 | D12: 1 | E12: 15 | F12: 10
A13: Suma total | B13: 25 | C13: 55 | D13: 15 | E13: 203 | F13: 305

Sheet URUAPAN_RP
A3: ACTIVIDAD | B3: Cuenta de ACTIVIDAD | C3: Suma de Numero de Agentes Participantes: | D3: Suma de Cantidad de Unidades Oficiales de Seguridad Vial: | E3: Suma de Kilómetros recorridos. | F3: Suma de Cantidad de Personas alcanzadas.
A4: ACTOS DELICTIVOS | B4: 1 | C4: 1 | D4: 1 | E4: 30 | F4: 0
A5: ESCUELAS | B5: 7 | C5: 14 | D5: 7 | E5: 27 | F5: 1011
A6: GASOLINERAS | B6: 2 | C6: 2 | D6: 2 | E6: 10 | F6: 12
A7: OFICINAS GUBERNAMENTALES | B7: 2 | C7: 4 | D7: 2 | E7: 4 | F7: 12
A8: OTROS OPERATIVOS (Especificar en las novedades relevantes) | B8: 3 | C8: 4 | D8: 3 | E8: 20 | F8: 30
A9: PERIFÉRICOS | B9: 2 | C9: 2 | D9: 2 | E9: 12 | F9: 9
A10: Suma total | B10: 17 | C10: 27 | D10: 17 | E10: 103 | F10: 1074

Sheet APATZINGAN_RP
A3: ACTIVIDAD | B3: Cuenta de ACTIVIDAD | C3: Suma de Numero de Agentes Participantes: | D3: Suma de Cantidad de Unidades Oficiales de Seguridad Vial: | E3: Suma de Kilómetros recorridos. | F3: Suma de Cantidad de Personas alcanzadas.
A4: APOYO A LA VIALIDAD | B4: 1 | C4: 3 | D4: 2 | E4: 20 | F4: 0
A5: CONCIENTIZACIÓN USO DE CASCO | B5: 1 | C5: 1 | D5: 1 | E5: 1 | F5: 23
A6: CORTES DE CIRCULACIÓN | B6: 1 | C6: 1 | D6: 1 | E6: 20 | F6: 0
A7: ESCUELAS | B7: 6 | C7: 10 | D7: 6 | E7: 48 | F7: 0
A8: OFICINAS GUBERNAMENTALES | B8: 3 | C8: 5 | D8: 3 | E8: 16 | F8: 0
A9: PASOS PEATONALES | B9: 2 | C9: 2 | D9: 1 | E9: 1 | F9: 0
A10: PATRULLAJES | B10: 3 | C10: 5 | D10: 3 | E10: 44 | F10: 0
A11: RECORRIDOS DE PROXIMIDAD | B11: 1 | C11: 2 | D11: 1 | E11: 10 | F11: 45
A12: REPARTICIÓN DE TRÍPTICOS | B12: 2 | C12: 4 | D12: 3 | E12: 21 | F12: 90
A13: VÍAS FÉRREAS | B13: 1 | C13: 2 | D13: 1 | E13: 4 | F13: 0
A14: Suma total | B14: 21 | C14: 35 | D14: 22 | E14: 185 | F14: 158

Sheet HUETAMO_RP
A3: ACTIVIDAD | B3: Cuenta de ACTIVIDAD | C3: Suma de Numero de Agentes Participantes: | D3: Suma de Cantidad de Unidades Oficiales de Seguridad Vial: | E3: Suma de Kilómetros recorridos. | F3: Suma de Cantidad de Personas alcanzadas.
A4: APOYO A LA VIALIDAD | B4: 1 | C4: 2 | D4: 1 | E4: 1 | F4: 0
A5: BANCOS | B5: 3 | C5: 3 | D5: 1 | E5: 0 | F5: 77
A6: CONCIENTIZACIÓN USO DE CASCO | B6: 1 | C6: 2 | D6: 1 | E6: 2 | F6: 18
A7: CONCIENTIZACIÓN Y PREVENCIÓN | B7: 1 | C7: 2 | D7: 1 | E7: 2 | F7: 19
A8: CORTES DE CIRCULACIÓN | B8: 1 | C8: 2 | D8: 1 | E8: 2 | F8: 50
A9: ESCUELAS | B9: 4 | C9: 5 | D9: 1 | E9: 2 | F9: 93
A10: OFICINAS GUBERNAMENTALES | B10: 4 | C10: 5 | D10: 2 | E10: 1 | F10: 22
A11: PASOS PEATONALES | B11: 2 | C11: 2 | D11: 0 | E11: 0 | F11: 8
A12: RECORRIDOS DE PROXIMIDAD | B12: 1 | C12: 2 | D12: 1 | E12: 40 | F12: 20
A13: Suma total | B13: 18 | C13: 25 | D13: 9 | E13: 50 | F13: 307

Sheet COALCOMAN_RP
A3: ACTIVIDAD | B3: Cuenta de ACTIVIDAD | C3: Suma de Numero de Agentes Participantes: | D3: Suma de Cantidad de Unidades Oficiales de Seguridad Vial: | E3: Suma de Kilómetros recorridos. | F3: Suma de Cantidad de Personas alcanzadas.
A4: ESCUELAS | B4: 5 | C4: 5 | D4: 3 | E4: 13 | F4: 0
A5: OFICINAS GUBERNAMENTALES | B5: 1 | C5: 1 | D5: 0 | E5: 0 | F5: 0
A6: PATRULLAJES | B6: 2 | C6: 3 | D6: 2 | E6: 57 | F6: 0
A7: RECORRIDOS DE PROXIMIDAD | B7: 1 | C7: 2 | D7: 0 | E7: 0 | F7: 19
A8: Suma total | B8: 9 | C8: 11 | D8: 5 | E8: 70 | F8: 19

Sheet ZITACUARO_RP
A3: ACTIVIDAD | B3: Cuenta de ACTIVIDAD | C3: Suma de Numero de Agentes Participantes: | D3: Suma de Cantidad de Unidades Oficiales de Seguridad Vial: | E3: Suma de Kilómetros recorridos. | F3: Suma de Cantidad de Personas alcanzadas.
A4: AMPLIACION CARRETERA CIUIDAD HIDALGO-ZITACUARO | B4: 2 | C4: 8 | D4: 2 | E4: 34 | F4: 0
A5: APOYO A EVENTOS RELIGIOSOS | B5: 1 | C5: 1 | D5: 0 | E5: 0 | F5: 0
A6: CONCIENTIZACIÓN USO DE CASCO | B6: 1 | C6: 4 | D6: 1 | E6: 6 | F6: 32
A7: CONCIENTIZACIÓN Y PREVENCIÓN | B7: 1 | C7: 4 | D7: 1 | E7: 8 | F7: 27
A8: CORTES DE CIRCULACIÓN | B8: 1 | C8: 4 | D8: 1 | E8: 8 | F8: 50
A9: ESCUELAS | B9: 10 | C9: 25 | D9: 8 | E9: 87 | F9: 172
A10: OBRAS PÚBLICAS | B10: 1 | C10: 3 | D10: 1 | E10: 18 | F10: 0
A11: OFICINAS GUBERNAMENTALES | B11: 7 | C11: 18 | D11: 8 | E11: 68 | F11: 30
A12: PATRULLAJES | B12: 5 | C12: 17 | D12: 5 | E12: 105 | F12: 15
A13: PERIFÉRICOS | B13: 2 | C13: 2 | D13: 2 | E13: 18 | F13: 0
A14: RECORRIDOS DE PROXIMIDAD | B14: 3 | C14: 11 | D14: 3 | E14: 32 | F14: 50
A15: REPARTICIÓN DE TRÍPTICOS | B15: 2 | C15: 8 | D15: 2 | E15: 15 | F15: 52
... A17: Suma total | B17: 37 | C17: 110 | D17: 35 | E17: 408 | F17: 428

Sheet LAZARO_CARDENAS_RP
A3: ACTIVIDAD | B3: Cuenta de ACTIVIDAD | C3: Suma de Numero de Agentes Participantes: | D3: Suma de Cantidad de Unidades Oficiales de Seguridad Vial: | E3: Suma de Kilómetros recorridos. | F3: Suma de Cantidad de Personas alcanzadas.
A4: BASES DE OPERACIONES INTERINSTITUCIONAL | B4: 2 | C4: 2 | D4: 2 | E4: 12 | F4: 35
A5: CONCIENTIZACIÓN USO DE CASCO | B5: 1 | C5: 2 | D5: 1 | E5: 15 | F5: 20
A6: CONCIENTIZACIÓN Y PREVENCIÓN | B6: 2 | C6: 4 | D6: 2 | E6: 15 | F6: 26
A7: ESCUELAS | B7: 7 | C7: 10 | D7: 20 | E7: 251 | F7: 470
A8: OFICINAS GUBERNAMENTALES | B8: 1 | C8: 1 | D8: 1 | E8: 15 | F8: 20
A9: PASOS PEATONALES | B9: 1 | C9: 1 | D9: 1 | E9: 1 | F9: 50
A10: PATRULLAJES | B10: 2 | C10: 3 | D10: 2 | E10: 17 | F10: 20
A11: Suma total | B11: 16 | C11: 23 | D11: 29 | E11: 326 | F11: 641

Sheet UNIFICADA
A1: ID_Folio | B1: Folio | C1: Region y Delegación. | D1: ACTIVIDAD | E1: Fecha: | F1: Hora: | G1: GPS | H1: Dirección o Referencia de la Ubicación: | I1: Tarjeta informativa (WhatsApp) | J1: Foto 1/2 | K1: Foto 2/2 | L1: Cantidad de Personas alcanzadas. | M1: Numero de Agentes Participantes: | N1: Nombre de Los Agentes de Seguridad Vial Participantes: | O1: Cantidad de Unidades Oficiales de Seguridad Vial: | P1: Numero Económico de las Unidades Participantes. | Q1: Kilómetros recorridos. | R1: User_ID | S1: REGIÓN | T1: TIPO DE REPORTE
A2: ac3870b2 | B2: ac3870b2 | C2: HUETAMO - NOCUPETARO | D2: RECORRIDOS DE PROXIMIDAD | E2: 46128 | F2: 0.73659722 | I2: *Guardia Civil* *Agrupamiento de Seguridad Vial* *Region Huetamo* *Delegación No. 50 Nocupetaro* *Jueves 16 de Abril de 2026* *Asunto: Recorrido en Disuasión del Delito ( Carreteras Seguras)* *17:30 horas* Para conocimiento del mando superior me permito informar que se continúa con los Recorridos sobre las carreteras estatales y vías Públicas dentro de esta jurisdicción haciendo acto de presencia y dando seguridad Vial a los Automovilistas y peatones ,sin novedad relevante hasta el momento. Informa la Unidad 04-350 (prestada del municipio) a cargo de los oficiales : Gustavo Calderón Gordillo y Reynaldo Mendez Ortega Reporto .Cmte. Jose Carmen Mondragón Posadas Encargado, de la Delegación de Seguridad Vial de Nocupetaro | J2: PROXIMIDAD SOCIAL_Images/ac3870b2.Foto 1-2.234138.jpg | K2: PROXIMIDAD SOCIAL_Images/ac3870b2.Foto 2-2.234138.jpg | L2: 20 | M2: 2 | O2: 1 | P2: 0 | Q2: 40 | R2: NOCUPETARO | S2: HUETAMO | T2: PROXIMIDAD SOCIAL
A3: 2f28bc3f | B3: 2f28bc3f | C3: COALCOMAN - COALCOMAN | D3: RECORRIDOS DE PROXIMIDAD | E3: 46128 | F3: 0.81030093 | I3: *Guardia Civil* *Unidad dé Delegaciones* *Región Coalcoman* *Delegación 030 Coalcoman* *Jueves 16 de abril del 2026. 19:25 horas. *Asunto:* Proximidad social. Me permito informar a mi superioridad, que el personal de está delegación de seguridad vial, nos encontramos realizando la proximidad Social entre la sociedad en la zona centro. Personas alcanzadas 19 *Elementos participantes* 1.- Leonardo Rolón Meraz (responsable) 2-.Sergio Suárez Jiménez. *Pie tierra* Lo que me permito informar . Respetuosamente. Integrante de la Coordinación de Seguridad Vial Estatal delegación Coalcoman 030 región Coalcoman Cmte. Leonardo Rolón Meraz. | J3: PROXIMIDAD SOCIAL_Images/2f28bc3f.Foto 1-2.012921.jpg | K3: PROXIMIDAD SOCIAL_Images/2f28bc3f.Foto 2-2.012921.jpg | L3: 19 | M3: 2 | N3: Leonardo Rolon Meraz (Responsable) Y Sérgio Suárez Jiménez. | O3: 0 | P3: 0 | Q3: 0 | R3: 11 | S3: COALCOMAN | T3: PROXIMIDAD SOCIAL
A4: e4fab872 | B4: e4fab872 | C4: JIQUILPAN - VENUSTIANO CARRANZA | D4: RECORRIDOS DE PROXIMIDAD | E4: 46128 | F4: 0.83016204 | I4: *G U A R D I A C I V I L* *COORDINACIÓN DEL AGRUPAMIENTO DE SEGURIDAD VIAL* *UNIDAD DE DELEGACIONES* *REGIÓN JIQUILPAN* *DELEGACIÓN 53 VENUSTIANO CARRANZA* *JUEVES 16 DE ABRIL DEL 2026* *18:00 HORAS* *Asunto:* Proximidad social Se informa que se realizan recorridos de Proximidad social en la cabecera municipal del municipio de venustiano Carranza *Unidad:* 04-181 *Kilómetros:* 10 Es lo que me permito a usted informar para su superior conocimiento quedando *sin novedad*. Reporta el encargado de la Delegación Jose de Jesús Alvarez Fernández de la coordinación del Agrupamiento de Seguridad Vial. | J4: PROXIMIDAD SOCIAL_Images/e4fab872.Foto 1-2.015633.jpg | K4: PROXIMIDAD SOCIAL_Images/e4fab872.Foto 2-2.015633.jpg | L4: 15 | M4: 2 | O4: 1 | P4: 0 | Q4: 15 | R4: 45 | S4: JIQUILPAN | T4: PROXIMIDAD SOCIAL
A5: 1e46b96d | B5: 1e46b96d | C5: ZITACUARO - ZITACUARO | D5: RECORRIDOS DE PROXIMIDAD | E5: 46128 | F5: 0.84559028 | I5: G U A R D I A C I V I L COORDINACIÓN DEL AGRUPAMIENTO DE SEGURIDAD VIAL UNIDAD DE DELEGACIONES REGIÓN ZITACUARO DELEGACIÓN 10 ZITÁCUARO JUEVES 16 DE MARZO DE 2026 Asunto: Proximidad social. Por medio de la presente se informa que se continúa con la campaña de Proximidad Social con el Tema Trabajando Unidos para proteger la integridad de todas y todos, donde se realizan recorridos de prevencion del delito en plazas y centros comerciales de prevención, los cuales se llevan a cabo sin novedad. Personas concientizadas (20) A cargo Diana Marín Colín Elementos de apoyo Lázaro Bernal Marín Marisol Hernández Vieyra Luis Alonso Jerónimo Enoc Martínez Rogel Unidad: 19-3978 Kilometros: 6 Reporta el encargado de la Delegación 10 Zitácuaro de la Coordinación del Agrupamiento de Seguridad Vial. Cmte. José María Mendoza Farías. | J5: PROXIMIDAD SOCIAL_Images/1e46b96d.Foto 1-2.021951.jpg | K5: PROXIMIDAD SOCIAL_Images/1e46b96d.Foto 2-2.021951.jpg | L5: 20 | M5: 5 | O5: 1 | P5: 0 | Q5: 6 | R5: 35 | S5: ZITACUARO | T5: PROXIMIDAD SOCIAL
A6: 212ecbed | B6: 212ecbed | C6: ZAMORA - ECUANDUREO | D6: RECORRIDOS DE PROXIMIDAD | E6: 46128 | F6: 0.96090278 | I6: G U A R D I A C I V I L COORDINACIÓN DEL AGRUPAMIENTO DE SEGURIDAD VIAL UNIDAD DE DELEGACIONES REGIÓN ZAMORA DELEGACIÓN ECUANDUREO JUEVES 16 DE ABRIL DE 2026 15:00 HORAS Asunto: Recorridos de Proximidad Social Por medio de la presente se informa a la superioridad que se dan Recorridos de Vigilancia en las Tiendas con la finalidad de dar Presencia y fomentar la proximidad social y prevenir el delito Informa Miguel Ramírez Julián y Marco Antonio Félix Flores de la Delegación de Seguridad Vial Ecuandureo Reporta el encargado de la Delegación Miguel Ramírez Julián de la coordinación del Agrupamiento de Seguridad Vial | J6: PROXIMIDAD SOCIAL_Images/212ecbed.Foto 1-2.050416.jpg | K6: PROXIMIDAD SOCIAL_Images/212ecbed.Foto 2-2.050416.jpg | L6: 10 | M6: 2 | O6: 0 | P6: 0 | Q6: 2 | R6: 31 | S6: ZAMORA | T6: PROXIMIDAD SOCIAL
A7: da388de7 | B7: da388de7 | C7: APATZINGAN - APATZINGAN | D7: RECORRIDOS DE PROXIMIDAD | E7: 46129 | F7: 0.39748843 | I7: *G U A R D I A C I V I L* *COORDINACIÓN DEL AGRUPAMIENTO DE SEGURIDAD VIAL* *UNIDAD DE DELEGACIONES* *REGIÓN APATZINGÁN* *DELEGACIÓN 07 APATZINGÁN* *Viernes 17 DE ABRIL DEL 2026* *Asunto:* Proximidad social *09:30 HORAS* *Coordenadas:* 19.086585,-102.354554 Por medio de la presente me permito Informar a usted que esta delegación de seguridad vial continúa con las actividades de próximidad social en los establecimientos y negocios de esta ciudad, haciéndoles del conocimiento los números de emergencia. *Elementos de la delegación* Unidades 24-7682 01.- Policía Raúl Dimas Nava 02.- Policía Griselda Wences Reporta el encargado de la Delegación Apatzingán de la coordinación del Agrupamiento de Seguridad Vial Cmte. Julio Duvalier Hernández De la Cruz. | J7: PROXIMIDAD SOCIAL_Images/da388de7.Foto 1-2.153307.jpg | K7: PROXIMIDAD SOCIAL_Images/da388de7.Foto 2-2.153307.jpg | L7: 45 | M7: 2 | O7: 1 | P7: 0 | Q7: 10 | R7: 13 | S7: APATZINGAN | T7: PROXIMIDAD SOCIAL
A8: bf7d7511 | B8: bf7d7511 | C8: ZITACUARO - ZITACUARO | D8: RECORRIDOS DE PROXIMIDAD | E8: 46129 | F8: 0.45701389 | I8: G U A R D I A C I V I L COORDINACIÓN DEL AGRUPAMIENTO DE SEGURIDAD VIAL UNIDAD DE DELEGACIONES REGIÓN ZITACUARO DELEGACIÓN 10 ZITÁCUARO VIERNES 17 DE MARZO DE 2026 Asunto: Proximidad social. Por medio de la presente se informa que se continúa con la campaña de Proximidad Social con el Tema Trabajando Unidos para proteger la integridad de todas y todos, donde se realizan recorridos de prevencion del delito en plazas y centros comerciales de prevención, los cuales se llevan a cabo sin novedad. Personas concientizadas (20) A cargo Marisol Hernández Vieyra Elemento de apoyo Lázaro Bernal Marin Luis Alonso Jerónimo Enoc Martínez Rogel Unidad: 19-3978 Kilometros: 6 Reporta el encargado de la Delegación 10 Zitácuaro de la Coordinación del Agrupamiento de Seguridad Vial. Cmte. José María Mendoza Farias | J8: PROXIMIDAD SOCIAL_Images/bf7d7511.Foto 1-2.165950.jpg | K8: PROXIMIDAD SOCIAL_Images/bf7d7511.Foto 2-2.165950.jpg | L8: 20 | M8: 4 | O8: 1 | P8: 0 | Q8: 6 | R8: 35 | S8: ZITACUARO | T8: PROXIMIDAD SOCIAL
A9: be085393 | B9: be085393 | C9: ZITACUARO - CIUDAD HIDALGO | D9: RECORRIDOS DE PROXIMIDAD | E9: 46129 | F9: 0.55762731 | I9: GUARDIA CIVIL COORDINACIÓN DEL AGRUPAMIENTO DE SEGURIDAD VIAL UNIDAD DE DELEGACIONES REGIÓN ZITÁCUARO DELEGACIÓN 09 CIUDAD HIDALGO VIERNES 17 DE ABRIL DE 2026 13:15 HORAS Asunto: Proximidad social. Para conocimiento de los mandos, se informa que se continúa con la campaña de proximidad social con el tema “Trabajando unidos para proteger la integridad de todas y todos”, realizando recorridos de prevención del delito en plazas y comercios de la zona centro de este municipio.Seguridad Vial de Ciudad Hidalgo lleva a cabo dichas actividades sin novedad. A cargo de los agentes de Seguridad Vial: el suscrito y Paulina Viridiana Mondragón Alanis. a bordo de la unidad 03-641 Kilometraje recorrido: 20 Personas alcanzadas: 10 Reporta el encargado de la delegación:Cmdte. Jesús Benito Vázquez Chávez, de la Coordinación del Agrupamiento de Seguridad Vial. | J9: PROXIMIDAD SOCIAL_Images/be085393.Foto 1-2.195538.jpg | K9: PROXIMIDAD SOCIAL_Images/be085393.Foto 2-2.195538.jpg | L9: 10 | M9: 2 | O9: 1 | P9: 0 | Q9: 20 | R9: 38 | S9: ZITACUARO | T9: PROXIMIDAD SOCIAL
A10: f0171461 | B10: f0171461 | C10: MORELIA - ACUITZIO DEL CANJE | D10: RECORRIDOS DE PROXIMIDAD | E10: 46129 | F10: 0.61744213 | I10: GUARDIA CIVIL COORDINACIÓN DE AGRUPAMIENTOS DE SEGURIDAD VIAL UNIDAD DE DELEGACIONES DELEGACION 043 ACUITZIO DEL CANJE VIERNES 17 DE ABRIL DE 2026 14:00 HORAS TARJETA INFORMATIVA ASUNTO: RECORRIDO EN CARRETERAS Por medio de la presente informo que a bordo de la CRP 23-0923 se dan recorridos de seguridad y vigilancia en la Carretera- Pátzcuaro Morelia kilometro 26+000 se encuentra sin novedad 25 km recorridos Reporta el encargado de la Delegación 043 Acuitzio del Canje Pol. Primero Roberto Carlos Duarte Báez de la Coordinación del Agrupamiento de Seguridad Vial. | J10: PROXIMIDAD SOCIAL_Images/f0171461.Foto 1-2.205044.jpg | K10: PROXIMIDAD SOCIAL_Images/f0171461.Foto 2-2.205044.jpg | L10: 0 | M10: 1 | O10: 1 | P10: 0 | Q10: 25 | R10: 23 | S10: MORELIA | T10: PROXIMIDAD SOCIAL
A11: 6a52176c | B11: 6a52176c | C11: LAZARO CARDENAS - ARTEAGA | D11: CONCIENTIZACIÓN Y PREVENCIÓN | E11: 46128 | F11: 0.74136574 | G11: RESPETA LOS LIMITES DE VELOCIDAD | I11: *Actividades* 14-04-2026 Se implementa el dispositivo vial *escuela segura* a la entrada y salida de los diferentes centros educativos de esta cabecera Mpal. * *Sin noveda* Se realizan recorridos dentro y fuera de la población en la unidad 04-153 con la finalidad de prevenir hechos de tránsito,prevención del delito y asistencia a la ciudadanía. *Sin novedad* Se monitorean oficinas gubernamentales como son: *Presidencia Municipal *Administración de Rentas *Registro Civil *Juzgado Mixto de primera instancia *Laborando sin novedad* Se entregan Trípticos de información para concientización y prevencion de hechos de tránsito con la leyenda *por tu seguridad y la de todos* Se realizan recorridos nocturnos en la unidad 04-153 para la prevención y disuasión de algun hecho delictivo sobre las diferentes calles y avenidas de la poblacion. *Sin novedad* | J11: CAMPAÑAS_Images/6a52176c.Foto 1-2.234910.jpg | K11: CAMPAÑAS_Images/6a52176c.Foto 2-2.234910.jpg | L11: 6 | M11: 2 | O11: 1 | P11: 0 | Q11: 0 | R11: 10 | S11: LAZARO CARDENAS | T11: CAMPAÑAS
A12: cca42424 | B12: cca42424 | C12: JIQUILPAN - JIQUILPAN | D12: CONCIENTIZACIÓN Y PREVENCIÓN | E12: 46128 | F12: 0.75353009 | G12: USO DE CASCO | I12: *G U A R D I A C I V I L* *COORDINACIÓN DEL AGRUPAMIENTO DE SEGURIDAD VIAL* *UNIDAD DE DELEGACIONES* *REGIÓN JIQUILPAN* *DELEGACIÓN 05 JIQUILPAN* *JUEVES 16 DE ABRIL DEL 2026* *17:50 HORAS* Asunto: Campaña de concientización de uso de casco Se informa a la superioridad que se realizó dispositivo de *concientización y sensibilización para el uso de casco* sobre la carretera Jiquilpan-Sahuayo a la altura del entronque con la avenida Universidad. Asi mismo quedamos pendientes para informar cualquier novedad de relevancia. Se realiza la función en la Unidad 03-600, a cargo del oficial Luis Alejandro Gomez Vilchis, con 02 elementos más. Reporta el Encargado de la Delegación, Jesús Manuel Martínez Ochoa, de la Coordinación del Agrupamiento de Seguridad Vial | J12: CAMPAÑAS_Images/cca42424.Foto 1-2.000556.jpg | K12: CAMPAÑAS_Images/cca42424.Foto 2-2.000556.jpg | L12: 25 | M12: 3 | O12: 1 | P12: 0 | Q12: 0 | R12: 41 | S12: JIQUILPAN | T12: CAMPAÑAS
A13: 84fc5dbc | B13: 84fc5dbc | C13: HUETAMO - NOCUPETARO | D13: CONCIENTIZACIÓN Y PREVENCIÓN | E13: 46128 | F13: 0.7825 | G13: UTILIZA EL CINTURON DE SEGURIDAD | I13: Guardia Civil Seguridad Vial Región Huetamo Delegación 50 Nocupetaro Asunto: Campaña de Concientización Jueves 16/04/2026 18:10 horas Para conocimiento de la superioridad, se informa que se realiza entrega de trípticos alusivos a los automovilistas, con los temas de, Uso del cinturón de seguridad esto con la finalidad de concientizar a los conductores y prevenir hechos de transito con resultados fatales. Personas alcanzadas 16 Informa unidad 04-350 a cargo del oficial Gustavo Calderón Gordillo.y Reynaldo Méndez Ortega Reportó el Cmte. Jose Carmen Mondragon Posadas Encargado de la Delegacion de Seguridad Vial Estatal Nocupetaro. | J13: CAMPAÑAS_Images/84fc5dbc.Foto 1-2.004757.jpg | K13: CAMPAÑAS_Images/84fc5dbc.Foto 2-2.004757.jpg | L13: 19 | M13: 2 | O13: 1 | P13: 0 | Q13: 2 | R13: NOCUPETARO | S13: HUETAMO | T13: CAMPAÑAS
A14: 7967502e | B14: 7967502e | C14: APATZINGAN - GABRIEL ZAMORA | D14: REPARTICIÓN DE TRÍPTICOS | E14: 46128 | F14: 0.81167824 | G14: UTILIZA EL CINTURON DE SEGURIDAD | I14: *G U A R D I A C I V I L* *COORDINACIÓN DEL AGRUPAMIENTO DE SEGURIDAD VIAL* *UNIDAD DE DELEGACIONES* *REGION APATZINGAN* *DELEGACIÓN 40 GABRIEL ZAMORA* *JUEVES 16 DE ABRIL DEL 2026.* *13:30 horas* *Asunto*:Campaña *Conductor Responsable* Guardia Civil "Seguridad Vial" Informa que se inicia con la campaña concientización para los conductores haciendo las recomendaciones pertinentes para la prevencion de accidentes, sobre la importancia del uso del cinturon de seguridad, respetar los límites de velocidad, evitar el uso de celular mientras maneja, y evitar conducir en estado de ebriedad ya que de ello depende la seguridad de los pasajeros abordo del vehículo. En el lugar Samantha Estela Ruiz Soto Reporta el Encargado de la delegación No. 40 Gabriel Zamora, Julio Cesar Silva Mendoza de la coordinación del agrupamiento de seguridad vial. | J14: CAMPAÑAS_Images/7967502e.Foto 1-2.013013.jpg | K14: CAMPAÑAS_Images/7967502e.Foto 2-2.013013.jpg | L14: 20 | M14: 1 | O14: 1 | P14: 0 | Q14: 1 | R14: 15 | S14: APATZINGAN | T14: CAMPAÑAS
A15: ac064af3 | B15: ac064af3 | C15: APATZINGAN - APATZINGAN | D15: REPARTICIÓN DE TRÍPTICOS | E15: 46129 | F15: 0.45305556 | G15: USO DE CASCO | I15: *G U A R D I A C I V I L* *COORDINACIÓN DEL AGRUPAMIENTO DE SEGURIDAD VIAL* *UNIDAD DE DELEGACIONES* *REGIÓN APATZINGÁN* *DELEGACIÓN APATZINGÁN* *VIERNES 17 DE ABRIL DE 2026* *10:40 HORAS* *Asunto:* Entrega de trípticos y perifoneo (Motociclista Responsable) Por medio de la presente me permito Informar a usted que esta delegación de seguridad vial, informa que se continúa con la campaña preventiva *Motociclista responsable utiliza el casco, no moto sardina* para la concientización, la regularización y prevención de accidentes en motocicleta, Sobre la Av. Constitución de esta ciudad, con la entrega de volantes alusivos y perifoneo. *Reporta* Unidades 24-7682, 04-157 01.- Policía Angel David Alejandre Tejeda 02.- Policía Adrian Alejandro Valle Vázquez 03.- Policía Raul Dimas Nava Reporta el encargado de la Delegación de Apatzingán de la coordinación del Agrupamiento de Seguridad Vial Julio Duvalier Hernández de la Cruz | J15: CAMPAÑAS_Images/ac064af3.Foto 1-2.165325.jpg | K15: CAMPAÑAS_Images/ac064af3.Foto 2-2.165325.jpg | L15: 70 | M15: 3 | O15: 2 | P15: 0 | Q15: 20 | R15: 13 | S15: APATZINGAN | T15: CAMPAÑAS
A16: f8a66913 | B16: f8a66913 | C16: LA PIEDAD - LA PIEDAD | D16: CONCIENTIZACIÓN Y PREVENCIÓN | E16: 46129 | F16: 0.45951389 | G16: UTILIZA EL CINTURON DE SEGURIDAD | I16: *GUARDIA CIVIL* *COORDINACIÓN DEL AGRUPAMIENTO DE SEGURIDAD VIAL* *UNIDAD DE DELEGACIÓNES* *REGION LA PIEDAD* *DELEGACIÓN LA PIEDAD* *VIERNES 17 DE ABRIL DE 2026* *10:40 HORAS* *ASUNTO:* Campaña prevención y concientización Por medio de la presente me permito informar que se da cumplimiento a las órdenes giradas por la superioridad, se realiza proximidad social, realizando entrega de trípticos con la leyenda *Utiliza cinturón de Seguridad* esto con la finalidad de crear conciencia y dar a conocer un poco las obligaciones q tenemos como conductores. Informa la Unidad 3405 a cargo del Pol. Arturo Buenrostro Rodríguez de la Delegación de Seguridad Vial de La Piedad. Reporta el encargado de la Delegación Pol. 2° J. Jesús Arévalo León de la coordinación del Agrupamiento de Seguridad Vial. | J16: CAMPAÑAS_Images/f8a66913.Foto 1-2.170217.jpg | K16: CAMPAÑAS_Images/f8a66913.Foto 2-2.170217.jpg | L16: 19 | M16: 3 | O16: 1 | P16: 0 | Q16: 10 | R16: 4 | S16: LA PIEDAD | T16: CAMPAÑAS
A17: 9680fcf2 | B17: 9680fcf2 | C17: ZITACUARO - ZITACUARO | D17: REPARTICIÓN DE TRÍPTICOS | E17: 46129 | F17: 0.47765046 | G17: UTILIZA EL CINTURON DE SEGURIDAD | I17: G U A R D I A C I V I L COORDINACIÓN DEL AGRUPAMIENTO DE SEGURIDAD VIAL UNIDAD DE DELEGACIONES REGIÓN ZITACUARO DELEGACIÓN 10 ZITÁCUARO MIÉRCOLES 17 DE ABRIL DEL 2026 Asunto: Reparticion de trípticos. Me permito informar para su superior conocimiento, se realiza el Operativo de prevención de hechos de tránsito entregando trípticos con las recomendaciones "USO OBLIGATORIO DEL CINTURÓN DE SEGURIDAD Y RECOMENDACIONES DE SEGURIDAD VIAL" en las vías públicas. Sin novedad. USO DEL CINTURON DE SEGURIDAD Personas concientizadas (20) A cargo: Marisol Hernández Vieyra Elementos de apoyo: Lázaro Bernal Marin Enoc Martinez rogel Juan Alonso Jeronimo Unidad: 3180 Kilómetro: 9. Reporta el encargado de la Delegación 10 Zitácuaro de la coordinación de agrupamiento de Seguridad Vial. Cmte. José María Mendoza Farías. | J17: CAMPAÑAS_Images/9680fcf2.Foto 1-2.172855.jpg | K17: CAMPAÑAS_Images/9680fcf2.Foto 2-2.172855.jpg | L17: 20 | M17: 4 | O17: 1 | P17: 0 | Q17: 9 | R17: 35 | S17: ZITACUARO | T17: CAMPAÑAS
A18: d09f8588 | B18: d09f8588 | C18: ZITACUARO - ZITACUARO | D18: REPARTICIÓN DE TRÍPTICOS | E18: 46129 | F18: 0.47888889 | G18: USO DE CASCO | I18: G U A R D I A C I V I L COORDINACIÓN DEL AGRUPAMIENTO DE SEGURIDAD VIAL UNIDAD DE DELEGACIONES REGIÓN ZITÁCUARO DELEGACIÓN 10 ZITÁCUARO VIERNES 17 ABRIL DEL 2026 Asunto: Repartición de trípticos. Me permito informar para su superior conocimiento, se realiza el Operativo de prevención de hechos de tránsito entregando trípticos con las recomendaciones "USO OBLIGATORIO DEL CASCO Y RECOMENDACIONES DE SEGURIDAD VIAL" en las vías públicas. Sin novedad. USO DEL CASCO Personas concientizadas (32) A cargo: Marisol Hernández Vieyra Elementos de apoyo: Lázaro Bernal Marin Enoc Martínez Rogel Juan Alonso Jerónimo Unidad: 19-3978 Kilómetros: 6. Reporta el Encargado de la Delegación 10 Zitácuaro de la Coordinación del Agrupamiento de Seguridad Vial. Cmte. José María Mendoza Farías. | J18: CAMPAÑAS_Images/d09f8588.Foto 1-2.173037.jpg | K18: CAMPAÑAS_Images/d09f8588.Foto 2-2.173037.jpg | L18: 32 | M18: 4 | O18: 1 | P18: 0 | Q18: 6 | R18: 35 | S18: ZITACUARO | T18: CAMPAÑAS
A19: 90e5775d | B19: 90e5775d | C19: LAZARO CARDENAS - ARTEAGA | D19: CONCIENTIZACIÓN Y PREVENCIÓN | E19: 46129 | F19: 0.47912037 | G19: RESPETA LOS LIMITES DE VELOCIDAD | I19: *G U A R D I A C I V I L* *COORDINACION DEL AGRUPAMIENTO DE SEGURIDAD VIAL* *REGIÓN LÁZARO CÁRDENAS* *UNIDAD DE DELEGACIÓNES* *DELEGACIÓN 36 ARTEAGA* *VIERNES 17 DE ABRIL 2026* *Asunto:* *Campaña de Prevención de Accidentes.* 11:10 HORAS. Guardia civil "Seguridad Vial" informa que se continúa con la entrega de trípticos con la leyenda de **Recomendaciónes de Seguridad Vial**para la concientización y prevención de accidentes viales, en las principales calles, avenidas y tramos carreteros de este municipio. Reporta el Encargado de la Delegación 36 Arteaga C.Moises Zarco Cuevas de la Coordinación del Agrupamiento de Seguridad Vial | J19: CAMPAÑAS_Images/90e5775d.Foto 1-2.173119.jpg | K19: CAMPAÑAS_Images/90e5775d.Foto 2-2.173119.jpg | L19: 20 | M19: 2 | O19: 1 | P19: 0 | Q19: 15 | R19: 10 | S19: LAZARO CARDENAS | T19: CAMPAÑAS
A20: 0e5a22d5 | B20: 0e5a22d5 | C20: ZAMORA - ZAMORA | D20: CONCIENTIZACIÓN Y PREVENCIÓN | E20: 46129 | F20: 0.49508102 | G20: UTILIZA EL CINTURON DE SEGURIDAD | I20: GUARDIA CIVIL COORDINACION DEL AGRUPAMIENTO DE SEGURIDAD VIAL UNIDAD DE DELEGACIÓNES REGIÓN ZAMORA VIERNES 17 DE ABRIL DE 2026 ASUNTO: ENTREGA DE TRÍPTICOS 11: 15 horas Señor Coordinador, Señor Subdirector para su superior conocimiento me permito informar que continuamos dando cumplimiento a las órdenes superiores con la campaña de seguridad vial repartiendo trípticos a conductores de Vehiculos haciendo la recomendación del uso del Cinturón de seguridad prevenir accidentes o lesiones en las vías públicas. Pie tierra Elementos: 1.- Emiliano Manrriquez Velázquez 2 Juan Santos Toxtega Bustamante Reportó el encargado de la Delegación Cmte Alfredo Velázquez González. Coordinación del Agrupamiento De Seguridad Vial. | J20: CAMPAÑAS_Images/0e5a22d5.Foto 1-2.175439.jpg | K20: CAMPAÑAS_Images/0e5a22d5.Foto 2-2.175439.jpg | L20: 8 | M20: 2 | O20: 0 | P20: 0 | Q20: 1 | R20: 27 | S20: ZAMORA | T20: CAMPAÑAS
A21: 4275f84e | B21: 4275f84e | C21: ZITACUARO - ZITACUARO | D21: CONCIENTIZACIÓN Y PREVENCIÓN | E21: 46129 | F21: 0.49493056 | G21: RESPETA LOS LIMITES DE VELOCIDAD | I21: G U A R D I A C I V I L COORDINACIÓN DEL AGRUPAMIENTO DE SEGURIDAD VIAL UNIDAD DE DELEGACIONES REGIÓN ZITACUARO DELEGACIÓN 10 ZITÁCUARO MIÉRCOLES 17 DE ABRIL DEL 2026 ASUNTO: Recomendaciones a Conductores de "Servicio público" Por medio de la presente se informa que se les hace recomendaciones a los conductores de servicio público que conduzcan con responsabilidad, y a cumplir debidamente con su documentación y a pasajeros tomar medidas preventivas para evitar accidentes. Recomendaciones a pasajeros 1. Ir atentos a su recorrido. 2. Hacer uso de los números de emergencia (089 o 911) ante cualquier suceso. 3. Realizar ascenso y descenso en paradas establecidas. 4. Ir sentados correctamente Conductores de servicio público concientizados (27). Quedando pendientes y a la orden. A cargo Marisol Hernández Vieyra Elementos de apoyo: Lázaro Bernal Marín Enoc Martínez Rogel Juan Alonso Jerónimo *Unidad:*3180 Kilómetros: 8 Reporta el Encargado de la Delegación 10 Zitácuaro de la Coordinación del Agrupamiento de Seguridad Vial. Cmte. José María Mendoza Farías | J21: CAMPAÑAS_Images/4275f84e.Foto 1-2.175458.jpg | K21: CAMPAÑAS_Images/4275f84e.Foto 2-2.175458.jpg | L21: 27 | M21: 4 | O21: 1 | P21: 0 | Q21: 8 | R21: 35 | S21: ZITACUARO | T21: CAMPAÑAS
A22: cda523b0 | B22: cda523b0 | C22: LA PIEDAD - YURECUARO | D22: REPARTICIÓN DE TRÍPTICOS | E22: 46129 | F22: 0.50069444 | G22: RESPETA LOS LIMITES DE VELOCIDAD | I22: Guardia Civil Coordinación del agrupamiento de Seguridad Vial Unidad de delegaciones Delegación 21 Yurécuaro Fecha:. 17 de Abril del 2026 Hora: 11:00 hrs Asunto: Entrega de trípticos. Por medio de la presente me permito informar, se hace entrega de trípticos con la leyenda de Respeta los límites de velocidad esto con la finalidad de dar a conocer a la ciudadanía. Unidad 03-625 El Policía: Gustavo Saavedra Ramirez Informa el encargado de la delegación 21 Yurécuaro de seguridad vial Gustavo Saavedra Ramirez | J22: CAMPAÑAS_Images/cda523b0.Foto 1-2.180143.jpg | K22: CAMPAÑAS_Images/cda523b0.Foto 2-2.180143.jpg | L22: 10 | M22: 1 | O22: 1 | P22: 0 | Q22: 15 | R22: 6 | S22: LA PIEDAD | T22: CAMPAÑAS
A23: 532207ac | B23: 532207ac | C23: ZAMORA - ZAMORA | D23: CONCIENTIZACIÓN Y PREVENCIÓN | E23: 46129 | F23: 0.58478009 | G23: USO DE CASCO | I23: GUARDIA CIVIL COORDINACIÓN DEL AGRUPAMIENTO DE SEGURIDAD VIAL UNIDAD DE DELEGACIONES REGION ZAMORA VIERNES 17 DE ABRIL DEL 2026 14:00 HORAS Asunto: Motociclista Responsable uso del casco Guardia Civil "Seguridad Vial Estatal" informa que se continúa con la Campaña de las Consecuencias de No usar el Casco de Seguridad (en una Motocicleta), como puede ser la Gravedad de la Lesiones, Posibilidades de Muerte y a tiempo de Hospitalización .,los cuales se le hace concientización de lo hechos de Conducir Un Vehículo Birodante , por lo que se da de Conocimiento a la Superioridad de lo elaborado hacia la Ciudadanía por lo que al momento se encuentra sin Ninguna Novedad. Informa C. Emiliano manrriquez Velázquez con 01 más pie tierra Reporta el Encargado de la Delegación C. Alfredo Velázquez González de la Coordinación del Agrupamiento de Seguridad Vial. | J23: CAMPAÑAS_Images/532207ac.Foto 1-2.200344.jpg | K23: CAMPAÑAS_Images/532207ac.Foto 2-2.200344.jpg | L23: 8 | M23: 2 | O23: 0 | P23: 0 | Q23: 1 | R23: 27 | S23: ZAMORA | T23: CAMPAÑAS
A24: a60cdd1c | B24: a60cdd1c | C24: LA PIEDAD - LA PIEDAD | D24: CONCIENTIZACIÓN Y PREVENCIÓN | E24: 46129 | F24: 0.59512731 | G24: UTILIZA EL CINTURON DE SEGURIDAD | I24: GUARDIA CIVIL* *COORDINACIÓN DEL AGRUPAMIENTO DE SEGURIDAD VIAL* *UNIDAD DE DELEGACIÓNES* *REGION LA PIEDAD* *DELEGACIÓN LA PIEDAD* *VIERNES 17 DE ABRIL DE 2026* *14:30 HORAS* *ASUNTO:* Campaña prevención y concientización Por medio de la presente me permito informar que se da cumplimiento a las órdenes giradas por la superioridad, se realiza proximidad social, realizando entrega de trípticos con la leyenda *Utiliza cinturón de Seguridad* esto con la finalidad de crear conciencia y dar a conocer un poco las obligaciones q tenemos como conductores. Informa la Unidad 3405 a cargo del Pol. Arturo Buenrostro Rodríguez de la Delegación de Seguridad Vial de La Piedad. Reporta el encargado de la Delegación Pol. 2° J. Jesús Arévalo León de la coordinación del Agrupamiento de Seguridad Vial. | J24: CAMPAÑAS_Images/a60cdd1c.Foto 1-2.203245.jpg | K24: CAMPAÑAS_Images/a60cdd1c.Foto 2-2.203245.jpg | L24: 21 | M24: 3 | O24: 1 | P24: 0 | Q24: 8 | R24: 4 | S24: LA PIEDAD | T24: CAMPAÑAS
A25: b9747e9b | B25: b9747e9b | C25: ZAMORA - TANGANCICUARO | D25: TALLER EDUCACIÓN SEGURIDAD VIAL | E25: 46129 | F25: 0.7037037 | I25: *GUARDIA CIVIL* *COORDINACIÓN DEL AGRUPAMIENTO DE SEGURIDAD VIAL* *UNIDAD DE DELEGACIONES* *REGION ZAMORA* *DELEGACIÓN 23 TANGANCÍCUARO.* .VIERNES 17 DE ABRIL DEL 2026.* *HORA:* 15:30 *ASUNTO*: Plática de manejo a la defensiva de Seguridad Vial. Se informa para su superior conocimiento que se realiza una platica de *_Manejo a la Defensiva y educación vial_*, virtual y presencial a personal de la empresa del grupo Agricola el Cerezo, ubicada en Prolongación Jesús González Ortega, colonia Sector 1, en el municipio de tangancicuaro de arista Michoacán, con un aproximado de 50 personas, impartida por personal operativo y administrativo de esta delegación bajo mi cargo. Informan los agentes de seguridad víal: Isauro Hernández Noyola Jorge Alejandro González Melgarejo. *REPORTA* Encargado de la coordinación del agrupamiento de seguridad vial. *Cmte. Isauro Hernández Noyola.* | J25: CAPACITACIONES_Images/b9747e9b.Foto 1-2.225207.jpg | K25: CAPACITACIONES_Images/b9747e9b.Foto 2-2.225207.jpg | L25: 50 | M25: 2 | O25: 1 | P25: 0 | Q25: 2 | R25: 34 | S25: ZAMORA | T25: CAPACITACIONES
A26: deb83033 | B26: deb83033 | C26: HUETAMO - HUETAMO | D26: PASOS PEATONALES | E26: 46128 | F26: 0.70900463 | I26: *Guardia Civil * *Coordinación del Agrupamiento de Seguridad Vial* *Unidad de Delegaciones* *Región Huetamo* *Delegación 12 Huetamo* Jueves 16 de Abril del 2026* *Asunto:* Apoyo en el Paso peatonal en la zona centro. *17:00 Horas* Por medio de la presente se informa al mando que se realiza el apoyo del paso peatonal y la seguridad en zona centro con la finalidad de salvaguardar la integridad física de la ciudadanía y así evitar accidentes. Al momento todo sin novedad de relevancia continuamos pendientes y a la orden. Estado de Fuerza; PIE TIERRA 👮🏻‍♂️ Julián González Pineda. Informa el Oficial Julián González Pineda elemento de la Delegación Regional 12 de Seguridad Vial. Reportó Cmdte. Florencio Reynoso Gómez, Encargado de la Delegación regional 12 de Seguridad Vial. | J26: DISPOSITIVOS DE SEGURIDAD VIAL_Images/deb83033.Foto 1-2.231622.jpg | K26: DISPOSITIVOS DE SEGURIDAD VIAL_Images/deb83033.Foto 2-2.231622.jpg | L26: 4 | M26: 1 | O26: 0 | P26: 0 | Q26: 0 | R26: 16 | S26: HUETAMO | T26: DISPOSITIVOS DE SEGURIDAD VIAL
A27: 76ceda15 | B27: 76ceda15 | C27: LAZARO CARDENAS - LAZARO CARDENAS | D27: PASOS PEATONALES | E27: 46128 | F27: 0.73015046 | I27: G U A R D I A C I V I L COORDINACIÓN DEL AGRUPAMIENTO DE SEGURIDAD VIAL UNIDAD DE DELEGACIONES REGIÓN LAZARO CARDENAS DELEGACIÓN 17 LAZARO CÁRDENAS Jueves 16 de Abril del 2026 17:10 horas Asunto: Apoyo a peatones Por medio de la presente me permito informar a usted que con esta hora se brinda apoyo a peatones para prevenir hechos de tránsito en la avenidad LázaroCárdenas. Reporta el encargado de la Delegación Lazaro Cárdenas de la coordinación del Agrupamiento de Seguridad Vial Oficial Victor Omar Sedano Gómez | J27: DISPOSITIVOS DE SEGURIDAD VIAL_Images/76ceda15.Foto 1-2.233641.jpg | K27: DISPOSITIVOS DE SEGURIDAD VIAL_Images/76ceda15.Foto 2-2.233641.jpg | L27: 50 | M27: 1 | O27: 1 | P27: 0 | Q27: 1 | R27: 9 | S27: LAZARO CARDENAS | T27: DISPOSITIVOS DE SEGURIDAD VIAL
A28: 0f084060 | B28: 0f084060 | C28: COALCOMAN - COALCOMAN | D28: PATRULLAJES | E28: 46128 | F28: 0.74483796 | I28: *Guardia Civil* *Unidad Dé Delegaciones* *Región Coalcoman* *Delegación 030 Coalcoman* *Jueves 16 de abril del 2026.* 16:40 horas. *Asunto:* Carretera segura. Por medio de la presente me permito informar a mi superioridad, que el personal de está delegación de seguridad vial, nos encontramos realizando recorridos intinerantes de vigilancia sobre la carretera estatal Coalcoman-Tepalcatepec ( localidad piedras de lumbre), con la finalidad de evitar algún hecho delictivo, auxiliar a conductores en caso de falla mecánica y crear la confianza entre la sociedad *Elementos participantes* 1-.Leonardo Rolón Meraz.(Responsable) 2.- Sergio Suárez Jiménez. *Abordo de la unidad oficial 03-608* 24 - kilómetros. Terminando el recorrido.alas 17:50 horas, sin novedad. Lo que me permito informar Respetuosamente. Integrante de la coordinación de Seguridad Vial Estatal delegación 030 región Coalcoman Cmte. Leonardo Rolón Meraz. | J28: DISPOSITIVOS DE SEGURIDAD VIAL_Images/0f084060.Foto 1-2.235349.jpg | K28: DISPOSITIVOS DE SEGURIDAD VIAL_Images/0f084060.Foto 2-2.235349.jpg | L28: 0 | M28: 2 | O28: 1 | P28: 0 | Q28: 24 | R28: 11 | S28: COALCOMAN | T28: DISPOSITIVOS DE SEGURIDAD VIAL
A29: 3041aa5b | B29: 3041aa5b | C29: MORELIA - ZINAPECUARO | D29: PATRULLAJES | E29: 46128 | F29: 0.7902662 | I29: *G U A R D I A C I V I L* *COORDINACIÓN DEL AGRUPAMIENTO DE SEGURIDAD VIAL* *UNIDAD DE DELEGACIONES* *REGIÓN MORELIA* *DELEGACIÓN 016 ZINAPECUARO* *16/04/2026* *18:50 HORAS* *Asunto: Monitoreo de la autopista* *Ubicación:*Autopista de Occidente Méx-GDL Km 202+256, Plaza de Cobro de Zinapecuaro* *CRP 04374* 🟢 *LIBRE* (Circulación Libre Guardia Civil Seguridad Vial Zinapecuaro para conocimiento de la superioridad se informa que Continua fluyendo la circulación en ambos sentidos la caseta de peaje México Guadalajara y Guadalajara México hasta el momento sin novedad reportado sin novedad | J29: DISPOSITIVOS DE SEGURIDAD VIAL_Images/3041aa5b.Foto 1-2.005848.jpg | K29: DISPOSITIVOS DE SEGURIDAD VIAL_Images/3041aa5b.Foto 2-2.005848.jpg | L29: 0 | M29: 3 | O29: 1 | P29: 0 | Q29: 18 | R29: 20 | S29: MORELIA | T29: DISPOSITIVOS DE SEGURIDAD VIAL
A30: 2ca95bb1 | B30: 2ca95bb1 | C30: ZAMORA - ZAMORA | D30: PASOS PEATONALES | E30: 46128 | F30: 0.80765046 | I30: GUARDIA CIVIL COORDINACION DEL AGRUPAMIENTO DE SEGURIDAD VIAL UNIDAD DE DELEGACIÓNES REGION ZAMORA JUEVES 16 DE ABRIL DE 2026 ASUNTO: CRUCES PEATONALES 18 : 00 Horas Por medio del presente se informa. Que se realizan apoyos en cruces peatonales dando seguridad a las personas, deteniendo el paso vehicular y dando información a la ciudadanía, de la forma correcta en la que tienen que cruzar y ubicar estás zonas Peatonales para una mejor aplicación y cruce. Sin novedad hasta el momento Informa Policía de Seguridad Vial Emiliano Manriquez Velázquez con uno más, Pie tierra. Reportó el encargado de la Delegación Cmte: Alfredo Velázquez González. Coordinación del Agrupamiento de Seguridad Vial | J30: DISPOSITIVOS DE SEGURIDAD VIAL_Images/2ca95bb1.Foto 1-2.012355.jpg | K30: DISPOSITIVOS DE SEGURIDAD VIAL_Images/2ca95bb1.Foto 2-2.012355.jpg | L30: 0 | M30: 2 | O30: 0 | P30: 0 | Q30: 1 | R30: 27 | S30: ZAMORA | T30: DISPOSITIVOS DE SEGURIDAD VIAL
A31: 8c095784 | B31: 8c095784 | C31: APATZINGAN - GABRIEL ZAMORA | D31: PATRULLAJES | E31: 46128 | F31: 0.81377315 | I31: *GUARDIA CIVIL* *COORDINACIÓN DEL AGRUPAMIENTO DE SEGURIDAD VIAL* *UNIDAD DE DELEGACIONES* *REGIÓN APATZINGÁN* *DELEGACION GABRIEL ZAMORA* *ASUNTO: CARRETERAS SEGURAS* *FECHA: 16/04/2026* *HORA: 17:30 HRS* Por medio de la presente me permito informar a usted que continua los patrullajes en el marco de Carreteras seguras realizando recorridos de prevención, vigilancia y disuasión del delito implementado por la coordinación del agrupamiento de seguridad vial para auxiliar y resguardar la integridad a las familias , hasta el momento sin novedad. Ubicación Km 122 Carretera Federal libre Carapan- Playa azul UNIDAD : 3138 Julio Cesar Silva Mendoza *INFORMA* *JULIO CESAR SILVA MENDOZA, ENCARGADO DE LA DELEGACIÓN GABRIEL ZAMORA.* | J31: DISPOSITIVOS DE SEGURIDAD VIAL_Images/8c095784.Foto 1-2.013309.jpg | K31: DISPOSITIVOS DE SEGURIDAD VIAL_Images/8c095784.Foto 2-2.013309.jpg | L31: 0 | M31: 1 | O31: 1 | P31: 0 | Q31: 24 | R31: 15 | S31: APATZINGAN | T31: DISPOSITIVOS DE SEGURIDAD VIAL
A32: 9169fd00 | B32: 9169fd00 | C32: ZITACUARO - ZITACUARO | D32: PATRULLAJES | E32: 46128 | F32: 0.82685185 | I32: G U A R D I A C I V I L COORDINACIÓN DEL AGRUPAMIENTO DE SEGURIDAD VIAL UNIDAD DE DELEGACIONES REGIÓN ZITACUARO DELEGACIÓN 10 ZITÁCUARO JUEVES 16 DE ABRIL DEL 2026 Asunto: Recorrido de la Carretera Segura. Por medio de la presente Me permito informar que se continua con los Recorridos de patrullaje y vigilancia sobre las Carreteras Estatales y Vias Publicas; haciendo presencia y proporcionando Seguridad a la ciudadanía. El cual se lleva a cabo dentro del municipio de Zitácuaro Michoacán. CARRETERA (ZITACUARO-TOLUCA Y ZITÁCUARO-MORELIA) SIN NOVEDAD A cargo: Diana Marin Colin Elementos de apoyo: Lázaro Bernal Marin Marisol Hernández Vieyra Juan Alonso Jerónimo Enoc Martínez Rogel Unidad: 193978 Kilómetros: 20 Es lo que me permito a usted informar para su superior conocimiento quedando sin novedad. Reporta el encargado de la Delegación 10 Zitácuaro de la coordinación del Agrupamiento de Seguridad Vial. Cmte. José María Mendoza Farías. | J32: DISPOSITIVOS DE SEGURIDAD VIAL_Images/9169fd00.Foto 1-2.015135.jpg | K32: DISPOSITIVOS DE SEGURIDAD VIAL_Images/9169fd00.Foto 2-2.015135.jpg | L32: 0 | M32: 5 | O32: 1 | P32: 0 | Q32: 20 | R32: 35 | S32: ZITACUARO | T32: DISPOSITIVOS DE SEGURIDAD VIAL
A33: d3ddac70 | B33: d3ddac70 | C33: LAZARO CARDENAS - ARTEAGA | D33: PATRULLAJES | E33: 46128 | F33: 0.83633102 | I33: *G U A R D I A C I V I L* *COORDINACION DE AGRUPAMIENTO DE SEGURIDAD VIAL* *REGIÓN LÁZARO CÁRDENAS* *UNIDAD DE DELEGACIÓNES* *DELEGACIÓN 36 ARTEAGA* *JUEVES 16 DE ABRIL 2026* *20:00 hrs.* *Asunto*. Recorridos de Prevencion por medio del presente se informa a la superioridad que al momento se realizan recorridos de prevención y disuasión del delito por las diferentes carreteras, calles y avenidas de esta cabecera Municipal en la unidad 04-153 Sin novedad relevante. Reportó el Encargado de la Delegación 36 Arteaga C.Moises Zarco Cuevas de la Coordinación del Agrupamiento de seguridad vial | J33: DISPOSITIVOS DE SEGURIDAD VIAL_Images/d3ddac70.Foto 1-2.020743.jpg | K33: DISPOSITIVOS DE SEGURIDAD VIAL_Images/d3ddac70.Foto 2-2.020743.jpg | L33: 0 | M33: 1 | O33: 1 | P33: 0 | Q33: 2 | R33: 10 | S33: LAZARO CARDENAS | T33: DISPOSITIVOS DE SEGURIDAD VIAL
A34: b7f23275 | B34: b7f23275 | C34: ZAMORA - COENEO | D34: PATRULLAJES | E34: 46128 | F34: 0.84810185 | I34: *GUARDÍA CIVIL* *COORDINACIÓN DEL AGRUPAMIENTO DE SEGURIDAD VÍAL* *UNIDAD DE DELEGACIÓNES* *REGIÓN ZAMORA* *DELEGACIÓN 41 COENEO* *JUEVES 16 DE ABRIL DE 2026* *19:10 HORAS* *UBICACIÓN; COMANJA-HUANIQUEO* *ASUNTO: PATRULLAJES DE PREVENCIÓN* Por medio de la Presente se informa a la Superioridad que se realizan recorridos sobre las carreteras pertenecientes a esta encontrándose al momento sin novedad. *Informa la unidad 03-621* *Personas alcanzadas 50* *Km recorridos 10* *Reporta Encargado de La Delegación de Seguridad vial de Coeneo; Clemente Vázquez Ávalos.* | J34: DISPOSITIVOS DE SEGURIDAD VIAL_Images/b7f23275.Foto 1-2.022229.jpg | K34: DISPOSITIVOS DE SEGURIDAD VIAL_Images/b7f23275.Foto 2-2.022229.jpg | L34: 50 | M34: 2 | O34: 1 | P34: 0 | Q34: 10 | R34: 30 | S34: ZAMORA | T34: DISPOSITIVOS DE SEGURIDAD VIAL
A35: d5899086 | B35: d5899086 | C35: LA PIEDAD - LA PIEDAD | D35: PASOS PEATONALES | E35: 46128 | F35: 0.85770833 | I35: *GUARDIA CIVIL* *COORDINACIÓN DEL AGRUPAMIENTO DE SEGURIDAD VIAL* *UNIDAD DE DELEGACIÓNES* *REGION LA PIEDAD* *DELEGACIÓN LA PIEDAD* *JUEVES16 DE ABRIL DE 2026* *20:10 HORAS* *ASUNTO:* Cruces Peatonales Para conocimiento del Mando, me permito informar que se está implementando un programa de concientización a la ciudadanía sobre el cruce y seguridad peatonal, invitándolos a cruzar por las rayas peatonales o lugares señalados y marcados en las esquinas. Informa la Unidad 3405 a cargo del Pol. Arturo Buenrostro Rodríguez de la Delegación de Seguridad Vial de La Piedad. Reporta el encargado de la Delegación Pol. 2° J. Jesús Arévalo León de la coordinación del Agrupamiento de Seguridad Vial. | J35: DISPOSITIVOS DE SEGURIDAD VIAL_Images/d5899086.Foto 1-2.023638.jpg | K35: DISPOSITIVOS DE SEGURIDAD VIAL_Images/d5899086.Foto 2-2.023638.jpg | L35: 0 | M35: 2 | O35: 1 | P35: 0 | Q35: 6 | R35: 4 | S35: LA PIEDAD | T35: DISPOSITIVOS DE SEGURIDAD VIAL
A36: 4442e0a4 | B36: 4442e0a4 | C36: LA PIEDAD - VISTA HERMOSA | D36: PATRULLAJES | E36: 46128 | F36: 0.93482639 | I36: *Guardia Civil* *Coordinación Agrupamiento de Seguridad Vial* *Unidad de Delegaciones* *Región la Piedad* *Delegación 54 Vista Hermosa* *Jueves 16 De Abril 2026* *18:00 horas* *Asunto* Patrullajes en carreteras vecinales la Angostura y Capulin comunidades de Vista Hermosa. Para conocimiento de la Superioridad, me permito informar que se efectuaron patrullajes y vigilancia en tramos carreteros vecinales de las comunidades de este municipio de Vista Hermosa. Quedando al momento sin novedad de relevancia. *NOTA* Patrullaje Se Realiza Con La Unidad 019-79 de Tránsito Municipal A cargo de la Cmnte Denise Morales Con 1 Elemento Mas de Seguridad Vial. Reporta la encargada de la Delegación 54 Vista Hermosa de la Coordinacion del Agrupamiento de Seguridad Vial. Cmndte: Denise Azucena Morales Briseño | J36: DISPOSITIVOS DE SEGURIDAD VIAL_Images/4442e0a4.Foto 1-2.042652.jpg | K36: DISPOSITIVOS DE SEGURIDAD VIAL_Images/4442e0a4.Foto 2-2.042652.jpg | L36: 10 | M36: 2 | O36: 0 | P36: 0 | Q36: 10 | R36: 5 | S36: LA PIEDAD | T36: DISPOSITIVOS DE SEGURIDAD VIAL
... A51: 0d4e1724 | B51: 0d4e1724 | C51: MORELIA - SANTA CLARA | D51: APOYO A LA VIALIDAD | E51: 46129 | F51: 0.42840278 | I51: *G U A R D I A C I V I L* *COORDINACIÓN DEL AGRUPAMIENTO DE SEGURIDAD VIAL* *UNIDAD DE DELEGACIONES* *REGIÓN MORELIA* *DELEGACIÓN 45 SANTA CLARA DEL COBRE* *VIERNES 17 DE ABRIL DE 2026* *09:48 HORAS* *Asunto: Cortejo Fúnebre* Por medio de la presente se informa a la superioridad, que se presta el apoyo a un cortejo fúnebre realizando un corte de circulación en la avenida Morelos bajando por Ignacio Allende dando vuelta por la avenida Hidalgo hasta llegar al templo De la Inmaculada Concepción Personas alcanzadas: 100 Informan Elementos De Seguridad Vial: 1.- Raziel Contreras Viramontes 2.- Leopoldo Pérez Correa Reporta el encargado de la Delegación 45 de Santa Clara del Cobre, el *Sub. Oficial Calixto Vazquez Chávez* de la coordinación del Agrupamiento de Seguridad Vial | J51: DISPOSITIVOS DE SEGURIDAD VIAL_Images/0d4e1724.Foto 1-2.165720.jpg | K51: DISPOSITIVOS DE SEGURIDAD VIAL_Images/0d4e1724.Foto 2-2.165720.jpg | L51: 100 | M51: 2 | O51: 0 | P51: 0 | Q51: 0 | R51: 25 | S51: MORELIA | T51: DISPOSITIVOS DE SEGURIDAD VIAL
A52: 67659004 | B52: 67659004 | C52: LA PIEDAD - LA PIEDAD | D52: PASOS PEATONALES | E52: 46129 | F52: 0.45905093 | I52: GUARDIA CIVIL* *COORDINACIÓN DEL AGRUPAMIENTO DE SEGURIDAD VIAL* *UNIDAD DE DELEGACIÓNES* *REGION LA PIEDAD* *DELEGACIÓN LA PIEDAD* *VIERNES 17 DE ABRIL DE 2026* *10:10 HORAS* *ASUNTO:* Cruces Peatonales Para conocimiento del Mando, me permito informar que se está implementando un programa de concientización a la ciudadanía sobre el cruce y seguridad peatonal, invitándolos a cruzar por las rayas peatonales o lugares señalados y marcados en las esquinas. Informa la Unidad 3405 a cargo del Pol. Arturo Buenrostro Rodríguez de la Delegación de Seguridad Vial de La Piedad. Reporta el encargado de la Delegación Pol. 2° J. Jesús Arévalo León de la coordinación del Agrupamiento de Seguridad Vial. | J52: DISPOSITIVOS DE SEGURIDAD VIAL_Images/67659004.Foto 1-2.170126.jpg | K52: DISPOSITIVOS DE SEGURIDAD VIAL_Images/67659004.Foto 2-2.170126.jpg | L52: 0 | M52: 3 | O52: 1 | P52: 0 | Q52: 6 | R52: 4 | S52: LA PIEDAD | T52: DISPOSITIVOS DE SEGURIDAD VIAL
A53: 6f0f2073 | B53: 6f0f2073 | C53: MORELIA - PATZCUARO | D53: PATRULLAJES | E53: 46129 | F53: 0.46060185 | I53: *G U A R D I A C I V I L* *COORDINACIÓN DEL AGRUPAMIENTO DE SEGURIDAD VIAL* *UNIDAD DE DELEGACIONES* *REGIÓN MORELIA* *DELEGACION 01 DE PATZCUARO* *VIERNES 17 ABRIL DE 20226* *10:55 HORAS* *Asunto:* Recorrido de Supervisión y Seguridad Vial Por medio de la presente se informa a usted que se realizan recorridos continuos de supervisión y seguridad vial en zona centro de esta ciudad, Retirando vehículos mal estacionados, Activando circulación y prestando apoyo a paso de peatones los compañeros Pie-Tierra Pendientes en su lugar de servicio Se anexa material fotográfico. *Reporta el encargado de la Delegación Angel Peralta Hernández de la coordinación del Agrupamiento de Seguridad Vial* | J53: DISPOSITIVOS DE SEGURIDAD VIAL_Images/6f0f2073.Foto 1-2.170348.jpg | K53: DISPOSITIVOS DE SEGURIDAD VIAL_Images/6f0f2073.Foto 2-2.170348.jpg | L53: 600 | M53: 1 | O53: 1 | P53: 0 | Q53: 5 | R53: 19 | S53: MORELIA | T53: DISPOSITIVOS DE SEGURIDAD VIAL
A54: 5b3d0532 | B54: 5b3d0532 | C54: APATZINGAN - APATZINGAN | D54: PATRULLAJES | E54: 46129 | F54: 0.47123843 | I54: *G U A R D I A C I V I L .* *COORDINACIÓN DEL AGRUPAMIENTO DE SEGURIDAD VIAL .* *UNIDAD DE DELEGACIONES*. *REGIÓN APATZINGÁN* *DELEGACIÓN 07 APATZINGÁN* *VIERNES 17 DE ABRIL DEL 2026* *Asunto:* Recorridos de Prevención y proximidad social *11:09 HORAS* Para conocimiento de la superioridad, Se informa que está delegación de seguridad vial, realiza recorridos de prevención y Monitoreo sobre la carretera Apatzingán-Aguililla así como proximidad social en el centro recreativo Bioparque, ubicado sobre la misma carretera en el km. 4+500, hasta el momento sin novedad alguna. *Delegación de Seguridad Vial* 01.- Policía Adrián Alejandro Valle Vázquez 02.- Angel David Alejandre Tejeda Unidad: 04-157 Reporta el encargado de la delegación Apatzingán de la coordinación del Agrupamiento de Seguridad vial. Cmte. Julio Duvalier Hernández de la Cruz. | J54: DISPOSITIVOS DE SEGURIDAD VIAL_Images/5b3d0532.Foto 1-2.171914.jpg | K54: DISPOSITIVOS DE SEGURIDAD VIAL_Images/5b3d0532.Foto 2-2.171914.jpg | L54: 0 | M54: 2 | O54: 1 | P54: 0 | Q54: 10 | R54: 13 | S54: APATZINGAN | T54: DISPOSITIVOS DE SEGURIDAD VIAL
A55: 73b714a8 | B55: 73b714a8 | C55: LA PIEDAD - VISTA HERMOSA | D55: PASOS PEATONALES | E55: 46129 | F55: 0.50087963 | I55: *GUARDIA CIVIL* *COORDINACIÓN DEL AGRUPAMIENTO DE SEGURIDAD VIAL.* *UNIDAD DE DELEGACIONES* *REGION LA PIEDAD* *DELEGACION #54 VISTA HERMOSA* *VIERNES 17 DE ABRIL DE 2026* *Asunto:* Se instala dispositivo de seguridad y vialidad en los principales cruces peatonales. *Ubicación:* Av. Madero cruce con C. Francisco Tamayo Por medio de la presente se informa al momento que siendo las 11:10 horas se instalan dispositivos de seguridad y vialidad en los principales cruces peatonales de este municipio quedando hasta momento sin novedad. *Reporta:* La Oficial Yolanda Quiroz Con 1 Elementos Mas de Seguridad Vial. Informa respetuosamente: La Encargado de la Delegación 54 Vista Hermosa Denise Azucena Morales Briseño. | J55: DISPOSITIVOS DE SEGURIDAD VIAL_Images/73b714a8.Foto 1-2.180158.jpg | K55: DISPOSITIVOS DE SEGURIDAD VIAL_Images/73b714a8.Foto 2-2.180158.jpg | L55: 20 | M55: 2 | O55: 0 | P55: 0 | Q55: 1 | R55: 5 | S55: LA PIEDAD | T55: DISPOSITIVOS DE SEGURIDAD VIAL
A56: 6d80e21a | B56: 6d80e21a | C56: ZAMORA - ZACAPU | D56: PATRULLAJES | E56: 46129 | F56: 0.50756944 | I56: *GUARDIA CIVIL* *COORDINACIÓN DE AGRUPAMIENTO DE SEGURIDAD VIAL* *UNIDAD DE DELEGACIÓNES* *REGIÓN ZAMORA* *DELEGACIÓN 02 ZACAPÚ* *17 de Abril del 2026* *11:00 Horas* ASUNTO : *Vigilancia en Carreteras* Para conocimiento del mando me permito informar a usted que se realizan recorridos de prevención y vigilancia sobre la carretera Zacapu - Zamora km 80+300 aproximadamente en este municipio de Zacapú Michoacán, reportando sin novedad. Unidad: 16-724 Cristian Armando Arceo Estrada Reporta el encargado de la delegación Rigoberto Peralta Hernandez, de la coordinación de agrupamiento de seguridad vial. | J56: DISPOSITIVOS DE SEGURIDAD VIAL_Images/6d80e21a.Foto 1-2.181134.jpg | K56: DISPOSITIVOS DE SEGURIDAD VIAL_Images/6d80e21a.Foto 2-2.181134.jpg | L56: 0 | M56: 1 | O56: 1 | P56: 0 | Q56: 8 | R56: 29 | S56: ZAMORA | T56: DISPOSITIVOS DE SEGURIDAD VIAL
A57: 6be99b0c | B57: 6be99b0c | C57: MORELIA - ZINAPECUARO | D57: PATRULLAJES | E57: 46129 | F57: 0.51861111 | I57: G U A R D I A C I V I L COORDINACIÓN DEL AGRUPAMIENTO DE SEGURIDAD VIAL UNIDAD DE DELEGACIONES REGIÓN MORELIA DELEGACIÓN ZINAPECUARO 17/04/2026 12:25 HORAS Asunto Dispositivo de Seguridad en Carreteras Lugar Carretera Morelia Acámbaro KM 47+900 localidad el alto de aviles municipio de Álvaro Obregón* Para conocimiento de la superioridad, el personal de esta delegación se encuentra realizando recorridos de prevención y discusión para prevenir delitos en las diferentes carreteras de este municipio Reportando sin novedad hasta el momento *Unidad 19-6870 Estado de Fuerza 1.- Raúl Cortez Lopez 2.- J. Guadalupe Bucio Carrillo Reporta al encargado de la delegación el C. Jose Rolando Ojeda Ortiz de la coordinación del Agrupamiento de Seguridad Vial | J57: DISPOSITIVOS DE SEGURIDAD VIAL_Images/6be99b0c.Foto 1-2.183011.jpg | K57: DISPOSITIVOS DE SEGURIDAD VIAL_Images/6be99b0c.Foto 2-2.183011.jpg | L57: 0 | M57: 2 | O57: 1 | P57: 0 | Q57: 47 | R57: 20 | S57: MORELIA | T57: DISPOSITIVOS DE SEGURIDAD VIAL
A58: 3d4f0e52 | B58: 3d4f0e52 | C58: ZITACUARO - ZITACUARO | D58: PATRULLAJES | E58: 46129 | F58: 0.51944444 | I58: G U A R D I A C I V I L COORDINACIÓN DEL AGRUPAMIENTO DE SEGURIDAD VIAL UNIDAD DE DELEGACIONES REGIÓN ZITÁCUARO DELEGACIÓN 10 ZITÁCUARO JUEVES 17 DE ABRIL DEL 2026 Asunto: Recorrido de la Carretera Segura. Por medio de la presente Me permito informar que se continua con los Recorridos de patrullaje y vigilancia sobre las Carreteras Estatales y Vias Publicas; haciendo presencia y proporcionando Seguridad a la ciudadanía. El cual se lleva a cabo dentro del municipio de Zitácuaro Michoacán. CARRETERA (ZITACUARO-TOLUCA Y ZITÁCUARO-TUZANTLA) SIN NOVEDAD A cargo: Marisol Hernández Vieyra Elementos de apoyo: Lázaro Bernal Marín Juan Alonso Jerónimo Enoc Martínez Rogel Unidad: 193978 Kilómetros: 20 Es lo que me permito a usted informar para su superior conocimiento quedando sin novedad. Reporta el Encargado de la Delegación 10 Zitácuaro de la Coordinación del Agrupamiento de Seguridad Vial. Cmte. José María Mendoza Farías. | J58: DISPOSITIVOS DE SEGURIDAD VIAL_Images/3d4f0e52.Foto 1-2.183019.jpg | K58: DISPOSITIVOS DE SEGURIDAD VIAL_Images/3d4f0e52.Foto 2-2.183019.jpg | L58: 0 | M58: 4 | O58: 1 | P58: 0 | Q58: 20 | R58: 35 | S58: ZITACUARO | T58: DISPOSITIVOS DE SEGURIDAD VIAL
A59: 380e14c2 | B59: 380e14c2 | C59: MORELIA - ZINAPECUARO | D59: PATRULLAJES | E59: 46129 | F59: 0.53309028 | I59: G U A R D I A C I V I L COORDINACIÓN DEL AGRUPAMIENTO DE SEGURIDAD VIAL UNIDAD DE DELEGACIONES REGIÓN MORELIA DELEGACIÓN ZINAPECUARO 17/04/2026 12:46 HORAS Asunto Dispositivo de Seguridad en Carreteras Lugar Carretera Morelia Acámbaro KM 31+500 localidad el Morelos municipio de Álvaro Zinapecuaro* Para conocimiento de la superioridad, el personal de esta delegación se encuentra realizando recorridos de prevención y discusión para prevenir delitos en las diferentes carreteras de este municipio Reportando sin novedad hasta el momento *Unidad 04-374 Estado de Fuerza 1.- Raúl Cortez Lopez 2.- J. Guadalupe Bucio Carrillo Reporta al encargado de la delegación el C. Jose Rolando Ojeda Ortiz de la coordinación del Agrupamiento de Seguridad Vial | J59: DISPOSITIVOS DE SEGURIDAD VIAL_Images/380e14c2.Foto 1-2.185114.jpg | K59: DISPOSITIVOS DE SEGURIDAD VIAL_Images/380e14c2.Foto 2-2.185114.jpg | L59: 0 | M59: 2 | O59: 1 | P59: 0 | Q59: 31 | R59: 20 | S59: MORELIA | T59: DISPOSITIVOS DE SEGURIDAD VIAL
A60: f81da5b8 | B60: f81da5b8 | C60: APATZINGAN - APATZINGAN | D60: APOYO A LA VIALIDAD | E60: 46129 | F60: 0.54564815 | I60: *G U A R D I A C I V I L .* *COORDINACIÓN DEL AGRUPAMIENTO DE SEGURIDAD VIAL .* *UNIDAD DE DELEGACIONES*. *REGIÓN APATZINGÁN* *DELEGACIÓN 07 APATZINGÁN* *VIERNES 17 DE ABRIL DEL 2026* *Hora* 12:50 horas *Asunto:* Se continúa el dispositivo de seguridad vial, en el mercado municipal. Por medio de la presente me permito Informar a usted que, esta delegación de Seguridad vial, continúa con el dispositivo de vialidad en la periferia del Mercado Municipal "Ignacio López Rayón" para el cruce de las personas peatonas, activar la circulación vehícular , retiro de vehículos mal estacionados y de doble fila, en las *coordenadas: 19.08384333,-102.354993 *Reporta:* Unidades 24-7682, 04-157 01.- Policía Adrian Alejandro Valle Vázquez 02.- Policía Raul Dimas Nava 03.- Policía Angel David Alejandre Tejeda Reporta el encargado de la delegación Apatzingán de la coordinación del Agrupamiento de Seguridad vial. Cmte. Julio Duvalier Hernández de la Cruz. | J60: DISPOSITIVOS DE SEGURIDAD VIAL_Images/f81da5b8.Foto 1-2.190654.jpg | K60: DISPOSITIVOS DE SEGURIDAD VIAL_Images/f81da5b8.Foto 2-2.190654.jpg | L60: 0 | M60: 3 | O60: 2 | P60: 0 | Q60: 20 | R60: 13 | S60: APATZINGAN | T60: DISPOSITIVOS DE SEGURIDAD VIAL
A61: 42805427 | B61: 42805427 | C61: ZAMORA - PUREPERO | D61: PATRULLAJES | E61: 46129 | F61: 0.56747685 | I61: *G U A R D I A C I V I L* *COORDINACION DEL AGRUPAMIENTO DE SEGURIDAD VIAL* *UNIDAD DE DELEGACIONES* *REGION ZAMORA* *DELEGACIÓN PUREPERO* *VIERNES 16 DE ABRIL DE 2026* *11:02 HORAS* *Asunto: Recorrido de Carretera Segura* Por medio de la Presente, Me Permito Informar que se continúa con los *Recorridos de Seguridad y Vigilancia en las Carreteras Estatales y Vías Públicas del Municipio de Purepero para la Seguridad de la Ciudadanía.* estos recorridos se realizan a cargo del *Oficial Aguilera Alejo Jose Luis a bordo de la Unidad 19-3976* Kilómetros recorridos 37 Reporta el *Policía 1°Jose Manuel Sanchez Mora* Encargado de la Delegación No. 020 Purepero de la Coordinación del Agrupamiento de Seguridad Vial | J61: DISPOSITIVOS DE SEGURIDAD VIAL_Images/42805427.Foto 1-2.193906.jpg | K61: DISPOSITIVOS DE SEGURIDAD VIAL_Images/42805427.Foto 2-2.193906.jpg | L61: 0 | M61: 2 | O61: 1 | P61: 0 | Q61: 37 | R61: 32 | S61: ZAMORA | T61: DISPOSITIVOS DE SEGURIDAD VIAL
A62: 615fe419 | B62: 615fe419 | C62: APATZINGAN - GABRIEL ZAMORA | D62: PASOS PEATONALES | E62: 46129 | F62: 0.57505787 | I62: *G U A R D I A C I V I L* *COORDINACIÓN DEL AGRUPAMIENTO DE SEGURIDAD VIAL* *UNIDAD DE DELEGACIONES* *REGION APATZINGAN* *DELEGACION 40 GABRIEL ZAMORA* *Viernes 17 de abril del 2026* *Asunto*: Se continúa con el servicio de Seguridad Vial en los cruces peatonales *11:01 horas* *Guardia Civil* "Seguridad Vial Estatal" se informa que se continúa con la campaña de Seguridad Vial en el cruce de peatones en la av.Revolucion, a la altura de la glorieta los cuales se llevan a cabo sin novedad. En el lugar Samantha Estela Ruiz Soto Reporta el encargado de la delegación No. 40 Gabriel Zamora, Julio Cesar Silva Mendoza de la coordinación del agrupamiento de seguridad vial. | J62: DISPOSITIVOS DE SEGURIDAD VIAL_Images/615fe419.Foto 1-2.194836.jpg | K62: DISPOSITIVOS DE SEGURIDAD VIAL_Images/615fe419.Foto 2-2.194836.jpg | L62: 0 | M62: 1 | O62: 1 | P62: 0 | Q62: 1 | R62: 15 | S62: APATZINGAN | T62: DISPOSITIVOS DE SEGURIDAD VIAL
A63: 204cacfe | B63: 204cacfe | C63: COALCOMAN - COALCOMAN | D63: PATRULLAJES | E63: 46129 | F63: 0.60123843 | I63: *Guardia Civil* *Unidad Dé Delegaciones* *Región Coalcoman* *Delegación 030 Coalcoman* *Viernes 17 de abril del 2026.* 12:50 horas. *Asunto:* Carretera segura. Por medio de la presente me permito informar a mi superioridad, que el personal de está delegación de seguridad vial, nos encontramos realizando recorridos intinerantes de vigilancia sobre la carretera estatal Coalcoman-Aquila (basurero municipal) con la finalidad de evitar algún hecho delictivo, auxiliar a conductores en caso de falla mecánica y crear la confianza entre la sociedad *Elementos participantes* 1.- Sergio Suárez Jiménez. *Abordo de la unidad oficial 03-608* 33- kilómetros. Terminando el recorrido.alas 14:15 horas, sin novedad. Lo que me permito informar Respetuosamente. Integrante de la coordinación de Seguridad Vial Estatal delegación 030 región Coalcoman Cmte. Leonardo Rolón Meraz. | J63: DISPOSITIVOS DE SEGURIDAD VIAL_Images/204cacfe.Foto 1-2.202639.jpg | K63: DISPOSITIVOS DE SEGURIDAD VIAL_Images/204cacfe.Foto 2-2.202639.jpg | L63: 0 | M63: 1 | O63: 1 | P63: 0 | Q63: 33 | R63: 11 | S63: COALCOMAN | T63: DISPOSITIVOS DE SEGURIDAD VIAL
A64: c8c082c8 | B64: c8c082c8 | C64: ZAMORA - COENEO | D64: APOYO A LA VIALIDAD | E64: 46129 | F64: 0.63207176 | I64: *GUARDÍA CIVIL* *COORDINACIÓN DEL AGRUPAMIENTO DE SEGURIDAD VÍAL* *UNIDAD DE DELEGACIÓNES* *REGIÓN ZAMORA* *DELEGACIÓN 41 COENEO* *ASUNTO: SERVICIO ESTABLECIDO* *UBICACIÓN: COENEO MICHOACÁN* *VIERNES 17 ABRIL DE 2026* *14:48 HORAS* Por medio de la Presente se informa a la Superioridad que se Continúa con personal pie tierra sobre la calle Morelos sur, Allende y Morelos norte, esto con la finalidad de retirar vehículos mal estacionados, y apoyar en cruces peatonales, así como dar una mejor fluidez vehicular y evitar algún hecho de tránsito. *Informa la unidad 03-621* A cargo del oficial. Baltazar Cisneros Flores. Diana Lizeth Lemus Sotelo. *Personas alcanzadas 160* *Kilómetros recorridos 3* *Reporta Encargado de La Delegación de Seguridad vial de Coeneo;* Clemente Vázquez Ávalos. | J64: DISPOSITIVOS DE SEGURIDAD VIAL_Images/c8c082c8.Foto 1-2.211100.jpg | K64: DISPOSITIVOS DE SEGURIDAD VIAL_Images/c8c082c8.Foto 2-2.211100.jpg | L64: 160 | M64: 2 | O64: 1 | P64: 0 | Q64: 3 | R64: 30 | S64: ZAMORA | T64: DISPOSITIVOS DE SEGURIDAD VIAL
A65: 29798003 | B65: 29798003 | C65: ZAMORA - JACONA | D65: PASOS PEATONALES | E65: 46129 | F65: 0.63399306 | I65: *G U A R D I A C I V I L* *COORDINACION DEL AGRUPAMIENTO DE SEGURIDAD VIAL* *UNIDAD DE DELEGACIÓNES* *REGION ZAMORA* *DELEGACIÓN JACONA* *VIERNES 17 DE ABRIL DEL 2026* *15:10HORAS* *Asunto:* Presencia y Seguridad Vial a Peatones Por medio de este conducto me permito informar que se continúa en el dispositivo de seguridad vial en el cruce de peatones sobre la Av. Francisco I. Madero, siendo esta la novedad al momento. Informan los Elementos Pie Tierra (02) 1.- Pedro Ortiz García 2.- Alfredo Ayala Zúñiga Reporta el *Cmdte. Francisco Javier Armas Ochoa* encargado de la delegación No. 022, de Jacona, de la Coordinación del Agrupamiento de Seguridad Vial. | J65: DISPOSITIVOS DE SEGURIDAD VIAL_Images/29798003.Foto 1-2.211356.jpg | K65: DISPOSITIVOS DE SEGURIDAD VIAL_Images/29798003.Foto 2-2.211356.jpg | L65: 0 | M65: 2 | O65: 0 | P65: 0 | Q65: 0 | R65: 28 | S65: ZAMORA | T65: DISPOSITIVOS DE SEGURIDAD VIAL
A66: d66cf599 | B66: d66cf599 | C66: LA PIEDAD - LA PIEDAD | D66: PASOS PEATONALES | E66: 46129 | F66: 0.66943287 | I66: *GUARDIA CIVIL* *COORDINACIÓN DEL AGRUPAMIENTO DE SEGURIDAD VIAL* *UNIDAD DE DELEGACIÓNES* *REGION LA PIEDAD* *DELEGACIÓN LA PIEDAD* *VIERNES 17 DE ABRIL DE 2026* *16:00 HORAS* *ASUNTO:* Cruces Peatonales Para conocimiento del Mando, me permito informar que se está implementando un programa de concientización a la ciudadanía sobre el cruce y seguridad peatonal, invitándolos a cruzar por las rayas peatonales o lugares señalados y marcados en las esquinas. Informa la Unidad 3405 a cargo del Pol. Arturo Buenrostro Rodríguez de la Delegación de Seguridad Vial de La Piedad. Reporta el encargado de la Delegación Pol. 2° J. Jesús Arévalo León de la coordinación del Agrupamiento de Seguridad Vial. | J66: DISPOSITIVOS DE SEGURIDAD VIAL_Images/d66cf599.Foto 1-2.220445.jpg | K66: DISPOSITIVOS DE SEGURIDAD VIAL_Images/d66cf599.Foto 2-2.220445.jpg | L66: 0 | M66: 2 | O66: 1 | P66: 0 | Q66: 6 | R66: 4 | S66: LA PIEDAD | T66: DISPOSITIVOS DE SEGURIDAD VIAL
A67: 68204f49 | B67: 68204f49 | C67: ZAMORA - ZAMORA | D67: PATRULLAJES | E67: 46129 | F67: 0.6937963 | I67: *GUARDIA CIVIL.* *COORDINACIÓN DE AGRUPAMIENTO DE SEGURIDAD VIAL.* *UNIDAD DE DELEGACIONES.* *REGIÓN ZAMORA.* VIERNES 17- ABRIL -2026 16:20 HRS ASUNTO: *RECORRIDOS EN DISUASIÓN DEL DELITO (CARRETERA SEGURAS SIN NOVEDAD AL MOMENTO)* _Me permito informa a la superioridad se da recorridos sobre las carreteras Estatales, Federales y vías Públicas, haciendo presencia y dando seguridad a los automovilistas siendo esta la novedad._ Informa: C. Jose Alberto Torres Villalpando con 03 más abordo en la unidad 04-189. Reporta el encargado de la delegación el C. Alfredo Velázquez González de la coordinación del agrupamiento de seguridad vial. | J67: DISPOSITIVOS DE SEGURIDAD VIAL_Images/68204f49.Foto 1-2.223938.jpg | K67: DISPOSITIVOS DE SEGURIDAD VIAL_Images/68204f49.Foto 2-2.223938.jpg | L67: 0 | M67: 4 | O67: 1 | P67: 0 | Q67: 12 | R67: 27 | S67: ZAMORA | T67: DISPOSITIVOS DE SEGURIDAD VIAL
A68: 30e451c8 | B68: 30e451c8 | C68: HUETAMO - HUETAMO | D68: PASOS PEATONALES | E68: 46129 | F68: 0.65836806 | I68: *Guardia Civil * *Coordinación del Agrupamiento de Seguridad Vial* *Unidad de Delegaciones* *Región Huetamo* *Delegación 12 Huetamo* Viernes 17 de Abril del 2026* *Asunto:* Apoyo en el Paso peatonal en la zona centro. *17:00 Horas* Por medio de la presente se informa al mando que se realiza el apoyo del paso peatonal y la seguridad en zona centro con la finalidad de salvaguardar la integridad física de la ciudadanía y así evitar accidentes. Al momento todo sin novedad de relevancia continuamos pendientes y a la orden. Estado de Fuerza:- PIE TIERRA Julián González Pineda. Informa el Oficial Julián González Pineda elemento de la Delegación Regional 12 así como de seguridad Vial. Reportó el Cmdte. Florencio Reynoso Gómez, Encargado de la Delegación 12 de la coordinación del Agrupamiento de Seguridad Vial. | J68: DISPOSITIVOS DE SEGURIDAD VIAL_Images/30e451c8.Foto 1-2.230049.jpg | K68: DISPOSITIVOS DE SEGURIDAD VIAL_Images/30e451c8.Foto 2-2.230049.jpg | L68: 4 | M68: 1 | O68: 0 | P68: 0 | Q68: 0 | R68: 16 | S68: HUETAMO | T68: DISPOSITIVOS DE SEGURIDAD VIAL
A69: 2e4b4053 | B69: 2e4b4053 | C69: ZITACUARO - TLALPUJAHUA | D69: PERIFÉRICOS | E69: 46128 | F69: 0.76105324 | I69: GUARDIA CIVIL COORDINACIÓN DEL AGRUPAMIENTO DE SEGURIDAD VIAL UNIDAD DE DELEGACIONES REGIÓN ZITÁCUARO DELEGACIÓN 31 TLALPUJAHUA JUEVES 16 DE ABRIL DEL 2026. 18:15 horas UBICACIÓN: Caseta de Peaje 54 Contepec, autopista México-Guadalajara km 134+300 ASUNTO: Monitoreo de Casetas de Peaje. *Estatus:* 🟢 *LIBRE* Por medio de la presente se informa que al momento se realizan monitoreos en la casetas de peaje 54 Contepec, sobre la autopista México-Guadalajara km 134+300, la cuál se encuentra laborando con fluidez y normalidad. *NOTA* Monitoreo se realiza abordó de la unidad 21-6435 Reporta la Encargado de la Delegación 31 Tlalpujahua Cmdte Alejandro Mario Medina Márquez de la Coordinación del Agrupamiento de Seguridad Vial | J69: MONITOREOS_Images/2e4b4053.Foto 1-2.001632.jpg | K69: MONITOREOS_Images/2e4b4053.Foto 2-2.001632.jpg | L69: 0 | M69: 1 | O69: 1 | P69: 0 | Q69: 9 | R69: 39 | S69: ZITACUARO | T69: MONITOREOS
A70: d7a13f4d | B70: d7a13f4d | C70: URUAPAN - TARETAN | D70: GASOLINERAS | E70: 46128 | F70: 0.79939815 | I70: *Guardia Civil* *Coordinación de Agrupamientos de Delegaciones* *Unidad de Delegaciónes* *Región Uruapan* *Delegación Taretan #27* *Jueves 16 de Abril del 2026* *Asunto:Recorridos de Monitoreo en gasolineras* *18:45 hrs*. *Guardia Civil Seguridad Vial Estatal* *Para conocimiento de los mandos me permito informar que se realizan recorridos en la unidad 16-864 de monitoreo y vigilancia en gasolineras de esta jurisdicción estando hasta el momento sin novedad.* *Unidad 16-864* *Kilómetros recorridos 5* *Pnas.alcanzadas 6* *Informa* *Respetuosamente* *Encargado Dionicio Díaz Rebolledo de la Seguridad Vial Estatal de Taretan #27* | J70: MONITOREOS_Images/d7a13f4d.Foto 1-2.011233.jpg | K70: MONITOREOS_Images/d7a13f4d.Foto 2-2.011233.jpg | L70: 6 | M70: 1 | O70: 1 | P70: 0 | Q70: 5 | R70: 49 | S70: URUAPAN | T70: MONITOREOS
A71: 10058def | B71: 10058def | C71: JIQUILPAN - VENUSTIANO CARRANZA | D71: OFICINAS GUBERNAMENTALES | E71: 46128 | F71: 0.82797454 | I71: *G U A R D I A C I V I L* *COORDINACIÓN DEL AGRUPAMIENTO DE SEGURIDAD VIAL* *UNIDAD DE DELEGACIONES* *REGIÓN JIQUILPAN* *DELEGACIÓN 53 VENUSTIANO CARRANZA* *JUEVES 16 DE ABRIL DEL 2026* *10:20 HORAS* *Asunto:* Monitoreos en Oficinas gubernamentales Se informa a la superiores, que se realizan Monitoreos en el Municipio de Venustiano Carranza para detectar manifestaciones o acciones ilicitas, Las oficinas municipales laborando normalmente, sin novedad hasta el momento. *Unidad:* 04-181 *Kilómetros:* 04 *sin novedad*. Reporta el encargado de la Delegación Jose de Jesús Alvarez Fernández de la coordinación del Agrupamiento de Seguridad Vial. | J71: MONITOREOS_Images/10058def.Foto 1-2.015253.jpg | K71: MONITOREOS_Images/10058def.Foto 2-2.015253.jpg | L71: 15 | M71: 2 | O71: 1 | P71: 0 | Q71: 5 | R71: 45 | S71: JIQUILPAN | T71: MONITOREOS
A72: 537b9785 | B72: 537b9785 | C72: JIQUILPAN - VENUSTIANO CARRANZA | D72: GASOLINERAS | E72: 46128 | F72: 0.82855324 | I72: *G U A R D I A C I V I L* *COORDINACIÓN DEL AGRUPAMIENTO DE SEGURIDAD VIAL* *UNIDAD DE DELEGACIONES* *REGIÓN JIQUILPAN* *DELEGACIÓN 53 VENUSTIANO CARRANZA* *16 DE ABRIL DE 2026* *12:00 HORAS* *Asunto:* Monitoreos en Gasolinerías Por este medio se informa a la superioridad qué, se realizan Monitoreos en gasolinerías del Municipio de venustiano Carranza con el fin de detectar manifestaciones e inhibir conductas delictivas *SIN NOVEDAD HASTA EL MOMENTO* Reporta el encargado de la Delegación José de Jesús Álvarez Fernández,de la coordinación del Agrupamiento de Seguridad Vial | J72: MONITOREOS_Images/537b9785.Foto 1-2.015358.jpg | K72: MONITOREOS_Images/537b9785.Foto 2-2.015358.jpg | L72: 15 | M72: 2 | O72: 1 | P72: 0 | Q72: 15 | R72: 45 | S72: JIQUILPAN | T72: MONITOREOS
A73: f5aef670 | B73: f5aef670 | C73: ZAMORA - ZAMORA | D73: TIENDAS DEPARTAMENTALES | E73: 46128 | F73: 0.84994213 | I73: GUARDIA CIVIL COORDINACION DEL AGRUPAMIENTO DE SEGURIDAD VIAL UNIDAD DE DELEGACIÓNES REGION ZAMORA JUEVES 16 DE ABRIL DE 2026 19:45 HRS ASUNTO: MONITOREO DE TIENDAS Y CENTROS COMERCIALES Por medio del presente se informa. Que se realizan recorridos de prevención y vigilancia en las tiendas y centros comerciales de la colonia centro sin incidencias que reportar durante el monitoreo . (Novedad) Sin novedad hasta el momento Informa el Oficial. Emiliano Manrriquez Velázquez Policía de la Delegación de Seguridad Vial de Zamora con 02 más Pie tierra Reportó el encargado de la delegación C. Alfredo Velázquez González, Coordinación del Agrupamiento de Seguridad Vial. | J73: MONITOREOS_Images/f5aef670.Foto 1-2.022452.jpg | K73: MONITOREOS_Images/f5aef670.Foto 2-2.022452.jpg | L73: 0 | M73: 3 | O73: 0 | P73: 0 | Q73: 1 | R73: 27 | S73: ZAMORA | T73: MONITOREOS
A74: 81118838 | B74: 81118838 | C74: ZITACUARO - ZITACUARO | D74: TIENDAS DEPARTAMENTALES | E74: 46128 | F74: 0.85415509 | I74: G U A R D I A C I V I L COORDINACIÓN DEL AGRUPAMIENTO DE SEGURIDAD VIAL UNIDAD DE DELEGACIONES REGIÓN ZITACUARO DELEGACIÓN 10 ZITÁCUARO JUEVES 16 DE ABRIL DE 2026 Asunto: Monitoreo de tiendas Por medio de la presente se informa que al momento se realiza monitoreo en diferentes tiendas departamentales pertenecientes a éste municipio de Zitácuaro Michoacán. Tiendas departamentales Sin novedad A cargo: Diana Marin Colin Elementos De apoyo: Marísol Hernández Vieyra Lázaro Bernal Marin Juan Alonso Jerónimo Enoc Martínez Rogel Unidad: 193978 Kilómetros: 09 Reporta el encargado de la Delegación 10 Zitácuaro de la Coordinación del Agrupamiento de Seguridad Vial. Cmte.: José María Mendoza Farías. | J74: MONITOREOS_Images/81118838.Foto 1-2.023208.jpg | K74: MONITOREOS_Images/81118838.Foto 2-2.023208.jpg | L74: 0 | M74: 5 | O74: 1 | P74: 0 | Q74: 9 | R74: 35 | S74: ZITACUARO | T74: MONITOREOS
A75: 12f6882b | B75: 12f6882b | C75: ZAMORA - ECUANDUREO | D75: OFICINAS GUBERNAMENTALES | E75: 46128 | F75: 0.95850694 | I75: Guardia Civil Coordinación del Agrupamiento de Seguridad Vial Unidad de Delegaciones Región Zamora Delegación Ecuandureo JUEVES 16 DE ABRIL DEL 2026 Asunto: Monitoreo de las Oficinas de Rentas y Presidencia Municipal 09:30 Horas Por medio de la presente se informa a la superioridad que se Monitorea las Oficinas de Rentas y Presidencia Municipal , esto con la finalidad de dar Presencia y fomentar la proximidad social y prevenir el delito La cuales se encuentran trabajando normal al público Informa Miguel Ramírez Julián y Marco Antonio Félix Flores de la Delegación de Seguridad Vial de Ecuandureo. Reportó el Encargado de la Delegación Miguel Ramírez Julián de la Coordinación del Agrupamiento de Seguridad Vial | J75: MONITOREOS_Images/12f6882b.Foto 1-2.050051.jpg | K75: MONITOREOS_Images/12f6882b.Foto 2-2.050051.jpg | L75: 5 | M75: 2 | O75: 0 | P75: 0 | Q75: 2 | R75: 31 | S75: ZAMORA | T75: MONITOREOS
A76: f55383ad | B76: f55383ad | C76: ZAMORA - ECUANDUREO | D76: BANCOS | E76: 46128 | F76: 0.96011574 | I76: G U A R D I A C I V I L COORDINACIÓN DEL AGRUPAMIENTO DE SEGURIDAD VIAL UNIDAD DE DELEGACIONES REGIÓN ZAMORA DELEGACIÓN ECUANDUREO JUEVES 16 DE ABRIL DE 2026 13:30 horas Asunto: Monitoreo de Cajeros automáticos Por medio de la presente se informa a la superioridad que se dan Recorridos de Vigilancia en los Cajeros automáticos con la finalidad de dar Presencia y fomentar la proximidad social y prevenir el delito (los Cajeros se encuentra laborando Normal) Informa Miguel Ramírez Julián y Marco Antonio Félix Flores de la Delegación de Seguridad Vial Ecuandureo Reporta el encargado de la Delegación Miguel Ramírez Julián de la coordinación del Agrupamiento de Seguridad Vial | J76: MONITOREOS_Images/f55383ad.Foto 1-2.050314.jpg | K76: MONITOREOS_Images/f55383ad.Foto 2-2.050314.jpg | L76: 5 | M76: 2 | O76: 0 | P76: 0 | Q76: 2 | R76: 31 | S76: ZAMORA | T76: MONITOREOS
A77: 70f62bb8 | B77: 70f62bb8 | C77: ZAMORA - ECUANDUREO | D77: PERIFÉRICOS | E77: 46128 | F77: 0.96153935 | I77: Guardia Civil Coordinacion del Agrupamiento de Seguridad Vial Unidad de Delegaciones Región Zamora Delegación 048 Ecuandureo Jueves 16 de Abril de 2026. 18:30 horas Ubicación Casetas Ecuandureo Morelia -Guadalajara y Guadalajara-Morelia. Asunto: Monitoreo de Casetas de Peaje. Estatus: 🟢 LIBRE Por medio de la presente se informa que al momento se realizan monitoreos en las casetas de peaje, las cuales se encuentran laborando sin novedad. NOTA Monitoreo se realiza abordó de la unidad de Seguridad Pública Municipal PM02 A cargo del Cmnte Juan Jaimes Cruz Con 1 Elemento más de Seguridad Pública Municipal. Reporta el Encargado de la Delegación 048 Ecuandureo de la Coordinacion del Agrupamiento de Seguridad Vial. Cmnte. Miguel Ramírez Julián | J77: MONITOREOS_Images/70f62bb8.Foto 1-2.050536.jpg | K77: MONITOREOS_Images/70f62bb8.Foto 2-2.050536.jpg | L77: 10 | M77: 2 | O77: 0 | P77: 0 | Q77: 5 | R77: 31 | S77: ZAMORA | T77: MONITOREOS
A78: 8dd4f587 | B78: 8dd4f587 | C78: LA PIEDAD - VISTA HERMOSA | D78: PERIFÉRICOS | E78: 46129 | F78: 0.31511574 | I78: *Guardia Civil* *Coordinación del Agrupamiento de Seguridad Vial* *Unidad de Delegaciones* *Región La Piedad* *Delegación 54 Vista Hermosa* *Viernes 17 de Abril de 2026* *Hora:* 07:20 horas *Asunto:* Monitoreo de carreteras Por medio de la presente me permito informar a la superioridad, que se realizan recorridos de monitoreo y vigilancia en carreteras y caminos de nuestra jurisdicción. Estando al momento sin novedad Informa la Unidad 019-79 de Transito Municipal, a cargo de la Cmnte Denise Morales con 1 Elemento más de Seguridad Vial. Reporta la Encargada de la Delegación 54 Vista Hermosa de la Coordinacion del Agrupamiento de Seguridad Vial. Cmnte. Denise Azucena Morales Briseño | J78: MONITOREOS_Images/8dd4f587.Foto 1-2.133418.jpg | K78: MONITOREOS_Images/8dd4f587.Foto 2-2.133418.jpg | L78: 15 | M78: 2 | O78: 0 | P78: 0 | Q78: 13 | R78: 5 | S78: LA PIEDAD | T78: MONITOREOS
A79: 23830def | B79: 23830def | C79: APATZINGAN - NUEVA ITALIA | D79: OFICINAS GUBERNAMENTALES | E79: 46129 | F79: 0.36134259 | I79: *G U A R D I A C I V I L* *COORDINACION DEL AGRUPAMIENTO DE SEGURIDAD VIAL* *UNIDAD DE DELEGACIONES* *REGION: APATZINGAN* *DELEGACION : NUEVA ITALIA* *VIERNES 17 DE ABRIL DEL 2026* *08:15AM* *ASUNTO: MONITOREO A DEPENDENCIAS DE GOBIERNO.* Por medio de la presente me permito Informar a la superioridad que está Delegación de seguridad vial monitorea las diferentes dependencias de gobierno receptaría de rentas del estado,registro civil y Presidencia municipal las mismas que se encuentran laborando con normalidad. Para conocimiento de la superioridad. *INFORMA* *. RESPETUOSAMENTE* *ENCARGADO DE LA DELEGACIÓN WILMER QUEZADAS SOSA DE LA COORDINACIÓN DEL AGRUPAMIENTO DE SEGURIDAD VIAL.* | J79: MONITOREOS_Images/23830def.Foto 1-2.144144.jpg | K79: MONITOREOS_Images/23830def.Foto 2-2.144144.jpg | L79: 0 | M79: 2 | O79: 1 | P79: 0 | Q79: 2 | R79: 14 | S79: APATZINGAN | T79: MONITOREOS
A80: cd0e4c5f | B80: cd0e4c5f | C80: APATZINGAN - NUEVA ITALIA | D80: VÍAS FÉRREAS | E80: 46129 | F80: 0.36247685 | I80: *G U A R D I A C I V I L* *COORDINACION DEL AGRUPAMIENTO DE SEGURIDAD VIAL* *UNIDAD DE DELEGACIONES* *REGION: APATZINGAN* *DELEGACION : NUEVA ITALIA* *VIERNES 17 DE MARZO DEL 2026* *08:25AM* *ASUNTO: MONITOREO A LAS VÍAS DEL FERROCARRIL.* Por medio de la presente me permito Informar a la superioridad que está Delegación de seguridad vial monitorea las vías del ferrocarril y estación ferroviaria que se encuentra en la colina la estación de esta cabecera municipal misma que se encuentra sin novedad y libre de bloqueos. Para conocimiento de la superioridad. *INFORMA* *. RESPETUOSAMENTE* *ENCARGADO DE LA DELEGACIÓN WILMER QUEZADAS SOSA DE LA COORDINACIÓN DEL AGRUPAMIENTO DE SEGURIDAD VIAL.* | J80: MONITOREOS_Images/cd0e4c5f.Foto 1-2.144311.jpg | K80: MONITOREOS_Images/cd0e4c5f.Foto 2-2.144311.jpg | L80: 0 | M80: 2 | O80: 1 | P80: 0 | Q80: 4 | R80: 14 | S80: APATZINGAN | T80: MONITOREOS
A81: 8cc51ee0 | B81: 8cc51ee0 | C81: MORELIA - ZINAPECUARO | D81: TIENDAS DEPARTAMENTALES | E81: 46129 | F81: 0.37390046 | I81: G U A R D I A C I V I L COORDINACIÓN DEL AGRUPAMIENTO DE SEGURIDAD VIAL UNIDAD DE DELEGACIONES REGIÓN MORELIA DELEGACIÓN ZINAPECUARO 17/04/2026 07:32 Horas Asunto : Monitoreo a tiendas departamentales Para conocimiento de la superioridad, el personal de esta delegación informa que se realiza un monitoreo a tiendas fepartamentaled en la localidad de el rocio municipio de Zinapecuaro Reportando sin novedad . *Kilómetros recorridos 10* Reporta al encargado de la delegación el C. Jose Rolando Ojeda Ortiz de la coordinación del Agrupamiento de Seguridad Vial | J81: MONITOREOS_Images/8cc51ee0.Foto 1-2.150019.jpg | K81: MONITOREOS_Images/8cc51ee0.Foto 2-2.150019.jpg | L81: 0 | M81: 2 | O81: 1 | P81: 0 | Q81: 10 | R81: 20 | S81: MORELIA | T81: MONITOREOS
A82: 5543ece3 | B82: 5543ece3 | C82: LA PIEDAD - VISTA HERMOSA | D82: OFICINAS GUBERNAMENTALES | E82: 46129 | F82: 0.3772338 | I82: *Guardia Civil* *Coordinación del Agrupamiento de Seguridad Vial* *Unidad de Delegaciones* *Región La Piedad* *Delegación 54 Vista Hermosa* *Viernes 17 de Abril del 2026* *Hora* 09:00 hrs. *Asunto:* Monitoreo de Oficinas Gubernamentales. Por medio de la presente se informa que a esta hora se realizan monitoreos en las oficinas de Administración de Rentas, Presidencia Municipal y Registro Civil, las cuales se encuentran laborando. Sin novedad de relevancia. *Nota:* Monitoreo se realiza a cargo de la oficial Yolanda Quiroz con 1 Elemento más de Seguridad Vial. Informa: Respetuosamente La Encargada de la Delegación 54 Vista Hermosa de la Coordinacion del Agrupamiento de Seguridad Vial. Cmdte. Denise Azucena Morales Briseño. | J82: MONITOREOS_Images/5543ece3.Foto 1-2.150358.jpg | K82: MONITOREOS_Images/5543ece3.Foto 2-2.150358.jpg | L82: 40 | M82: 2 | O82: 0 | P82: 0 | Q82: 3 | R82: 5 | S82: LA PIEDAD | T82: MONITOREOS
A83: 9158d291 | B83: 9158d291 | C83: ZITACUARO - MARAVATIO | D83: OFICINAS GUBERNAMENTALES | E83: 46129 | F83: 0.3644213 | I83: Guardia Civil Coordinación del Agrupamiento de Seguridad Vial Unidad de Delegaciones Región Zitácuaro Delegación Maravatío 17/04/26 08:40 Asunto: Monitoreo en la presidencia municipal. Por medio de la presente se informa que la presidencia municipal de esta ciudad de Maravatío, se encuentra laborando en su total normalidad. Reportando hasta el momento sin novedad alguna. Informa la Unidad 3280 a cargo de Ricardo Heriberto Tapia López y Mario González Vallesteros agentes de la Delegación de Seguridad Vial de Maravatío. Reportó el encargado de la delegación Jose Luis Arvizu Zamora, de la coordinación del Agrupamiento de Seguridad Vial Maravatío. | J83: MONITOREOS_Images/9158d291.Foto 1-2.150416.jpg | K83: MONITOREOS_Images/9158d291.Foto 2-2.150416.jpg | L83: 0 | M83: 3 | O83: 1 | P83: 0 | Q83: 10 | R83: 36 | S83: ZITACUARO | T83: MONITOREOS
A84: 7b2e5518 | B84: 7b2e5518 | C84: LAZARO CARDENAS - ARTEAGA | D84: OFICINAS GUBERNAMENTALES | E84: 46129 | F84: 0.37800926 | I84: *G U A R D I A C I V I L* *COORDINACIÓN DE AGRUPAMIENTO DE SEGURIDAD VIAL* *REGIÓN LÁZARO CÁRDENAS* *UNIDAD DE DELEGACIÓNES* *DELEGACIÓN 36 ARTEAGA* *VIERNES 17 DE ABRIL DE 2026* *Asunto:* Monitoreo de Oficinas Gubernamentales 09:00 hrs Guardia Civil "Seguridad vial" informa que personal de esta delegación *Monitorea las Oficinas Públicas* como son: 1.- Palacio Municipal ( Laborando) 2.-Administracion de Rentas (Laborando) 3.- Juzgado Mixto de Primera Instancia (Laborando) 4.- Registro Civil ( Laborando) Reporta el encargado de la Delegación 36 Arteaga Moises Zarco Cuevas de la Coordinación del Agrupamiento de seguridad vial | J84: MONITOREOS_Images/7b2e5518.Foto 1-2.150453.jpg | K84: MONITOREOS_Images/7b2e5518.Foto 2-2.150453.jpg | L84: 20 | M84: 1 | O84: 1 | P84: 0 | Q84: 15 | R84: 10 | S84: LAZARO CARDENAS | T84: MONITOREOS
A85: 3c4e6cdb | B85: 3c4e6cdb | C85: ZAMORA - ZAMORA | D85: OFICINAS GUBERNAMENTALES | E85: 46129 | F85: 0.37865741 | I85: GUARDIA CIVIL COORDINACIÓN DEL AGRUPAMIENTO DE SEGURIDAD VIAL UNIDAD DE DELEGACIÓNES REGIÓN ZAMORA ASUNTO: MONITOREO DE OFICINAS DE GOBIERNOS ESTATALES Y MUNICIPALES. VIERNES 17 DE ABRIL 2026 09: 00 HRS . Guardia Civil, Seguridad Vial Informa que se monitorean las diferentes, Instalaciones donde se encuentra laborando las dependencias estatales como lo son las recaudadoras de Impuestos Rentas La misma se encuentra en Presidencia Municipal y El Centro Comerciales de Plaza Madero, por lo que se encuentran laborando con Normalidad, para su superior Conocimiento. Informa el Agente de Seguridad vial José Alberto Torres Villalpando con tres más en la unidad 04- 189 Reporta el encargado de la delegacion el Cmte. Alfredo Velázquez González . De la Coordinación de Agrupamientos de Seguridad vial | J85: MONITOREOS_Images/3c4e6cdb.Foto 1-2.150931.jpg | K85: MONITOREOS_Images/3c4e6cdb.Foto 2-2.150931.jpg | L85: 0 | M85: 4 | O85: 1 | P85: 0 | Q85: 1 | R85: 27 | S85: ZAMORA | T85: MONITOREOS
A86: e185d2cf | B86: e185d2cf | C86: ZITACUARO - MARAVATIO | D86: OFICINAS GUBERNAMENTALES | E86: 46129 | F86: 0.37767361 | I86: Guardia Civil Coordinación del Agrupamiento de Seguridad Vial Unidad de Delegaciones Región Zitácuaro Delegación Maravatío 17/04/26 09:00 Asunto: Monitoreo de Oficinas Estatales Por medio de la presente se informa que la oficina de *la administración de rentas "SATMICH",* se encuentra laborando en su total normalidad. Reportando hasta el momento sin novedad alguna. Informa la Unidad 3280 a cargo de Ricardo Heriberto Tapia López, con Mario González Vallesteros agentes viales, de la Delegación de Seguridad Vial de Maravatío. Reportó el encargado de la delegación Jose Luis Arvizu Zamora, de la coordinación del Agrupamiento de Seguridad Vial Maravatío. | J86: MONITOREOS_Images/e185d2cf.Foto 1-2.150954.jpg | K86: MONITOREOS_Images/e185d2cf.Foto 2-2.150954.jpg | L86: 0 | M86: 3 | O86: 2 | P86: 0 | Q86: 8 | R86: 36 | S86: ZITACUARO | T86: MONITOREOS
... A94: c7481141 | B94: c7481141 | C94: JIQUILPAN - BRISEÑAS | D94: GASOLINERAS | E94: 46129 | F94: 0.38974537 | I94: *Guardia Civil* *Coordinación del Agrupación de Seguridad Vial* *Región Jiquilpan* *Delegación 25 Briseñas* *VIERNES 17 DE ABRIL DEL 2026* *ASUNTO* Monitoreo en Gasolineras Para conocimiento de la superioridad, me permito informar que se realizan Monitoreos en gasolineras del Municipio de Briseñas para detectar y evitar conductas delictivas. *Realizó la función* JOSE DE JESÚS ALVAREZ CHÁVEZ a bordo de la unidad oficial 04-179 de Seguridad vial. REPORTA EL ENCARGADO DE LA DELEGACIÓN *JOSE DE JESÚS ÁLVAREZ CHÁVEZ* DE LA COORDINACIÓN DEL AGRUPAMIENTO DE SEGURIDAD VIAL. | J94: MONITOREOS_Images/c7481141.Foto 1-2.152246.jpg | K94: MONITOREOS_Images/c7481141.Foto 2-2.152246.jpg | L94: 8 | M94: 1 | O94: 1 | P94: 0 | Q94: 14 | R94: 43 | S94: JIQUILPAN | T94: MONITOREOS
A95: 45ef55d8 | B95: 45ef55d8 | C95: COALCOMAN - COALCOMAN | D95: OFICINAS GUBERNAMENTALES | E95: 46129 | F95: 0.39431713 | I95: *Guardia Civil* *Unidad de Delegaciónes* *Región Coalcomán* *Delegación 030 Coalcomán *Viernes 17 de abril del 2026* 09:25 horas. *Asunto:* Monitoreo de dependencias públicas. Por medio de la presente me permito informar a mi superioridad, que se realizó un monitoreo por las dependencias públicas como son Rentas del Estado, Registro Civil, y presidencia municipal laboran con normalidad. *Elementos participantes* 1-.Sergio Suárez Jiménez. *Pie tierra.* Lo que me permito informar Respetuosamente Integrante de la coordinación de Seguridad Vial Estatal delegación 030 región Coalcomán Cmte. Leonardo Rolón Meraz | J95: MONITOREOS_Images/45ef55d8.Foto 1-2.152920.jpg | K95: MONITOREOS_Images/45ef55d8.Foto 2-2.152920.jpg | L95: 0 | M95: 1 | N95: Sergio Suárez Jiménez. | O95: 0 | P95: 0 | Q95: 0 | R95: 11 | S95: COALCOMAN | T95: MONITOREOS
A96: 1b6f9288 | B96: 1b6f9288 | C96: JIQUILPAN - BRISEÑAS | D96: AVENIDAS | E96: 46129 | F96: 0.39403935 | I96: **GUARDIA CIVIL* *COORDINACIÓN DEL AGRUPAMIENTO DE SEGURIDAD VIAL* *UNIDAD DE DELEGACIONES* *REGIÓN JIQUILPAN* *DELEGACIÓN 25 BRISEÑAS* *VIERNES 17 de ABRIL DEL 2026* *Asunto*:*monitoreo de carreteras* Para conocimiento de la superioridad me permite se monitoreo la carretera Briseñas - Sahuayo Y Briseñas -Zamora al momento encontrándose sin novedad de relevancia para conocimiento del mando Unidad:04-179 REPORTA EL ENCARGADO DE LA DELEGACIÓN *JOSE DE JESÚS ÁLVAREZ CHÁVEZ* DE LA COORDINACIÓN DEL AGRUPAMIENTO DE SEGURIDAD VIAL | J96: MONITOREOS_Images/1b6f9288.Foto 1-2.152945.jpg | K96: MONITOREOS_Images/1b6f9288.Foto 2-2.152945.jpg | L96: 8 | M96: 1 | O96: 1 | P96: 0 | Q96: 14 | R96: 43 | S96: JIQUILPAN | T96: MONITOREOS
A97: 2dd8b423 | B97: 2dd8b423 | C97: LA PIEDAD - PASTOR ORTIZ | D97: OFICINAS GUBERNAMENTALES | E97: 46129 | F97: 0.39805556 | I97: Guardia Civil Coordinación del Agrupamiento de Seguridad Vial Unidad de Delegaciónes Región La Piedad Delegación 038 Pastor Ortiz *Viernes 17 de Abril del 2026* 09:35 Horas. Asunto: Monitoreo Oficinas Gubernamentales. Se realizan monitoreo en el municipio de Pastor Ortiz en las Oficinas Gubernamentales como Presidencia Municipal, Registro Civil y Receptoria de Rentas. Sin novedad. QUEDANDO PENDIENTES Y A LA ORDEN Reporta el Encargado de la Delegación de Pastor Ortiz de la Coordinación del Agrupamiento de Seguridad Vial José Antonio Martinez Corona, | J97: MONITOREOS_Images/2dd8b423.Foto 1-2.153335.jpg | K97: MONITOREOS_Images/2dd8b423.Foto 2-2.153335.jpg | L97: 0 | M97: 1 | O97: 0 | P97: 0 | Q97: 0 | S97: LA PIEDAD | T97: MONITOREOS
A98: 134823b8 | B98: 134823b8 | C98: ZAMORA - JACONA | D98: OFICINAS GUBERNAMENTALES | E98: 46129 | F98: 0.40283565 | I98: G U A R D I A C I V I L COORDINACION DEL AGRUPAMIENTO DE SEGURIDAD VIAL UNIDAD DE DELEGACIÓNES REGION ZAMORA DELEGACIÓN JACONA VIERNES 17 DE ABRIL DEL 2026 09:30 HORAS Asunto: Monitoreo de oficinas de Gobierno Estatales y Municipales Por medio de la presente se informa a la superioridad que se monitorean las diferentes oficinas de gobierno, estatales y municipales, así mismo se informa que Presidencia Municipal, Reseptoria de Rentas y Registro Civil, Se encuentran laborando con normalidad, siendo esta la novedad al momento. Elementos Pie Tierra (02) 1.- Alfredo Ayala Zúñiga 2.- Pedro Ortiz García Reporta el Cmdte, Francisco Javier Armas Ochoa encargado de la delegación No. 022, de Jacona, de la Coordinación del Agrupamiento de Seguridad Vial. | J98: MONITOREOS_Images/134823b8.Foto 1-2.154132.jpg | K98: MONITOREOS_Images/134823b8.Foto 2-2.154132.jpg | L98: 0 | M98: 2 | O98: 1 | P98: 0 | Q98: 11 | R98: 28 | S98: ZAMORA | T98: MONITOREOS
A99: 4b816c99 | B99: 4b816c99 | C99: ZITACUARO - TLALPUJAHUA | D99: OFICINAS GUBERNAMENTALES | E99: 46129 | F99: 0.41209491 | I99: GUARDIA CIVIL COORDINACIÓN DEL AGRUPAMIENTO DE SEGURIDAD VIAL UNIDAD DE DELEGACIONES REGIÓN ZITÁCUARO DELEGACIÓN 31 TLALPUJAHUA VIERNES 17 DE ABRIL DEL 2026 09:50 HORAS ASUNTO: Monitoreo a Oficinas Gubernamentales Para conocimiento de la superioridad, se informa que se realizó el monitoreo en las diversas oficinas gubernamentales de la cabecera municipal, con el objetivo de detectar manifestaciones y prevenir cualquier delito. OFICINAS REVISADAS *OFICINA DE RENTAS:* LABORANDO CON NORMALIDAD *H. AYUNTAMIENTO:* LABORANDO CON NORMALIDAD *REGISTRO CIVIL:* LABORANDO CON NORMALIDAD Reporta el encargado de la Delegación Cmte. Alejandro Mario Medina Márquez De la Coordinación del Agrupamiento de Seguridad Vial. | J99: MONITOREOS_Images/4b816c99.Foto 1-2.155344.jpg | K99: MONITOREOS_Images/4b816c99.Foto 2-2.155344.jpg | L99: 0 | M99: 1 | O99: 1 | P99: 0 | Q99: 2 | R99: 39 | S99: ZITACUARO | T99: MONITOREOS
A100: d8d244a7 | B100: d8d244a7 | C100: LA PIEDAD - PURUANDIRO | D100: OFICINAS GUBERNAMENTALES | E100: 46129 | F100: 0.41592593 | I100: *Guardia Civil* *Coordinación de Seguridad Vial* *Unidad de delegaciones* *Region la Piedad* *Delegación # 18 Puruandiro* *Fecha* Viernes 17 de Abril del 2026. *Tema:* Monitoreo de oficinas gubernamentales. *Hora:* 09:25 hrs Por medio de la presente me permito informar, que se realiza monitoreo en oficinas gubernamentales, administración de rentas, presidencia municipal, y juzgados de 1ra instancia *Administración de rentas* Actividades normales* *Presidencia Municipal* Actividades normales *Juzgados* actividades normales Elementos : Jorge Luis Torres Robledo y Elizabeth Martínez González. Unidad : 3249 Reporta el encargado de la delegación no. 18 de puruandiro de la coordinacion del agrupamiento de Seguridad vial cmte. Jorge Luis Torres Robledo. | J100: MONITOREOS_Images/d8d244a7.Foto 1-2.155950.jpg | K100: MONITOREOS_Images/d8d244a7.Foto 2-2.155950.jpg | L100: 0 | M100: 2 | O100: 1 | P100: 0 | Q100: 5 | R100: 46 | S100: LA PIEDAD | T100: MONITOREOS
A101: ef3fb76e | B101: ef3fb76e | C101: JIQUILPAN - JIQUILPAN | D101: GASOLINERAS | E101: 46129 | F101: 0.4212963 | I101: *G U A R D I A C I V I L* *COORDINACIÓN DEL AGRUPAMIENTO DE SEGURIDAD VIAL* *UNIDAD DE DELEGACIONES* *REGIÓN JIQUILPAN* *DELEGACIÓN 05 JIQUILPAN* *VIERNES 17 DE ABRIL DEL 2026* *09:32 HORAS* *Asunto: Monitoreo a Gasolineras* Por medio de la presente se informa a la Superioridad, que se encuentra sin novedad el recorrido de Prevención y Vigilancia en Gasolineras de este municipio de Jiquilpan. Asi mismo quedamos pendientes para informar cualquier novedad de relevancia. Se realiza la función en la Unidad 03-600. Reporta el Encargado de la Delegación, Jesús Manuel Martínez Ochoa, de la Coordinación del Agrupamiento de Seguridad Vial | J101: MONITOREOS_Images/ef3fb76e.Foto 1-2.160708.jpg | K101: MONITOREOS_Images/ef3fb76e.Foto 2-2.160708.jpg | L101: 4 | M101: 3 | O101: 1 | P101: 0 | Q101: 18 | R101: 41 | S101: JIQUILPAN | T101: MONITOREOS
A102: 1ca2e919 | B102: 1ca2e919 | C102: ZAMORA - ZACAPU | D102: OFICINAS GUBERNAMENTALES | E102: 46129 | F102: 0.42287037 | I102: *GUARDIA CIVIL* *COORDINACION DEL AGRUPAMIENTO DE SEGURIDAD VIAL* *UNIDAD DE DELEGACIÓNES* *REGION ZAMORA* *DELEGACIÓN 02 ZACAPU* *Viernes 17 de abril de 2026* *HORA:* 09:42 Horas. *ASUNTO:* Monitoreo de oficinas Gubernamentales. Por medio de la presente se informa que al momento se llevan a cabo monitoreo en la presidencia municipal así como la oficina de Rentas del Estado, se encuentran laborando con Normalidad. Unidad: 16-724 Cristian Armando Arceo Estrada Reporta el encargado de la Delegación Rigoberto Peralta Hernández, de la coordinación de agrupamiento de seguridad vial. | J102: MONITOREOS_Images/1ca2e919.Foto 1-2.160944.jpg | K102: MONITOREOS_Images/1ca2e919.Foto 2-2.160944.jpg | L102: 0 | M102: 1 | O102: 1 | P102: 0 | Q102: 10 | R102: 29 | S102: ZAMORA | T102: MONITOREOS
A103: 39765f74 | B103: 39765f74 | C103: MORELIA - SANTA CLARA | D103: OFICINAS GUBERNAMENTALES | E103: 46129 | F103: 0.42694444 | I103: *G U A R D I A C I V I L* *COORDINACIÓN DEL AGRUPAMIENTO DE SEGURIDAD VIAL* *UNIDAD DE DELEGACIONES* *REGIÓN MORELIA* *DELEGACIÓN 45 DE SANTA CLARA DEL COBRE* *VIERNES 17 DE ABRIL DE 2026* *10:05 HORAS* *Asunto: Monitoreo de Oficinas Gubernamentales* Por medio de la Presente se informa, que con esta fecha y hora se realiza Monitoreo de oficinas gubernamentales, Receptoría de Rentas y Registro Civil del estado, instaladas en el interior del palacio municipal de Santa Clara del Cobre, municipio de Salvador Escalante, las cuales se encuentran laborando de manera normal. Personas alcanzadas: 20 Sin Novedad Informan elementos de Seguridad 1.- Frincka Raziel Contreras 2.- Leopoldo Pérez Correa Reporta el encargado de la Delegación 45 de Santa Santa Clara del Cobre, el *Cmdte Sub Oficial Calixto Vázquez Chávez* de la coordinación del Agrupamiento de Seguridad Vial | J103: MONITOREOS_Images/39765f74.Foto 1-2.161526.jpg | K103: MONITOREOS_Images/39765f74.Foto 2-2.161526.jpg | L103: 20 | M103: 2 | O103: 0 | P103: 0 | Q103: 0 | R103: 25 | S103: MORELIA | T103: MONITOREOS
A104: 16333735 | B104: 16333735 | C104: LA PIEDAD - VISTA HERMOSA | D104: PERIFÉRICOS | E104: 46129 | F104: 0.42998843 | I104: *Guardia Civil* *Coordinacion del Agrupamiento de Seguridad Vial* *Unidad de Delegaciones* *Región La Piedad* *Delegación 54 Vista Hermosa* *Viernes 17 de Abril de 2026.* 10:00 horas Ubicación Casetas Vista Hermosa-Guadalajara y Guadalajara-Vista Hermosa. *Asunto:* Monitoreo de Casetas de Peaje. *Estatus:* 🟢 *LIBRE* Por medio de la presente se informa que al momento se realizan monitoreos en las casetas de peaje, las cuales se encuentran laborando sin novedad. *NOTA* Monitoreo se realiza abordó de la unidad 019-79 de Transito Municipal a cargo de la Oficial Yolanda Quiroz 1 Elemento más de Seguridad Vial. Reporta la Encargado de la Delegación 54 Vista Hermosa de la Coordinacion del Agrupamiento de Seguridad Vial. Cmnte. Denise Azucena Morales Briseño | J104: MONITOREOS_Images/16333735.Foto 1-2.161944.jpg | K104: MONITOREOS_Images/16333735.Foto 2-2.161944.jpg | L104: 10 | M104: 2 | O104: 0 | P104: 0 | Q104: 11 | R104: 5 | S104: LA PIEDAD | T104: MONITOREOS
A105: 06c6456a | B105: 06c6456a | C105: ZITACUARO - CIUDAD HIDALGO | D105: OFICINAS GUBERNAMENTALES | E105: 46129 | F105: 0.40571759 | I105: GUARDA CIVIL COORDINACIÓN DEL AGRUPAMIENTO DE SEGURIDAD VIAL UNIDAD DE DELEGACIONES REGIÓN ZITACUARO DELEGACIÓN 09 CIUDAD HIDALGO VIERNES 17 DE ABRIL DE 2026 09:25 HORAS Asunto: Monitoreo de oficinas gubernamentales Por medio del presente se informa que se realizaron recorridos y monitoreo en las oficinas gubernamentales de este municipio de Ciudad Hidalgo. •La Oficina de Receptoría de Rentas del Estado se encuentra Laborando con normalidad. •La Presidencia Municipal se encuentra laborando con normalidad. •El Registro Civil, oficialía 034-01 se encuentra laborando con normalidad. Informa el suscrito Jesús Benito Vázquez Chávez y Paulina Viridiana Mondragón Alanis. a bordo de la unidad 03-641. Kilometraje recorrido: 22 Personas alcanzadas: 30 Reporta el Encargado de la delegación Cmte Jesus Benito Vázquez Chávez De la coordinación del Agrupamiento de Seguridad Vial | J105: MONITOREOS_Images/06c6456a.Foto 1-2.162857.jpg | K105: MONITOREOS_Images/06c6456a.Foto 2-2.162857.jpg | L105: 30 | M105: 2 | O105: 1 | P105: 0 | Q105: 22 | R105: 38 | S105: ZITACUARO | T105: MONITOREOS
A106: 13733f51 | B106: 13733f51 | C106: ZITACUARO - ZITACUARO | D106: OFICINAS GUBERNAMENTALES | E106: 46129 | F106: 0.44111111 | I106: G U A R D I A C I V I L COORDINACIÓN DEL AGRUPAMIENTO DE SEGURIDAD VIAL UNIDAD DE DELEGACIONES REGIÓN ZITÁCUARO DELEGACIÓN 10 ZITÁCUARO VIERNES 17 DE ABRIL DE 2026 Asunto: Monitoreo. Por medio de la presente se informa que al momento se realiza monitoreo del Palacio Municipal. Sin Novedad A cargo: Marisol Hernández Vieyra Elementos de Apoyo: Lázaro Bernal Marin Enoc Martínez Rogel Juan Alonso Jerónimo Unidad: 3180 Kilómetros: 09 Reporta el Encargado de la Delegación 10 Zitácuaro de la Coordinación del Agrupamiento de Seguridad Vial. Cmte.. José María Mendoza Farías. | J106: MONITOREOS_Images/13733f51.Foto 1-2.163646.jpg | K106: MONITOREOS_Images/13733f51.Foto 2-2.163646.jpg | L106: 0 | M106: 4 | O106: 1 | P106: 0 | Q106: 9 | R106: 35 | S106: ZITACUARO | T106: MONITOREOS
A107: d8af6302 | B107: d8af6302 | C107: ZITACUARO - ZITACUARO | D107: OFICINAS GUBERNAMENTALES | E107: 46129 | F107: 0.44256944 | I107: G U A R D I A C I V I L COORDINACIÓN DEL AGRUPAMIENTO DE SEGURIDAD VIAL UNIDAD DE DELEGACIONES REGIÓN ZITÁCUARO DELEGACIÓN 10 ZITÁCUARO VIERNES 17 DE ABRIL DEL 2026 Asunto: Monitoreo Rentas Por medio de la presente se informa que al momento se realiza monitoreo de la administración de rentas. Receptoría De Rentas Sin Novedad A cargo: Marisol Hernández Vieyra Elementos de Apoyo Luis Alonso Jerónimo Lázaro Bernal Marín Enoc Martínez Rogel Unidad: 3180 Km. (8) Reporto el Encargado de la Delegación 10 Zitácuaro de la Coordinación de Agrupamiento de Seguridad Vial Cmte. José María Mendoza Farías | J107: MONITOREOS_Images/d8af6302.Foto 1-2.163901.jpg | K107: MONITOREOS_Images/d8af6302.Foto 2-2.163901.jpg | L107: 0 | M107: 4 | O107: 1 | P107: 0 | Q107: 8 | R107: 35 | S107: ZITACUARO | T107: MONITOREOS
A108: 193da15e | B108: 193da15e | C108: LA PIEDAD - LA PIEDAD | D108: AVENIDAS | E108: 46129 | F108: 0.45770833 | I108: GUARDIA CIVIL* *COORDINACIÓN DEL AGRUPAMIENTO DE SEGURIDAD VIAL* *UNIDAD DE DELEGACIÓNES* *REGION LA PIEDAD* *DELEGACIÓN LA PIEDAD* *VIERNES 17 DE ABRIL DE 2026* *09:00 HORAS* *ASUNTO:* Monitoreo de carreteras Por medio de la presente se informar que se encuentran sin novedad los recorridos de monitoreo y vigilancia en: carreteras y caminos det nuestra jurisdicción. Estando todo sin novedad Informa la Unidad 3405 a cargo del Pol. Arturo Buenrostro Rodríguez de la Delegación de Seguridad Vial de La Piedad. Reporta el encargado de la Delegación Pol. 2° J. Jesús Arévalo León de la coordinación del Agrupamiento de Seguridad Vial. | J108: MONITOREOS_Images/193da15e.Foto 1-2.165951.jpg | K108: MONITOREOS_Images/193da15e.Foto 2-2.165951.jpg | L108: 0 | M108: 3 | O108: 1 | P108: 0 | Q108: 4 | R108: 4 | S108: LA PIEDAD | T108: MONITOREOS
A109: 5f372436 | B109: 5f372436 | C109: URUAPAN - PARACHO | D109: OFICINAS GUBERNAMENTALES | E109: 46129 | F109: 0.41488426 | I109: *GUARDIA CIVIL* *COORDINACIÓN DEL AGRUPAMIENTO DE SEGURIDAD VIAL* *UNIDAD DE DELEGACIONES* *REGIÓN URUAPAN* *DELEGACIÓN 026 PARACHO* *VIERNES 17 DE ABRIL DE 2026* *Asunto:* Monitoreo de oficinas de gobierno. *11:00 Horas* Por medio de la presente se informa a la superioridad que, se monitorean las diferentes oficinas de Gobierno, Estatales y Municipales de las cuales son: Presidencia Municipal, Receptoría de Rentas y Registro Civil, laborando con normalidad. *INforma unidad 3142* a cargo del elemento Agustín Baltazar Avalos, junto a un elemento de la Delegación de Seguridad Vial de Paracho. Reporta el encargado de la Delegación 026 de Paracho, Marco Antonio Estrada Silva, de la Coordinación del Agrupamiento de Seguridad Vial. | J109: MONITOREOS_Images/5f372436.Foto 1-2.170003.jpg | K109: MONITOREOS_Images/5f372436.Foto 2-2.170003.jpg | L109: 0 | M109: 2 | O109: 1 | P109: 0 | Q109: 2 | R109: 51 | S109: URUAPAN | T109: MONITOREOS
A110: 74dc2599 | B110: 74dc2599 | C110: LA PIEDAD - LA PIEDAD | D110: OFICINAS GUBERNAMENTALES | E110: 46129 | F110: 0.45849537 | I110: GUARDIA CIVIL* *COORDINACIÓN DEL AGRUPAMIENTO DE SEGURIDAD VIAL* *UNIDAD DE DELEGACIÓNES* *REGION LA PIEDAD* *DELEGACIÓN LA PIEDAD* *VIERNES 17 DE ABRIL DE 2026* *09:40 HORAS* *ASUNTO:* Oficinas gubernamentales Por medio de la presente se informar que se encuentran sin novedad los recorridos de monitoreo y vigilancia en: oficinas de rentas y presidencia municipal de este municipio. Estando todo sin novedad Informa la Unidad 3405 a cargo del Pol. Arturo Buenrostro Rodríguez de la Delegación de Seguridad Vial de La Piedad. Reporta el encargado de la Delegación Pol. 2° J. Jesús Arévalo León de la coordinación del Agrupamiento de Seguridad Vial. | J110: MONITOREOS_Images/74dc2599.Foto 1-2.170043.jpg | K110: MONITOREOS_Images/74dc2599.Foto 2-2.170043.jpg | L110: 0 | M110: 3 | O110: 1 | P110: 0 | Q110: 11 | R110: 4 | S110: LA PIEDAD | T110: MONITOREOS
A111: ac9c4c2f | B111: ac9c4c2f | C111: HUETAMO - CARACUARO | D111: OFICINAS GUBERNAMENTALES | E111: 46129 | F111: 0.45924769 | I111: *Guardia Civil.* *Coordinación del Agrupamiento de Seguridad Vial.* *Unidad de Delegaciones* *Región Huetamo.* *Delegación 55 Carácuaro.* *Viernes 17 de abril de 2026.* 11:00 horas. Asunto: *Monitoreo a oficinas gubernamentales.* Reporta el encargado de la Delegación 055 Carácuaro de la Coordinación del Agrupamiento de Seguridad Vial, se realiza monitoreo en las diferentes oficinas gubernamentales de esta cabecera municipal, mismas que se encuentran libres de manifestaciones y laborando de manera normal: *• Receptoría de Rentas.* *• H. Ayuntamiento.* *• Registro Civil.* *Atiende:* Yesi Rodríguez López. Unidad 03-623. Reportó el Encargado de la Seguridad Vial 55 Carácuaro: Cmdte. Emmanuel Reynoso Gómez. | J111: MONITOREOS_Images/ac9c4c2f.Foto 1-2.170203.jpg | K111: MONITOREOS_Images/ac9c4c2f.Foto 2-2.170203.jpg | L111: 0 | M111: 1 | O111: 1 | P111: 0 | Q111: 0 | R111: 18 | S111: HUETAMO | T111: MONITOREOS
A112: 5dd6f596 | B112: 5dd6f596 | C112: ZAMORA - ZAMORA | D112: GASOLINERAS | E112: 46129 | F112: 0.46134259 | I112: *GUARDIA CIVIL* *COORDINACIÓN DE AGRUPAMIENTO DE SEGURIDAD VIAL* *UNIDAD DE DELEGACIONES* *REGION ZAMORA* *VIERNES 17- ABRIL -2026* *ASUNTO: MONITOREO DE GASOLINERAS* 10:45HRS. _Guardia Civil "Seguridad Vial"_ informa que se realizan recorridos de prevención en las gasolineras, de este municipio sin incidencias que reportar durante el monitoreo. Informa: C. José Alberto Torres Villalpando con 01 más abordo de la unidad 04-189. Reporta el encargado de la delegación el C. Alfredo Velázquez González de la coordinación del agrupamiento de seguridad vial. | J112: MONITOREOS_Images/5dd6f596.Foto 1-2.170455.jpg | K112: MONITOREOS_Images/5dd6f596.Foto 2-2.170455.jpg | L112: 0 | M112: 2 | O112: 1 | P112: 0 | Q112: 6 | R112: 27 | S112: ZAMORA | T112: MONITOREOS
A113: ae4ed686 | B113: ae4ed686 | C113: URUAPAN - TARETAN | D113: PERIFÉRICOS | E113: 46129 | F113: 0.46974537 | I113: *GUARDIA CIVIL* *COORDINACIÓN DEL AGRUPAMIENTO DE SEGURIDAD VIAL* *UNIDAD DE DELEGACIONES* *REGIÓN URUAPAN* *DELEGACIÓN TARETAN #27* *VIERNES 17 DE ABRIL DEL 2026* *ASUNTO: MONITOREO DE CASETA DE TARETAN* *11:00hrs* *Guardia Civil Seguridad Vial Estatal* para conocimiento de los mandos me permito informar que se monitorea la caseta de Taretan de la autopista siglo XXI con la finalidad de detectar posibles bloqueos hasta el momento se encuentra sin novedad la caseta de peaje. *Unidad 16-864* *Kilómetros recorridos 6* *Pnas.alcanzadas 4* *Informa* *Respetuosamente* *Encargado Dionicio Díaz Rebolledo de la Seguridad Vial Estatal de Taretan #27* | J113: MONITOREOS_Images/ae4ed686.Foto 1-2.171825.jpg | K113: MONITOREOS_Images/ae4ed686.Foto 2-2.171825.jpg | L113: 4 | M113: 1 | O113: 1 | P113: 0 | Q113: 6 | R113: 49 | S113: URUAPAN | T113: MONITOREOS
A114: 75496f1e | B114: 75496f1e | C114: LA PIEDAD - YURECUARO | D114: AVENIDAS | E114: 46129 | F114: 0.50140046 | I114: Guardia Civil Coordinacion del Agrupamiento de Seguridad Vial Unidad de Delegaciones Región La Piedad Delegación 21 YURÉCUARO Viernes 17 de Abril de 2026. 12:00 horas Ubicación carretera federal perteneciente al municipio de YURECUARO con límites al municipio de Tanhuato. Asunto: Monitoreo de carreteras. Estatus: 🟢 LIBRE Por medio de la presente se informa que al momento se realizan monitoreos en la carretera federal Yurécuaro/ Tanhuato.las cuales se encuentran con flujo normal y sin novedad. NOTA Monitoreo se realiza abordó de la unidad 03-625 A cargo de el Cmnte Gustavo Saavedra Ramirez de Seguridad Vial. Reporta la Encargado de la Delegación 21 Yurécuaro de la Coordinacion del Agrupamiento de Seguridad Vial. Cmnte. Gustavo Saavedra Ramirez. | J114: MONITOREOS_Images/75496f1e.Foto 1-2.180236.jpg | K114: MONITOREOS_Images/75496f1e.Foto 2-2.180236.jpg | L114: 0 | M114: 1 | O114: 1 | P114: 0 | Q114: 25 | R114: 6 | S114: LA PIEDAD | T114: MONITOREOS
A115: 3c50e968 | B115: 3c50e968 | C115: HUETAMO - NOCUPETARO | D115: OFICINAS GUBERNAMENTALES | E115: 46129 | F115: 0.50559028 | I115: Guardia Civil Agrupamiento de Seguridad Vial* Región Huetamo Delegación 050 Nocupetaro Jueves 16/04/2026 Hora; 11:40 horas Se realizan monitoreos en el municipio de Nocupetaro en las oficinas de gobierno con la finalidad de inhibir conductas delictivas y vereficar que no esten bloqueadas ,para informar en tiempo. *MONITOREOS:* •PRESIDENCIA MUNICIPAL *SIN NOVEDAD* •RECEPTORIA DE RENTAS SATMICH. *SIN NOVEDAD* •CORREOS *SIN NOVEDAD* •TELEGRAFOS *SIN NOVEDAD* •REGISTRO CIVIL *SIN NOVEDAD* *Informa la unidad 04-350 a cargo del oficial: Gustavo Calderón Gordillo.y Reynaldo Mendez Ortega *Reportó, Cmdte. Jose Carmen Mondragón Posadas ,Encargado de la Delegacion de Seguridad Vial Nocupetaro*. | J115: MONITOREOS_Images/3c50e968.Foto 1-2.180908.jpg | K115: MONITOREOS_Images/3c50e968.Foto 2-2.180908.jpg | L115: 20 | M115: 2 | O115: 1 | P115: 0 | Q115: 1 | R115: NOCUPETARO | S115: HUETAMO | T115: MONITOREOS
A116: c846ca7c | B116: c846ca7c | C116: URUAPAN - TARETAN | D116: PERIFÉRICOS | E116: 46129 | F116: 0.48990741 | I116: *GUARDIA CIVIL* *COORDINACIÓN DEL AGRUPAMIENTO DE SEGURIDAD VIAL* *UNIDAD DE DELEGACIONES* *REGIÓN URUAPAN* *DELEGACIÓN TARETAN #27* *VIERNES 17 DE ABRIL DEL 2026* *ASUNTO: MONITOREO DE CASETA DE TARETAN* *11:45 am.hrs* *Guardia Civil Seguridad Vial Estatal* para conocimiento de los mandos me permito informar que se continúa monitoreando la caseta de Taretan de la autopista siglo XXI con la finalidad de detectar posibles bloqueos hasta el momento se encuentra sin novedad la caseta de peaje. *Unidad 16-864* *Kilómetros recorridos 6* *Pnas.alcanzadas 5* *Informa* *Respetuosamente* *Encargado Dionicio Díaz Rebolledo de la Seguridad Vial Estatal de Taretan #27* | J116: MONITOREOS_Images/c846ca7c.Foto 1-2.181428.jpg | K116: MONITOREOS_Images/c846ca7c.Foto 2-2.181428.jpg | L116: 5 | M116: 1 | O116: 1 | P116: 0 | Q116: 6 | R116: 49 | S116: URUAPAN | T116: MONITOREOS
A117: 23d0c065 | B117: 23d0c065 | C117: MORELIA - ZINAPECUARO | D117: VÍAS FÉRREAS | E117: 46129 | F117: 0.52628472 | I117: G U A R D I A C I V I L COORDINACIÓN DEL AGRUPAMIENTO DE SEGURIDAD VIAL UNIDAD DE DELEGACIONES REGIÓN MORELIA DELEGACIÓN ZINAPECUARO 17/04/2026 12:33 HORAS Asunto Monitoreo de Vías Ferreas Para conocimiento de la superioridad, el personal de esta delegación informa que se realiza monitoreo de Vías Ferreas en la localidad de Tzintzimeo municipio cipio de Álvaro Obregón Reportando sin novedad hasta el momento Kilómetros recorridos 36 Reporta al encargado de la delegación el C. Jose Rolando Ojeda Ortiz de la coordinación del Agrupamiento de Seguridad Vial | J117: MONITOREOS_Images/23d0c065.Foto 1-2.184102.jpg | K117: MONITOREOS_Images/23d0c065.Foto 2-2.184102.jpg | L117: 0 | M117: 2 | O117: 1 | P117: 0 | Q117: 36 | R117: 20 | S117: MORELIA | T117: MONITOREOS
A118: a41f4b68 | B118: a41f4b68 | C118: JIQUILPAN - JIQUILPAN | D118: BANCOS | E118: 46129 | F118: 0.48140046 | I118: *G U A R D I A C I V I L* *COORDINACIÓN DEL AGRUPAMIENTO DE SEGURIDAD VIAL* *UNIDAD DE DELEGACIONES* *REGIÓN JIQUILPAN* *DELEGACIÓN 05 JIQUILPAN* *VIERNES 17 DE ABRIL DEL 2026* *11:06 HORAS* *Asunto: Monitoreo a Bancos* Por medio de la presente se informa a la Superioridad, que se encuentra sin novedad el recorrido de Prevención y Vigilancia en Cajeros Automáticos y sucursales de Bancos de este municipio de Sahuayo. Asi mismo quedamos pendientes para informar cualquier novedad de relevancia. Se realiza la función en la Unidad 03-600. Reporta el Encargado de la Delegación, Jesús Manuel Martínez Ochoa, de la Coordinación del Agrupamiento de Seguridad Vial | J118: MONITOREOS_Images/a41f4b68.Foto 1-2.185025.jpg | K118: MONITOREOS_Images/a41f4b68.Foto 2-2.185025.jpg | L118: 8 | M118: 3 | O118: 1 | P118: 0 | Q118: 12 | R118: 41 | S118: JIQUILPAN | T118: MONITOREOS
A119: fb48b2d3 | B119: fb48b2d3 | C119: JIQUILPAN - JIQUILPAN | D119: AVENIDAS | E119: 46129 | F119: 0.53550926 | I119: *G U A R D I A C I V I L* *COORDINACIÓN DEL AGRUPAMIENTO DE SEGURIDAD VIAL* *UNIDAD DE DELEGACIONES* *REGIÓN JIQUILPAN* *DELEGACIÓN 05 JIQUILPAN* *VIERNES 17 DE ABRIL DEL 2026* *12:49 HORAS* *Asunto: Monitoreo a Avenidas y Carreteras* Por medio de la presente se informa a la Superioridad, que se encuentra sin novedad el recorrido de Prevención y Vigilancia en avenidas, carreteras, accesos y salidas al municipio de Sahuayo. Asi mismo quedamos pendientes para informar cualquier novedad de relevancia. Se realiza la función a bordo de la Unidad 04-198 . Reporta el Encargado de la Delegación, Jesús Manuel Martínez Ochoa, de la Coordinación del Agrupamiento de Seguridad Vial | J119: MONITOREOS_Images/fb48b2d3.Foto 1-2.185148.jpg | K119: MONITOREOS_Images/fb48b2d3.Foto 2-2.185148.jpg | L119: 6 | M119: 3 | O119: 1 | P119: 0 | Q119: 22 | R119: 41 | S119: JIQUILPAN | T119: MONITOREOS
A120: 0954bc02 | B120: 0954bc02 | C120: HUETAMO - CARACUARO | D120: BANCOS | E120: 46129 | F120: 0.54315972 | I120: *Guardia Civil.* *Coordinación del Agrupamiento de Seguridad Vial.* *Unidad de Delegaciones.* *Región Huetamo.* *Delegación 55 Carácuaro.* Viernes 17 de abril de 2026 12:30 horas. Asunto: Monitoreo a instituciones bancarias. Reporta el encargado de la Delegación 055 Carácuaro de la Coordinación del Agrupamiento de Seguridad Vial, se realiza monitoreo en las diferentes instituciones bancarias de esta cabecera municipal, mismas que se encuentran sin novedad. Continuamos pendientes e informando. Atiende: Yesi Rodríguez López. Unidad 03-623. Reportó el Encargado de la Seguridad Vial Carácuaro: Cmdte. Emmanuel Reynoso Gómez. | J120: MONITOREOS_Images/0954bc02.Foto 1-2.190300.jpg | K120: MONITOREOS_Images/0954bc02.Foto 2-2.190300.jpg | L120: 0 | M120: 1 | O120: 1 | P120: 0 | Q120: 0 | R120: 18 | S120: HUETAMO | T120: MONITOREOS
A121: e4c47f96 | B121: e4c47f96 | C121: URUAPAN - ARIO DE ROSALES | D121: OFICINAS GUBERNAMENTALES | E121: 46129 | F121: 0.55236111 | I121: *GUARDIA CIVIL* *COORDINACION DEL AGRUPAMIENTO DE SEGURIDAD VIAL* *UNIDAD DE DELEGACIONES* *REGIÓN URUAPAN* *DELEGACIÓN 14 ARIO DE ROSALES* *FECHA:*17 ABRIL 2026 *HORA:* 9:00 hrs *Tema:* Monitoreo de Oficinas Gubernamentales. Por medio de la Presente me Permito Informar que se realiza Monitoreo en Oficinas Gubernamentales: Receptoría de Rentas, Registro hasta esta hora Civil laborando con normalidad. Personas alcansadas 12 Kilómetros Recorridos 2 *Receptoría de Rentas* Sin novedad. *Presidencia Municipal* Sin novedad. *Registro Civil* Sin novedad. Reporta el encargado de la Delegación Jose Rodrígo Álvarez Reyes de la Coordinación del Agrupamiento de Seguridad Vial. | J121: MONITOREOS_Images/e4c47f96.Foto 1-2.191752.jpg | K121: MONITOREOS_Images/e4c47f96.Foto 2-2.191752.jpg | L121: 12 | M121: 2 | O121: 1 | P121: 0 | Q121: 2 | R121: 52 | S121: URUAPAN | T121: MONITOREOS
...

Sheet ALERTA #
A3: No. | B3: CATEGORÍA | C3: ACTIVIDAD | D3: MORELIA | G3: JIQUILPAN | J3: ZAMORA | M3: LA PIEDAD | P3: URUAPAN | S3: APATZINGAN | V3: HUETAMO | Y3: COALCOMAN | AB3: ZITACUARO | AE3: LAZARO CARDENAS
A4: 1 | B4: INSTITUCIONES | C4: APOYO A EVENTOS PÚBLICOS | D4: 0 | E4: 0 | G4: 0 | H4: 0 | J4: 0 | K4: 0 | M4: 0 | N4: 0 | P4: 0 | Q4: 0 | S4: 0 | T4: 0 | V4: 0 | W4: 0 | Y4: 0 | Z4: 0 | AB4: 0 | AC4: 0 | AE4: 0 | AF4: 0
C5: APOYO A EVENTOS DEPORTIVOS | D5: 0 | E5: 0 | G5: 0 | H5: 0 | J5: 0 | K5: 0 | M5: 0 | N5: 0 | P5: 0 | Q5: 0 | S5: 0 | T5: 0 | V5: 0 | W5: 0 | Y5: 0 | Z5: 0 | AB5: 0 | AC5: 0 | AE5: 0 | AF5: 0
C6: APOYO A EVENTOS CULTURALES | D6: 0 | E6: 0 | G6: 0 | H6: 0 | J6: 0 | K6: 0 | M6: 0 | N6: 0 | P6: 0 | Q6: 0 | S6: 0 | T6: 0 | V6: 0 | W6: 0 | Y6: 0 | Z6: 0 | AB6: 0 | AC6: 0 | AE6: 0 | AF6: 0
C7: APOYO A EVENTOS RELIGIOSOS | D7: 0 | E7: 0 | G7: 0 | H7: 0 | J7: 0 | K7: 0 | M7: 0 | N7: 0 | P7: 0 | Q7: 0 | S7: 0 | T7: 0 | V7: 0 | W7: 0 | Y7: 0 | Z7: 0 | AB7: 0 | AC7: 1 | AE7: 0 | AF7: 0
C8: APOYOS A OTRAS DEPENDENCIAS (Publicas o privadas) | D8: 5 | E8: 5 | G8: 0 | H8: 0 | J8: 1 | K8: 1 | M8: 0 | N8: 0 | P8: 0 | Q8: 0 | S8: 0 | T8: 0 | V8: 0 | W8: 0 | Y8: 0 | Z8: 0 | AB8: 0 | AC8: 0 | AE8: 0 | AF8: 0
C9: ESCUELAS | D9: 8 | E9: 17 | G9: 5 | H9: 5 | J9: 7 | K9: 11 | M9: 8 | N9: 8 | P9: 7 | Q9: 7 | S9: 4 | T9: 4 | V9: 1 | W9: 4 | Y9: 0 | Z9: 2 | AB9: 15 | AC9: 17 | AE9: 3 | AF9: -10
C10: DILIGENCIAS | D10: 1 | E10: 1 | G10: 0 | H10: 0 | J10: 0 | K10: 0 | M10: 0 | N10: 0 | P10: 0 | Q10: 0 | S10: 0 | T10: 0 | V10: 0 | W10: 0 | Y10: 0 | Z10: 0 | AB10: 0 | AC10: 0 | AE10: 0 | AF10: 0
C11: OTROS TIPOS (Especificar en las novedades relevantes) | D11: 0 | E11: 0 | G11: 0 | H11: 0 | J11: 0 | K11: 0 | M11: 0 | N11: 0 | P11: 0 | Q11: 0 | S11: 0 | T11: 0 | V11: 0 | W11: 0 | Y11: 0 | Z11: 0 | AB11: 0 | AC11: 0 | AE11: 0 | AF11: 0
A12: 2 | B12: REPORTES C5i | C12: OBSTRUCCIÓN DE COCHERAS | D12: 0 | E12: 0 | G12: 0 | H12: 0 | J12: 0 | K12: 0 | M12: 0 | N12: 0 | P12: 0 | Q12: 0 | S12: 0 | T12: 0 | V12: 0 | W12: 0 | Y12: 0 | Z12: 0 | AB12: 0 | AC12: 0 | AE12: 0 | AF12: 0
C13: OTROS TIPOS DE OBSTRUCCIÓN | D13: 0 | E13: 0 | G13: 0 | H13: 0 | J13: 0 | K13: 0 | M13: 0 | N13: 0 | P13: 0 | Q13: 0 | S13: 0 | T13: 0 | V13: 0 | W13: 0 | Y13: 0 | Z13: 0 | AB13: 0 | AC13: 0 | AE13: 0 | AF13: 0
C14: ACTOS DELICTIVOS | D14: 0 | E14: 0 | G14: 0 | H14: 0 | J14: 0 | K14: 0 | M14: 0 | N14: 0 | P14: 0 | Q14: 0 | S14: 0 | T14: 0 | V14: 0 | W14: 0 | Y14: 0 | Z14: 0 | AB14: 0 | AC14: 0 | AE14: 0 | AF14: 0
C15: SINIESTROS | D15: 0 | E15: 0 | G15: 0 | H15: 0 | J15: 2 | K15: 2 | M15: 0 | N15: 0 | P15: 1 | Q15: 1 | S15: 0 | T15: 0 | V15: 0 | W15: 0 | Y15: 0 | Z15: 0 | AB15: 0 | AC15: 0 | AE15: 0 | AF15: 0
C16: HECHOS DE TRÁNSITO | D16: 1 | E16: 1 | G16: 0 | H16: 0 | J16: 1 | K16: 1 | M16: 0 | N16: 0 | P16: 0 | Q16: 0 | S16: 0 | T16: 0 | V16: 2 | W16: 2 | Y16: 0 | Z16: 0 | AB16: 1 | AC16: 1 | AE16: 0 | AF16: 0
C17: CONSENTRACION PERSONAS | D17: 0 | E17: 0 | G17: 0 | H17: 0 | J17: 0 | K17: 0 | M17: 0 | N17: 0 | P17: 0 | Q17: 0 | S17: 0 | T17: 0 | V17: 0 | W17: 0 | Y17: 0 | Z17: 0 | AB17: 0 | AC17: 0 | AE17: 0 | AF17: 0
C18: OTROS REPORTES (Especificar en las novedades relevantes) | D18: 0 | E18: 0 | G18: 0 | H18: 0 | J18: 0 | K18: 0 | M18: 0 | N18: 0 | P18: 0 | Q18: 0 | S18: 0 | T18: 0 | V18: 0 | W18: 0 | Y18: 0 | Z18: 0 | AB18: 0 | AC18: 0 | AE18: 0 | AF18: 0
A19: 3 | B19: ABANDERAMIENTOS | C19: CORTES DE CIRCULACIÓN | D19: 7 | E19: 7 | G19: 0 | H19: 0 | J19: 0 | K19: 0 | M19: 0 | N19: 0 | P19: 0 | Q19: 0 | S19: 0 | T19: 0 | V19: 1 | W19: 1 | Y19: 0 | Z19: 0 | AB19: 3 | AC19: 3 | AE19: 0 | AF19: 0
C20: ACCIDENTES | D20: 0 | E20: 0 | G20: 0 | H20: 0 | J20: 0 | K20: 1 | M20: 0 | N20: 0 | P20: 0 | Q20: 0 | S20: 0 | T20: 0 | V20: 0 | W20: 0 | Y20: 0 | Z20: 0 | AB20: 0 | AC20: 0 | AE20: 0 | AF20: 0
C21: MARCHAS | D21: 0 | E21: 0 | G21: 0 | H21: 0 | J21: 0 | K21: 0 | M21: 0 | N21: 0 | P21: 0 | Q21: 0 | S21: 0 | T21: 0 | V21: 0 | W21: 0 | Y21: 0 | Z21: 0 | AB21: 0 | AC21: 0 | AE21: 0 | AF21: 0
C22: MÍTINES | D22: 0 | E22: 0 | G22: 0 | H22: 0 | J22: 0 | K22: 0 | M22: 0 | N22: 0 | P22: 0 | Q22: 0 | S22: 0 | T22: 0 | V22: 0 | W22: 0 | Y22: 0 | Z22: 0 | AB22: 0 | AC22: 0 | AE22: 0 | AF22: 0
C23: OBRAS PÚBLICAS | D23: 0 | E23: 0 | G23: 0 | H23: 0 | J23: 0 | K23: 0 | M23: 0 | N23: 0 | P23: 0 | Q23: 0 | S23: 0 | T23: 0 | V23: 0 | W23: 0 | Y23: 0 | Z23: 0 | AB23: 2 | AC23: 2 | AE23: 0 | AF23: 0
C24: ACOMPAÑAMIENTO A CARAVANAS U OTROS | D24: 0 | E24: 0 | G24: 0 | H24: 0 | J24: 0 | K24: 0 | M24: 1 | N24: 1 | P24: 0 | Q24: 0 | S24: 0 | T24: 0 | V24: 0 | W24: 0 | Y24: 0 | Z24: 0 | AB24: 0 | AC24: 0 | AE24: 0 | AF24: 0
C25: OTROS ABANDERAMIENTOS (Especificar en las novedades relevantes) | D25: 0 | E25: 0 | G25: 0 | H25: 0 | J25: 0 | K25: 0 | M25: 0 | N25: 0 | P25: 0 | Q25: 0 | S25: 0 | T25: 0 | V25: 0 | W25: 0 | Y25: 0 | Z25: 0 | AB25: 0 | AC25: 0 | AE25: 0 | AF25: 0
A26: 4 | B26: OPERATIVOS | C26: ESCUELAS SEGURAS | D26: 21 | E26: 17 | G26: 8 | H26: 5 | J26: 17 | K26: 11 | M26: 13 | N26: 13 | P26: 13 | Q26: 7 | S26: 9 | T26: 4 | V26: 4 | W26: 4 | Y26: 4 | Z26: 2 | AB26: 24 | AC26: 17 | AE26: 9 | AF26: -10
C27: GUARDIAN VIAL | D27: 17 | E27: 11 | G27: 0 | H27: 0 | J27: 20 | K27: 15 | M27: 0 | N27: 0 | P27: 1 | Q27: 0 | S27: 0 | T27: 0 | V27: 0 | W27: 0 | Y27: 0 | Z27: 0 | AB27: 18 | AC27: 12 | AE27: 0 | AF27: 0
C28: MONITOREO INTEGRAL | D28: 7 | E28: 5 | G28: 0 | H28: 0 | J28: 19 | K28: 14 | M28: 0 | N28: 0 | P28: 5 | Q28: 2 | S28: 0 | T28: 0 | V28: 0 | W28: 0 | Y28: 0 | Z28: 0 | AB28: 22 | AC28: 14 | AE28: 0 | AF28: 0
C29: CONCIENTIZACIÓN USO DE CASCO | D29: 0 | E29: 0 | G29: 0 | H29: 0 | J29: 0 | K29: 0 | M29: 0 | N29: 0 | P29: 0 | Q29: 0 | S29: 0 | T29: 0 | V29: 1 | W29: 1 | Y29: 0 | Z29: 0 | AB29: 3 | AC29: 3 | AE29: 1 | AF29: 1
C30: AMPLIACION CARRETERA CIUIDAD HIDALGO-ZITACUARO | D30: 0 | E30: 0 | G30: 0 | H30: 0 | J30: 0 | K30: 0 | M30: 0 | N30: 0 | P30: 0 | Q30: 0 | S30: 0 | T30: 0 | V30: 0 | W30: 0 | Y30: 0 | Z30: 0 | AB30: 10 | AC30: 6 | AE30: 0 | AF30: 0
C31: SEGURIDAD EN CARRETERAS - ZINAPECUARO - MORELIA | D31: 1 | E31: 1 | G31: 0 | H31: 0 | J31: 0 | K31: 0 | M31: 0 | N31: 0 | P31: 0 | Q31: 0 | S31: 0 | T31: 0 | V31: 0 | W31: 0 | Y31: 0 | Z31: 0 | AB31: 0 | AC31: 0 | AE31: 0 | AF31: 0
C32: SEGURIDAD EN CARRETERAS - SALAMANCA - MORELIA | D32: 1 | E32: 1 | G32: 0 | H32: 0 | J32: 0 | K32: 0 | M32: 0 | N32: 0 | P32: 0 | Q32: 0 | S32: 0 | T32: 0 | V32: 0 | W32: 0 | Y32: 0 | Z32: 0 | AB32: 0 | AC32: 0 | AE32: 0 | AF32: 0
C33: APOYO COCOTRA | D33: 0 | E33: 0 | G33: 0 | H33: 0 | J33: 0 | K33: 0 | M33: 0 | N33: 0 | P33: 0 | Q33: 0 | S33: 0 | T33: 0 | V33: 0 | W33: 0 | Y33: 0 | Z33: 0 | AB33: 0 | AC33: 0 | AE33: 0 | AF33: 0
C34: BASES DE OPERACIONES INTERINSTITUCIONAL | D34: 0 | E34: 0 | G34: 0 | H34: 0 | J34: 0 | K34: 0 | M34: 0 | N34: 0 | P34: 0 | Q34: 0 | S34: 0 | T34: 0 | V34: 0 | W34: 0 | Y34: 0 | Z34: 0 | AB34: 0 | AC34: 0 | AE34: 0 | AF34: 0
C35: OTROS OPERATIVOS (Especificar en las novedades relevantes) | D35: 0 | E35: 0 | G35: 0 | H35: 0 | J35: 0 | K35: 0 | M35: 0 | N35: 0 | P35: 3 | Q35: 3 | S35: 0 | T35: 0 | V35: 0 | W35: 0 | Y35: 0 | Z35: 0 | AB35: 0 | AC35: 0 | AE35: 0 | AF35: 0
A36: 5 | B36: PROGRAMAS | C36: CONDUCE SIN ALCOHOL (ALCOHOLÍMETRO) | D36: 0 | E36: 0 | G36: 0 | H36: 0 | J36: 0 | K36: 0 | M36: 0 | N36: 0 | P36: 0 | Q36: 0 | S36: 0 | T36: 0 | V36: 0 | W36: 0 | Y36: 0 | Z36: 0 | AB36: 0 | AC36: 0 | AE36: 0 | AF36: 0
C37: OTROS PROGRAMAS (Especificar en las novedades relevantes) | D37: 0 | E37: 0 | G37: 0 | H37: 0 | J37: 0 | K37: 0 | M37: 0 | N37: 0 | P37: 0 | Q37: 0 | S37: 0 | T37: 0 | V37: 0 | W37: 0 | Y37: 0 | Z37: 0 | AB37: 0 | AC37: 0 | AE37: 0 | AF37: 0
A38: 6 | B38: MONITOREOS | C38: VÍAS FÉRREAS | D38: 1 | E38: 1 | G38: 0 | H38: 0 | J38: 0 | K38: 0 | M38: 0 | N38: 0 | P38: 0 | Q38: 0 | S38: 1 | T38: 1 | V38: 0 | W38: 0 | Y38: 0 | Z38: 0 | AB38: 0 | AC38: 0 | AE38: 0 | AF38: 0
C39: PERIFÉRICOS | D39: 0 | E39: 0 | G39: 0 | H39: 0 | J39: 1 | K39: 2 | M39: 2 | N39: 2 | P39: 0 | Q39: 0 | S39: 0 | T39: 0 | V39: 0 | W39: 0 | Y39: 0 | Z39: 0 | AB39: 0 | AC39: 0 | AE39: 0 | AF39: 0
C40: AVENIDAS | D40: 0 | E40: 0 | G40: 2 | H40: 2 | J40: 0 | K40: 0 | M40: 4 | N40: 4 | P40: 0 | Q40: 0 | S40: 0 | T40: 0 | V40: 0 | W40: 0 | Y40: 0 | Z40: 0 | AB40: 0 | AC40: 0 | AE40: 0 | AF40: 0
C41: TIENDAS DEPARTAMENTALES | D41: 1 | E41: 1 | G41: 0 | H41: 0 | J41: 2 | K41: 3 | M41: 0 | N41: 0 | P41: 0 | Q41: 0 | S41: 0 | T41: 0 | V41: 0 | W41: 0 | Y41: 0 | Z41: 0 | AB41: 4 | AC41: 4 | AE41: 0 | AF41: 0
C42: BANCOS | D42: 1 | E42: 1 | G42: 2 | H42: 2 | J42: 1 | K42: 2 | M42: 0 | N42: 0 | P42: 0 | Q42: 0 | S42: 0 | T42: 0 | V42: 0 | W42: 2 | Y42: 0 | Z42: 0 | AB42: 0 | AC42: 0 | AE42: 0 | AF42: 0
C43: GASOLINERAS | D43: 0 | E43: 0 | G43: 3 | H43: 3 | J43: 1 | K43: 1 | M43: 0 | N43: 0 | P43: 0 | Q43: 0 | S43: 0 | T43: 0 | V43: 0 | W43: 0 | Y43: 0 | Z43: 0 | AB43: 0 | AC43: 0 | AE43: 0 | AF43: 0
C44: OFICINAS GUBERNAMENTALES | D44: 2 | E44: 3 | G44: 1 | H44: 1 | J44: 7 | K44: 8 | M44: 4 | N44: 4 | P44: 2 | Q44: 2 | S44: 2 | T44: 2 | V44: 1 | W44: 3 | Y44: 0 | Z44: 1 | AB44: 11 | AC44: 10 | AE44: 0 | AF44: 0
C45: MANIFESTACIONES | D45: 0 | E45: 0 | G45: 0 | H45: 0 | J45: 0 | K45: 0 | M45: 0 | N45: 0 | P45: 0 | Q45: 0 | S45: 0 | T45: 0 | V45: 0 | W45: 0 | Y45: 0 | Z45: 0 | AB45: 0 | AC45: 0 | AE45: 0 | AF45: 0
C46: OTROS MONITOREOS (Especificar en las novedades relevantes) | D46: 0 | E46: 0 | G46: 0 | H46: 0 | J46: 0 | K46: 0 | M46: 0 | N46: 0 | P46: 0 | Q46: 0 | S46: 0 | T46: 0 | V46: 0 | W46: 0 | Y46: 0 | Z46: 0 | AB46: 0 | AC46: 0 | AE46: 0 | AF46: 0
A47: 7 | B47: AUXILIO VIAL A CONDUCTORES | C47: FALLAS MECÁNICAS | D47: 0 | E47: 0 | G47: 0 | H47: 0 | J47: 0 | K47: 0 | M47: 0 | N47: 0 | P47: 0 | Q47: 0 | S47: 0 | T47: 0 | V47: 0 | W47: 0 | Y47: 0 | Z47: 0 | AB47: 0 | AC47: 0 | AE47: 0 | AF47: 0
C48: PEATÓN | D48: 0 | E48: 0 | G48: 0 | H48: 0 | J48: 0 | K48: 0 | M48: 0 | N48: 0 | P48: 0 | Q48: 0 | S48: 0 | T48: 0 | V48: 0 | W48: 0 | Y48: 0 | Z48: 0 | AB48: 0 | AC48: 0 | AE48: 0 | AF48: 0
C49: ESCOLTA EN SITUACIONES DE EMERGENCIA | D49: 0 | E49: 0 | G49: 0 | H49: 0 | J49: 0 | K49: 0 | M49: 0 | N49: 0 | P49: 0 | Q49: 0 | S49: 0 | T49: 0 | V49: 0 | W49: 0 | Y49: 0 | Z49: 0 | AB49: 0 | AC49: 0 | AE49: 0 | AF49: 0
C50: AGRICOLAS | D50: 0 | E50: 0 | G50: 0 | H50: 0 | J50: 0 | K50: 0 | M50: 0 | N50: 0 | P50: 0 | Q50: 0 | S50: 0 | T50: 0 | V50: 0 | W50: 0 | Y50: 0 | Z50: 0 | AB50: 0 | AC50: 0 | AE50: 0 | AF50: 0
C51: OTROS AUXILIOS (Especificar en las novedades relevantes) | D51: 0 | E51: 0 | G51: 0 | H51: 0 | J51: 0 | K51: 0 | M51: 0 | N51: 0 | P51: 0 | Q51: 0 | S51: 0 | T51: 0 | V51: 0 | W51: 0 | Y51: 0 | Z51: 0 | AB51: 0 | AC51: 0 | AE51: 0 | AF51: 0
A52: 8 | B52: DISPOSITIVOS DE SEGURIDAD VIAL | C52: APOYO A LA VIALIDAD | D52: 1 | E52: 2 | G52: 0 | H52: 0 | J52: 2 | K52: 2 | M52: 0 | N52: 0 | P52: 0 | Q52: 0 | S52: 2 | T52: 1 | V52: 1 | W52: 1 | Y52: 0 | Z52: 0 | AB52: 0 | AC52: 0 | AE52: 0 | AF52: 0
C53: PASO LIBRE DE FUNCIONARIOS | D53: 0 | E53: 0 | G53: 0 | H53: 0 | J53: 0 | K53: 0 | M53: 0 | N53: 0 | P53: 0 | Q53: 0 | S53: 0 | T53: 0 | V53: 0 | W53: 0 | Y53: 0 | Z53: 0 | AB53: 0 | AC53: 0 | AE53: 0 | AF53: 0
C54: ZONAS DE MAYOR PASE DE TRANSEÚNTES | D54: 0 | E54: 0 | G54: 0 | H54: 0 | J54: 0 | K54: 0 | M54: 0 | N54: 0 | P54: 0 | Q54: 0 | S54: 0 | T54: 0 | V54: 0 | W54: 0 | Y54: 0 | Z54: 0 | AB54: 0 | AC54: 0 | AE54: 0 | AF54: 0
C55: PASOS PEATONALES | D55: 1 | E55: 2 | G55: 0 | H55: 0 | J55: 3 | K55: 6 | M55: 5 | N55: 5 | P55: 0 | Q55: 0 | S55: 0 | T55: 1 | V55: 0 | W55: 2 | Y55: 0 | Z55: 0 | AB55: 0 | AC55: 0 | AE55: 0 | AF55: 0
C56: MEDIDAS DE PROTECCIÓN | D56: 0 | E56: 0 | G56: 0 | H56: 0 | J56: 0 | K56: 0 | M56: 0 | N56: 0 | P56: 0 | Q56: 0 | S56: 0 | T56: 0 | V56: 0 | W56: 0 | Y56: 0 | Z56: 0 | AB56: 0 | AC56: 0 | AE56: 0 | AF56: 0
C57: PATRULLAJES | D57: 7 | E57: 7 | G57: 0 | H57: 0 | J57: 5 | K57: 5 | M57: 2 | N57: 2 | P57: 0 | Q57: 0 | S57: 2 | T57: 2 | V57: 0 | W57: 0 | Y57: 1 | Z57: 1 | AB57: 12 | AC57: 12 | AE57: 1 | AF57: 1
C58: SERVICIOS DE ESCOLTAS | D58: 0 | E58: 0 | G58: 0 | H58: 0 | J58: 0 | K58: 0 | M58: 0 | N58: 0 | P58: 0 | Q58: 0 | S58: 0 | T58: 0 | V58: 0 | W58: 0 | Y58: 0 | Z58: 0 | AB58: 0 | AC58: 0 | AE58: 0 | AF58: 0
C59: OTROS (Especificar en las novedades relevantes) | D59: 0 | E59: 0 | G59: 0 | H59: 0 | J59: 0 | K59: 0 | M59: 0 | N59: 0 | P59: 0 | Q59: 0 | S59: 0 | T59: 0 | V59: 0 | W59: 0 | Y59: 0 | Z59: 0 | AB59: 0 | AC59: 0 | AE59: 0 | AF59: 0
A60: 9 | B60: CAPACITACIONES | C60: TALLER EDUCACIÓN SEGURIDAD VIAL | D60: 0 | E60: 0 | G60: 0 | H60: 0 | J60: 1 | K60: 1 | M60: 0 | N60: 0 | P60: 0 | Q60: 0 | S60: 0 | T60: 0 | V60: 0 | W60: 0 | Y60: 0 | Z60: 0 | AB60: 0 | AC60: 0 | AE60: 0 | AF60: 0
C61: CAMPAÑA EDUCACIÓN SEGURIDAD VIAL | D61: 0 | E61: 0 | G61: 0 | H61: 0 | J61: 0 | K61: 0 | M61: 0 | N61: 0 | P61: 0 | Q61: 0 | S61: 0 | T61: 0 | V61: 0 | W61: 0 | Y61: 0 | Z61: 0 | AB61: 0 | AC61: 0 | AE61: 0 | AF61: 0
C62: CAPACITACIONES EDUCACIÓN SEGURIDAD VIAL | D62: 0 | E62: 0 | G62: 0 | H62: 0 | J62: 0 | K62: 0 | M62: 0 | N62: 0 | P62: 0 | Q62: 0 | S62: 0 | T62: 0 | V62: 0 | W62: 0 | Y62: 0 | Z62: 0 | AB62: 0 | AC62: 0 | AE62: 0 | AF62: 0
C63: MÓDULOS EDUCACIÓN SEGURIDAD VIAL | D63: 0 | E63: 0 | G63: 0 | H63: 0 | J63: 0 | K63: 0 | M63: 0 | N63: 0 | P63: 0 | Q63: 0 | S63: 0 | T63: 0 | V63: 0 | W63: 0 | Y63: 0 | Z63: 0 | AB63: 0 | AC63: 0 | AE63: 0 | AF63: 0
C64: SSP | D64: 0 | E64: 0 | G64: 0 | H64: 0 | J64: 0 | K64: 0 | M64: 0 | N64: 0 | P64: 0 | Q64: 0 | S64: 0 | T64: 0 | V64: 0 | W64: 0 | Y64: 0 | Z64: 0 | AB64: 0 | AC64: 0 | AE64: 0 | AF64: 0
C65: CALEA | D65: 0 | E65: 0 | G65: 0 | H65: 0 | J65: 0 | K65: 0 | M65: 0 | N65: 0 | P65: 0 | Q65: 0 | S65: 0 | T65: 0 | V65: 0 | W65: 0 | Y65: 0 | Z65: 0 | AB65: 0 | AC65: 0 | AE65: 0 | AF65: 0
C66: OTRAS (Especificar en las novedades relevantes) | D66: 0 | E66: 0 | G66: 0 | H66: 0 | J66: 0 | K66: 0 | M66: 0 | N66: 0 | P66: 0 | Q66: 0 | S66: 0 | T66: 0 | V66: 0 | W66: 0 | Y66: 0 | Z66: 0 | AB66: 0 | AC66: 0 | AE66: 0 | AF66: 0
A67: 10 | B67: CAMPAÑAS | C67: CONCIENTIZACIÓN Y PREVENCIÓN | D67: 0 | E67: 0 | G67: 2 | H67: 2 | J67: 2 | K67: 4 | M67: 4 | N67: 4 | P67: 0 | Q67: 0 | S67: 0 | T67: 0 | V67: 1 | W67: 1 | Y67: 0 | Z67: 0 | AB67: 3 | AC67: 3 | AE67: 2 | AF67: 2
C68: REPARTICIÓN DE TRÍPTICOS | D68: 0 | E68: 0 | G68: 0 | H68: 0 | J68: 0 | K68: 0 | M68: 0 | N68: 0 | P68: 0 | Q68: 0 | S68: 2 | T68: 1 | V68: 0 | W68: 0 | Y68: 0 | Z68: 0 | AB68: 6 | AC68: 6 | AE68: 0 | AF68: 0
C69: ESTACIONALES (SEMANA SANTA, NAVIDAD ETC.) | D69: 0 | E69: 0 | G69: 0 | H69: 0 | J69: 0 | K69: 0 | M69: 0 | N69: 0 | P69: 0 | Q69: 0 | S69: 0 | T69: 0 | V69: 0 | W69: 0 | Y69: 0 | Z69: 0 | AB69: 0 | AC69: 0 | AE69: 0 | AF69: 0
C70: OTRAS (Especificar en las novedades relevantes) | D70: 0 | E70: 0 | G70: 0 | H70: 0 | J70: 0 | K70: 0 | M70: 0 | N70: 0 | P70: 0 | Q70: 0 | S70: 0 | T70: 0 | V70: 0 | W70: 0 | Y70: 0 | Z70: 0 | AB70: 0 | AC70: 0 | AE70: 0 | AF70: 0
A71: 11 | B71: PROXIMIDAD SOCIAL | C71: PREVENCIÓN SOCIAL | D71: 0 | E71: 0 | G71: 0 | H71: 0 | J71: 0 | K71: 0 | M71: 0 | N71: 0 | P71: 0 | Q71: 0 | S71: 0 | T71: 0 | V71: 0 | W71: 0 | Y71: 0 | Z71: 0 | AB71: 0 | AC71: 0 | AE71: 0 | AF71: 0
C72: RECORRIDOS DE PROXIMIDAD | D72: 0 | E72: 0 | G72: 1 | H72: 1 | J72: 1 | K72: 2 | M72: 0 | N72: 0 | P72: 0 | Q72: 0 | S72: 1 | T72: 1 | V72: 1 | W72: 1 | Y72: 1 | Z72: 2 | AB72: 8 | AC72: 8 | AE72: 0 | AF72: 0
C73: APOYO A TURISTAS | D73: 0 | E73: 0 | G73: 0 | H73: 0 | J73: 0 | K73: 0 | M73: 0 | N73: 0 | P73: 0 | Q73: 0 | S73: 0 | T73: 0 | V73: 0 | W73: 0 | Y73: 0 | Z73: 0 | AB73: 0 | AC73: 0 | AE73: 0 | AF73: 0
C74: APOYO A PERSONAS DE LA TERCERA EDAD | D74: 0 | E74: 0 | G74: 0 | H74: 0 | J74: 0 | K74: 0 | M74: 0 | N74: 0 | P74: 0 | Q74: 0 | S74: 0 | T74: 0 | V74: 0 | W74: 0 | Y74: 0 | Z74: 0 | AB74: 0 | AC74: 0 | AE74: 0 | AF74: 0
C75: APOYO A PERSONAS PERDIDAS | D75: 0 | E75: 0 | G75: 0 | H75: 0 | J75: 0 | K75: 0 | M75: 0 | N75: 0 | P75: 0 | Q75: 0 | S75: 0 | T75: 0 | V75: 0 | W75: 0 | Y75: 0 | Z75: 0 | AB75: 0 | AC75: 0 | AE75: 0 | AF75: 0
C76: RECUPERACIÓN DE ESPACIOS | D76: 0 | E76: 0 | G76: 0 | H76: 0 | J76: 0 | K76: 0 | M76: 0 | N76: 0 | P76: 0 | Q76: 0 | S76: 0 | T76: 0 | V76: 0 | W76: 0 | Y76: 0 | Z76: 0 | AB76: 0 | AC76: 0 | AE76: 0 | AF76: 0
C77: OTRAS (Especificar en las novedades relevantes) | D77: 0 | E77: 0 | G77: 0 | H77: 0 | J77: 0 | K77: 0 | M77: 0 | N77: 0 | P77: 0 | Q77: 0 | S77: 0 | T77: 0 | V77: 0 | W77: 0 | Y77: 0 | Z77: 0 | AB77: 0 | AC77: 0 | AE77: 0 | AF77: 0
A78: TOTAL | C78: DISPOSITIVOS REALIZADOS
B200: CANTIDAD | C200: ESTADO DE FUERZA PARTICIPANTE | D200: UNIDADES PARTICIPANTES | E200: KM
B201: 0 | C201: 0 | D201: 0 | E201: 0
B202: 1 | C202: 2 | D202: 1 | E202: 10
B203: 2 | C203: 4 | D203: 2 | E203: 15
B204: 3 | C204: 6 | D204: 3 | E204: 35
B205: 4 | C205: 8 | D205: 4 | E205: 45
B206: 5 | C206: 10 | D206: 5 | E206: 55
B207: 6 | C207: 12 | D207: 6 | E207: 68
B208: 7 | C208: 14 | D208: 7 | E208: 80
B209: 8 | C209: 16 | D209: 8 | E209: 92
B210: 9 | C210: 18 | D210: 9 | E210: 104
B211: 10 | C211: 20 | D211: 10 | E211: 116
B212: 11 | C212: 22 | D212: 11 | E212: 128
... B221: 20 | C221: 40 | D221: 20 | E221: 236

Sheet ALERTAS
B4: INSTITUCIONES | F4: MORELIA | G4: JIQUILPAN | H4: ZAMORA | I4: LA PIEDAD | J4: URUAPAN | K4: APATZINGÁN | L4: HUETAMO | M4: COALCOMÁN | N4: ZITÁCUARO | O4: LÁZARO CÁRDENAS | R4: LIBERACIONES | S4: CANTIDAD | V4: MORELIA | W4: JIQUILPAN | X4: ZAMORA | Y4: LA PIEDAD | Z4: URUAPAN | AA4: APATZINGÁN | AB4: HUETAMO | AC4: COALCOMÁN | AD4: ZITÁCUARO | AE4: LÁZARO CÁRDENAS
B5: APOYO A EVENTOS PÚBLICOS | C5: 1 | F5: 1 | G5: 0 | H5: 0 | I5: 0 | J5: 0 | K5: 0 | L5: 0 | M5: 0 | N5: 0 | O5: 0 | R5: LIBERACIÓN MOTOCICLETAS | S5: 0
B6: APOYO A EVENTOS DEPORTIVOS | C6: 0 | F6: 0 | G6: 0 | H6: 0 | I6: 0 | J6: 0 | K6: 0 | L6: 0 | M6: 0 | N6: 0 | O6: 0 | R6: LIBERACIÓN VEHÍCULOS | S6: 0
B7: APOYO A EVENTOS CULTURALES | C7: 0 | F7: 0 | G7: 0 | H7: 0 | I7: 0 | J7: 0 | K7: 0 | L7: 0 | M7: 0 | N7: 0 | O7: 0 | R7: LIBERACIÓN CAMIONES | S7: 0
B8: APOYO A EVENTOS RELIGIOSOS | C8: 1 | F8: 0 | G8: 0 | H8: 0 | I8: 0 | J8: 0 | K8: 0 | L8: 0 | M8: 0 | N8: 1 | O8: 0 | R8: LIBERACIÓN REMOLQUES | S8: 0
B9: APOYOS A OTRAS DEPENDENCIAS | C9: 2 | F9: 1 | G9: 0 | H9: 1 | I9: 0 | J9: 0 | K9: 0 | L9: 0 | M9: 0 | N9: 0 | O9: 0
B10: ESCUELAS | C10: 74 | F10: 14 | G10: 4 | H10: 11 | I10: 6 | J10: 7 | K10: 6 | L10: 4 | M10: 5 | N10: 10 | O10: 7 | R10: ÁREAS AUXILIARES | S10: CANTIDAD | V10: MORELIA | W10: JIQUILPAN | X10: ZAMORA | Y10: LA PIEDAD | Z10: URUAPAN | AA10: APATZINGÁN | AB10: HUETAMO | AC10: COALCOMÁN | AD10: ZITÁCUARO | AE10: LÁZARO CÁRDENAS
B11: DILIGENCIAS | C11: 1 | F11: 1 | G11: 0 | H11: 0 | I11: 0 | J11: 0 | K11: 0 | L11: 0 | M11: 0 | N11: 0 | O11: 0 | R11: EXÁMEN TEÓRICO | S11: 0
B12: OTROS TIPOS | C12: 0 | F12: 0 | G12: 0 | H12: 0 | I12: 0 | J12: 0 | K12: 0 | L12: 0 | M12: 0 | N12: 0 | O12: 0
B14: REPORTES C5i | F14: MORELIA | G14: JIQUILPAN | H14: ZAMORA | I14: LA PIEDAD | J14: URUAPAN | K14: APATZINGÁN | L14: HUETAMO | M14: COALCOMÁN | N14: ZITÁCUARO | O14: LÁZARO CÁRDENAS | R14: MONITOREOS | V14: MORELIA | W14: JIQUILPAN | X14: ZAMORA | Y14: LA PIEDAD | Z14: URUAPAN | AA14: APATZINGÁN | AB14: HUETAMO | AC14: COALCOMÁN | AD14: ZITÁCUARO | AE14: LÁZARO CÁRDENAS
B15: OBSTRUCCIÓN DE COCHERAS | C15: 0 | F15: 0 | G15: 0 | H15: 0 | I15: 0 | J15: 0 | K15: 0 | L15: 0 | M15: 0 | N15: 0 | O15: 0 | R15: VÍAS FÉRREAS | S15: 2 | V15: 1 | W15: 0 | X15: 0 | Y15: 0 | Z15: 0 | AA15: 1 | AB15: 0 | AC15: 0 | AD15: 0 | AE15: 0
B16: OTROS TIPOS DE OBSTRUCCIÓN | C16: 0 | F16: 0 | G16: 0 | H16: 0 | I16: 0 | J16: 0 | K16: 0 | L16: 0 | M16: 0 | N16: 0 | O16: 0 | R16: PERIFÉRICOS | S16: 8 | V16: 0 | W16: 1 | X16: 1 | Y16: 2 | Z16: 2 | AA16: 0 | AB16: 0 | AC16: 0 | AD16: 2 | AE16: 0
B17: ACTOS DELICTIVOS | C17: 1 | F17: 0 | G17: 0 | H17: 0 | I17: 0 | J17: 1 | K17: 0 | L17: 0 | M17: 0 | N17: 0 | O17: 0 | R17: AVENIDAS | S17: 5 | V17: 0 | W17: 2 | X17: 0 | Y17: 3 | Z17: 0 | AA17: 0 | AB17: 0 | AC17: 0 | AD17: 0 | AE17: 0
B18: SINIESTROS | C18: 3 | F18: 0 | G18: 0 | H18: 2 | I18: 0 | J18: 1 | K18: 0 | L18: 0 | M18: 0 | N18: 0 | O18: 0 | R18: TIENDAS DEPARTAMENTALES | S18: 4 | V18: 1 | W18: 1 | X18: 1 | Y18: 0 | Z18: 0 | AA18: 0 | AB18: 0 | AC18: 0 | AD18: 1 | AE18: 0
B19: HECHOS DE TRÁNSITO | C19: 5 | F19: 1 | G19: 0 | H19: 1 | I19: 0 | J19: 0 | K19: 0 | L19: 2 | M19: 0 | N19: 1 | O19: 0 | R19: BANCOS | S19: 6 | V19: 1 | W19: 1 | X19: 1 | Y19: 0 | Z19: 0 | AA19: 0 | AB19: 3 | AC19: 0 | AD19: 0 | AE19: 0
B20: CONSENTRACION PERSONAS | C20: 0 | F20: 0 | G20: 0 | H20: 0 | I20: 0 | J20: 0 | K20: 0 | L20: 0 | M20: 0 | N20: 0 | O20: 0 | R20: GASOLINERAS | S20: 6 | V20: 0 | W20: 3 | X20: 1 | Y20: 0 | Z20: 2 | AA20: 0 | AB20: 0 | AC20: 0 | AD20: 0 | AE20: 0
B21: OTROS REPORTES | C21: 0 | F21: 0 | G21: 0 | H21: 0 | I21: 0 | J21: 0 | K21: 0 | L21: 0 | M21: 0 | N21: 0 | O21: 0 | R21: OFICINAS GUBERNAMENTALES | S21: 32 | V21: 2 | W21: 2 | X21: 6 | Y21: 4 | Z21: 2 | AA21: 3 | AB21: 4 | AC21: 1 | AD21: 7 | AE21: 1
R22: MANIFESTACIONES | S22: 0 | V22: 0 | W22: 0 | X22: 0 | Y22: 0 | Z22: 0 | AA22: 0 | AB22: 0 | AC22: 0 | AD22: 0 | AE22: 0
R23: OTROS MONITOREOS (Especificar en las novedades relevantes) | S23: 0 | V23: 0 | W23: 0 | X23: 0 | Y23: 0 | Z23: 0 | AA23: 0 | AB23: 0 | AC23: 0 | AD23: 0 | AE23: 0
B24: ABANDERAMIENTOS | F24: MORELIA | G24: JIQUILPAN | H24: ZAMORA | I24: LA PIEDAD | J24: URUAPAN | K24: APATZINGÁN | L24: HUETAMO | M24: COALCOMÁN | N24: ZITÁCUARO | O24: LÁZARO CÁRDENAS
B25: CORTES DE CIRCULACIÓN | C25: 9 | F25: 6 | G25: 0 | H25: 0 | I25: 0 | J25: 0 | K25: 1 | L25: 1 | M25: 0 | N25: 1 | O25: 0
B26: ACCIDENTES | C26: 1 | F26: 0 | G26: 0 | H26: 1 | I26: 0 | J26: 0 | K26: 0 | L26: 0 | M26: 0 | N26: 0 | O26: 0 | R26: A CONDUCTORES | V26: MORELIA | W26: JIQUILPAN | X26: ZAMORA | Y26: LA PIEDAD | Z26: URUAPAN | AA26: APATZINGÁN | AB26: HUETAMO | AC26: COALCOMÁN | AD26: ZITÁCUARO | AE26: LÁZARO CÁRDENAS
B27: MARCHAS | C27: 0 | F27: 0 | G27: 0 | H27: 0 | I27: 0 | J27: 0 | K27: 0 | L27: 0 | M27: 0 | N27: 0 | O27: 0 | R27: FALLAS MECÁNICAS | S27: 0 | V27: 0 | W27: 0 | X27: 0 | Y27: 0 | Z27: 0 | AA27: 0 | AB27: 0 | AC27: 0 | AD27: 0 | AE27: 0
B28: MÍTINES | C28: 0 | F28: 0 | G28: 0 | H28: 0 | I28: 0 | J28: 0 | K28: 0 | L28: 0 | M28: 0 | N28: 0 | O28: 0 | R28: PEATÓN | S28: 0 | V28: 0 | W28: 0 | X28: 0 | Y28: 0 | Z28: 0 | AA28: 0 | AB28: 0 | AC28: 0 | AD28: 0 | AE28: 0
B29: OBRAS PÚBLICAS | C29: 2 | F29: 0 | G29: 1 | H29: 0 | I29: 0 | J29: 0 | K29: 0 | L29: 0 | M29: 0 | N29: 1 | O29: 0 | R29: ESCOLTA EN SITUACIONES DE EMERGENCIA | S29: 0 | V29: 0 | W29: 0 | X29: 0 | Y29: 0 | Z29: 0 | AA29: 0 | AB29: 0 | AC29: 0 | AD29: 0 | AE29: 0
B30: ACOMPAÑAMIENTO A CARAVANAS U OTROS | C30: 1 | F30: 0 | G30: 0 | H30: 0 | I30: 1 | J30: 0 | K30: 0 | L30: 0 | M30: 0 | N30: 0 | O30: 0 | R30: AGRICOLAS | S30: 0 | V30: 0 | W30: 0 | X30: 0 | Y30: 0 | Z30: 0 | AA30: 0 | AB30: 0 | AC30: 0 | AD30: 0 | AE30: 0
B31: OTROS ABANDERAMIENTOS | C31: 0 | F31: 0 | G31: 0 | H31: 0 | I31: 0 | J31: 0 | K31: 0 | L31: 0 | M31: 0 | N31: 0 | O31: 0 | R31: OTROS AUXILIOS (Especificar en las novedades relevantes) | S31: 0 | V31: 0 | W31: 0 | X31: 0 | Y31: 0 | Z31: 0 | AA31: 0 | AB31: 0 | AC31: 0 | AD31: 0 | AE31: 0
B34: OPERATIVOS | F34: MORELIA | G34: JIQUILPAN | H34: ZAMORA | I34: LA PIEDAD | J34: URUAPAN | K34: APATZINGÁN | L34: HUETAMO | M34: COALCOMÁN | N34: ZITÁCUARO | O34: LÁZARO CÁRDENAS | R34: DISPOSITIVOS DE SEGURIDAD VIAL | V34: MORELIA | W34: JIQUILPAN | X34: ZAMORA | Y34: LA PIEDAD | Z34: URUAPAN | AA34: APATZINGÁN | AB34: HUETAMO | AC34: COALCOMÁN | AD34: ZITÁCUARO | AE34: LÁZARO CÁRDENAS
B35: ESCUELAS SEGURAS | C35: 10 | F35: 1 | G35: 1 | H35: 1 | I35: 1 | J35: 1 | K35: 1 | L35: 1 | M35: 1 | N35: 1 | O35: 1 | R35: APOYO A LA VIALIDAD | S35: 5 | V35: 1 | W35: 0 | X35: 2 | Y35: 0 | Z35: 0 | AA35: 1 | AB35: 1 | AC35: 0 | AD35: 0 | AE35: 0
B36: GUARDIAN VIAL | C36: 4 | F36: 1 | G36: 0 | H36: 1 | I36: 0 | J36: 1 | K36: 0 | L36: 0 | M36: 0 | N36: 1 | O36: 0 | R36: PASO LIBRE DE FUNCIONARIOS | S36: 0 | V36: 0 | W36: 0 | X36: 0 | Y36: 0 | Z36: 0 | AA36: 0 | AB36: 0 | AC36: 0 | AD36: 0 | AE36: 0
B37: MONITOREO INTEGRAL | C37: 4 | F37: 1 | G37: 0 | H37: 1 | I37: 0 | J37: 1 | K37: 0 | L37: 0 | M37: 0 | N37: 1 | O37: 0 | R37: ZONAS DE MAYOR PASE DE TRANSEÚNTES | S37: 0 | V37: 0 | W37: 0 | X37: 0 | Y37: 0 | Z37: 0 | AA37: 0 | AB37: 0 | AC37: 0 | AD37: 0 | AE37: 0
B38: CONCIENTIZACIÓN USO DE CASCO | C38: 4 | F38: 0 | G38: 0 | H38: 0 | I38: 0 | J38: 0 | K38: 1 | L38: 1 | M38: 0 | N38: 1 | O38: 1 | R38: PASOS PEATONALES | S38: 13 | V38: 1 | W38: 0 | X38: 3 | Y38: 4 | Z38: 0 | AA38: 2 | AB38: 2 | AC38: 0 | AD38: 0 | AE38: 1
B39: AMPLIACION CARRETERA CIUIDAD HIDALGO-ZITACUARO | C39: 1 | F39: 0 | G39: 0 | H39: 0 | I39: 0 | J39: 0 | K39: 0 | L39: 0 | M39: 0 | N39: 1 | O39: 0 | R39: MEDIDAS DE PROTECCIÓN | S39: 0 | V39: 0 | W39: 0 | X39: 0 | Y39: 0 | Z39: 0 | AA39: 0 | AB39: 0 | AC39: 0 | AD39: 0 | AE39: 0
B40: SEGURIDAD EN CARRETERAS - ZINAPECUARO - MORELIA | C40: 1 | F40: 1 | G40: 0 | H40: 0 | I40: 0 | J40: 0 | K40: 0 | L40: 0 | M40: 0 | N40: 0 | O40: 0 | R40: PATRULLAJES | S40: 25 | V40: 7 | W40: 0 | X40: 4 | Y40: 2 | Z40: 0 | AA40: 3 | AB40: 0 | AC40: 2 | AD40: 5 | AE40: 2
B41: SEGURIDAD EN CARRETERAS - SALAMANCA - MORELIA | C41: 1 | F41: 1 | G41: 0 | H41: 0 | I41: 0 | J41: 0 | K41: 0 | L41: 0 | M41: 0 | N41: 0 | O41: 0 | R41: SERVICIOS DE ESCOLTAS | S41: 0 | V41: 0 | W41: 0 | X41: 0 | Y41: 0 | Z41: 0 | AA41: 0 | AB41: 0 | AC41: 0 | AD41: 0 | AE41: 0
B42: APOYO COCOTRA | C42: 0 | F42: 0 | G42: 0 | H42: 0 | I42: 0 | J42: 0 | K42: 0 | L42: 0 | M42: 0 | N42: 0 | O42: 0 | R42: OTROS TIPOS | S42: 0 | V42: 0 | W42: 0 | X42: 0 | Y42: 0 | Z42: 0 | AA42: 0 | AB42: 0 | AC42: 0 | AD42: 0 | AE42: 0
B43: BASES DE OPERACIONES INTERINSTITUCIONAL | C43: 2 | F43: 0 | G43: 0 | H43: 0 | I43: 0 | J43: 0 | K43: 0 | L43: 0 | M43: 0 | N43: 0 | O43: 2
B44: OTROS OPERATIVOS (Especificar en las novedades relevantes) | C44: 1 | F44: 0 | G44: 0 | H44: 0 | I44: 0 | J44: 1 | K44: 0 | L44: 0 | M44: 0 | N44: 0 | O44: 0 | R44: CAPACITACIONES | V44: MORELIA | W44: JIQUILPAN | X44: ZAMORA | Y44: LA PIEDAD | Z44: URUAPAN | AA44: APATZINGÁN | AB44: HUETAMO | AC44: COALCOMÁN | AD44: ZITÁCUARO | AE44: LÁZARO CÁRDENAS
R45: TALLER EDUCACIÓN SEGURIDAD VIAL | S45: 1 | V45: 0 | W45: 0 | X45: 1 | Y45: 0 | Z45: 0 | AA45: 0 | AB45: 0 | AC45: 0 | AD45: 0 | AE45: 0
R46: CAMPAÑA EDUCACIÓN SEGURIDAD VIAL | S46: 0 | V46: 0 | W46: 0 | X46: 0 | Y46: 0 | Z46: 0 | AA46: 0 | AB46: 0 | AC46: 0 | AD46: 0 | AE46: 0
B47: PROGRAMAS | F47: MORELIA | G47: JIQUILPAN | H47: ZAMORA | I47: LA PIEDAD | J47: URUAPAN | K47: APATZINGÁN | L47: HUETAMO | M47: COALCOMÁN | N47: ZITÁCUARO | O47: LÁZARO CÁRDENAS | R47: CAPACITACIONES EDUCACIÓN SEGURIDAD VIAL | S47: 0 | V47: 0 | W47: 0 | X47: 0 | Y47: 0 | Z47: 0 | AA47: 0 | AB47: 0 | AC47: 0 | AD47: 0 | AE47: 0
B48: CONDUCE SIN ALCOHOL (ALCOHOLÍMETRO) | C48: 0 | F48: 0 | G48: 0 | H48: 0 | I48: 0 | J48: 0 | K48: 0 | L48: 0 | M48: 0 | N48: 0 | O48: 0 | R48: MÓDULOS EDUCACIÓN SEGURIDAD VIAL | S48: 0 | V48: 0 | W48: 0 | X48: 0 | Y48: 0 | Z48: 0 | AA48: 0 | AB48: 0 | AC48: 0 | AD48: 0 | AE48: 0
B49: OTROS PROGRAMAS | C49: 0 | F49: 0 | G49: 0 | H49: 0 | I49: 0 | J49: 0 | K49: 0 | L49: 0 | M49: 0 | N49: 0 | O49: 0 | R49: SSP | S49: 0 | V49: 0 | W49: 0 | X49: 0 | Y49: 0 | Z49: 0 | AA49: 0 | AB49: 0 | AC49: 0 | AD49: 0 | AE49: 0
R50: CALEA | S50: 0 | V50: 0 | W50: 0 | X50: 0 | Y50: 0 | Z50: 0 | AA50: 0 | AB50: 0 | AC50: 0 | AD50: 0 | AE50: 0
R51: OTRAS (Especificar en las novedades relevantes) | S51: 0 | V51: 0 | W51: 0 | X51: 0 | Y51: 0 | Z51: 0 | AA51: 0 | AB51: 0 | AC51: 0 | AD51: 0 | AE51: 0
R53: CAMPAÑAS | V53: MORELIA | W53: JIQUILPAN | X53: ZAMORA | Y53: LA PIEDAD | Z53: URUAPAN | AA53: APATZINGÁN | AB53: HUETAMO | AC53: COALCOMÁN | AD53: ZITÁCUARO | AE53: LÁZARO CÁRDENAS
R54: CONCIENTIZACIÓN | S54: 9 | V54: 0 | W54: 1 | X54: 2 | Y54: 2 | Z54: 0 | AA54: 0 | AB54: 1 | AC54: 0 | AD54: 1 | AE54: 2
R55: REPARTICIÓN DE TRÍPTICOS | S55: 5 | V55: 0 | W55: 0 | X55: 0 | Y55: 1 | Z55: 0 | AA55: 2 | AB55: 0 | AC55: 0 | AD55: 2 | AE55: 0
R56: SEMANA SANTA, NAVIDAD ETC. | S56: 0 | V56: 0 | W56: 0 | X56: 0 | Y56: 0 | Z56: 0 | AA56: 0 | AB56: 0 | AC56: 0 | AD56: 0 | AE56: 0
R57: OTROS TIPOS | S57: 0 | V57: 0 | W57: 0 | X57: 0 | Y57: 0 | Z57: 0 | AA57: 0 | AB57: 0 | AC57: 0 | AD57: 0 | AE57: 0
R59: PROXIMIDAD SOCIAL | V59: MORELIA | W59: JIQUILPAN | X59: ZAMORA | Y59: LA PIEDAD | Z59: URUAPAN | AA59: APATZINGÁN | AB59: HUETAMO | AC59: COALCOMÁN | AD59: ZITÁCUARO | AE59: LÁZARO CÁRDENAS
R60: PREVENCIÓN SOCIAL | S60: 0 | V60: 0 | W60: 0 | X60: 0 | Y60: 0 | Z60: 0 | AA60: 0 | AB60: 0 | AC60: 0 | AD60: 0 | AE60: 0
R61: RECORRIDOS DE PROXIMIDAD | S61: 9 | V61: 1 | W61: 1 | X61: 1 | Y61: 0 | Z61: 0 | AA61: 1 | AB61: 1 | AC61: 1 | AD61: 3 | AE61: 0
R62: APOYO A TURISTAS | S62: 0 | V62: 0 | W62: 0 | X62: 0 | Y62: 0 | Z62: 0 | AA62: 0 | AB62: 0 | AC62: 0 | AD62: 0 | AE62: 0
R63: APOYO A PERSONAS DE LA TERCERA EDAD | S63: 0 | V63: 0 | W63: 0 | X63: 0 | Y63: 0 | Z63: 0 | AA63: 0 | AB63: 0 | AC63: 0 | AD63: 0 | AE63: 0
R64: APOYO A PERSONAS PERDIDAS | S64: 0 | V64: 0 | W64: 0 | X64: 0 | Y64: 0 | Z64: 0 | AA64: 0 | AB64: 0 | AC64: 0 | AD64: 0 | AE64: 0
R65: RECUPERACIÓN DE ESPACIOS | S65: 0 | V65: 0 | W65: 0 | X65: 0 | Y65: 0 | Z65: 0 | AA65: 0 | AB65: 0 | AC65: 0 | AD65: 0 | AE65: 0
R66: OTRAS (Especificar en las novedades relevantes) | S66: 0 | V66: 0 | W66: 0 | X66: 0 | Y66: 0 | Z66: 0 | AA66: 0 | AB66: 0 | AC66: 0 | AD66: 0 | AE66: 0
R116: APOYOS Y DISPOSITIVOS REALIZADOS | U116: MORELIA | V116: JIQUILPAN | W116: ZAMORA | X116: LA PIEDAD | Y116: URUAPAN | Z116: APATZINGÁN | AA116: HUETAMO | AB116: COALCOMÁN | AC116: ZITÁCUARO | AD116: LÁZARO CÁRDENAS
R117: INSTITUCIONES
R118: REPORTES C5i
R119: ABANDERAMIENTOS
R120: OPERATIVOS
R121: PROGRAMAS
R122: MONITOREOS O RECORRIDOS
R123: A CONDUCTORES
R124: DISPOSITIVOS DE SEGURIDAD VIAL
R125: CAPACITACIONES
R126: CAMPAÑAS
R127: PROXIMIDAD SOCIAL
R129: SERVICIOS ESPECÍFICOS | U129: MORELIA | V129: JIQUILPAN | W129: ZAMORA | X129: LA PIEDAD | Y129: URUAPAN | Z129: APATZINGÁN | AA129: HUETAMO | AB129: COALCOMÁN | AC129: ZITÁCUARO | AD129: LÁZARO CÁRDENAS
R130: ESCUELAS
R131: PASOS PEATONALES
R132: ZONAS DE MAYOR
R133: VÍAS FÉRREAS
R134: SERVICIO DE ESCOLTAS
R135: CARAVANAS

Sheet SINIESTROS Y HECHOS
R1: 46129
R2: CLASIFICACIÓN DE HECHO O SINIESTRO | V2: MORELIA | AA2: JIQUILPAN
B3: CONTROL DE HECHOS | F3: MORELIA | G3: JIQUILPAN | H3: ZAMORA | I3: LA PIEDAD | J3: URUAPAN | K3: APATZINGÁN | L3: HUETAMO | M3: COALCOMÁN | N3: ZITÁCUARO | O3: LÁZARO CÁRDENAS | V3: CANTIDAD | W3: LESIONADOS | X3: DEFUNCIONES | Y3: FUERO COMÚN | AA3: CANTIDAD | AB3: LESIONADOS | AC3: DEFUNCIONES | AD3: FUERO COMÚN
B4: SINIESTROS | C4: 3 | F4: 0 | G4: 0 | H4: 2 | I4: 0 | J4: 1 | K4: 0 | L4: 0 | M4: 0 | N4: 0 | O4: 0 | R4: EXPLOSIÓN | S4: 0 | V4: 0 | W4: 0 | X4: 0 | Y4: 0 | Z4: 0 | AA4: 0 | AB4: 0 | AC4: 0 | AD4: 0
B5: HECHOS DE TRÁNSITO | C5: 5 | F5: 1 | G5: 0 | H5: 1 | I5: 0 | J5: 0 | K5: 0 | L5: 2 | M5: 0 | N5: 1 | O5: 0 | R5: INCENDIO | S5: 0 | V5: 0 | W5: 0 | X5: 0 | Y5: 0 | Z5: 0 | AA5: 0 | AB5: 0 | AC5: 0 | AD5: 0
R6: DESBARRANCAMIENTO | S6: 0 | V6: 0 | W6: 0 | X6: 0 | Y6: 0 | Z6: 0 | AA6: 0 | AB6: 0 | AC6: 0 | AD6: 0
B7: ESTATUS | F7: MORELIA | G7: JIQUILPAN | H7: ZAMORA | I7: LA PIEDAD | J7: URUAPAN | K7: APATZINGÁN | L7: HUETAMO | M7: COALCOMÁN | N7: ZITÁCUARO | O7: LÁZARO CÁRDENAS | R7: VOLCADURA | S7: 0 | V7: 0 | W7: 0 | X7: 0 | Y7: 0 | Z7: 0 | AA7: 0 | AB7: 0 | AC7: 0 | AD7: 0
B8: RESUELTOS | C8: 3 | F8: 0 | G8: 0 | H8: 1 | I8: 0 | J8: 0 | K8: 0 | L8: 2 | M8: 0 | N8: 0 | O8: 0 | R8: SALIDA DE RODAMIENTO | S8: 0 | V8: 0 | W8: 0 | X8: 0 | Y8: 0 | Z8: 0 | AA8: 0 | AB8: 0 | AC8: 0 | AD8: 0
B9: PENDIENTES | C9: 2 | F9: 1 | G9: 0 | H9: 0 | I9: 0 | J9: 0 | K9: 0 | L9: 0 | M9: 0 | N9: 1 | O9: 0 | R9: SUBIDA A CAMELLÓN | S9: 0 | V9: 0 | W9: 0 | X9: 0 | Y9: 0 | Z9: 0 | AA9: 0 | AB9: 0 | AC9: 0 | AD9: 0
B10: TURNADOS | C10: 3 | F10: 0 | G10: 0 | H10: 2 | I10: 0 | J10: 1 | K10: 0 | L10: 0 | M10: 0 | N10: 0 | O10: 0 | R10: CAIDA DE MOTOCICLETA | S10: 0 | V10: 0 | W10: 0 | X10: 0 | Y10: 0 | Z10: 0 | AA10: 0 | AB10: 0 | AC10: 0 | AD10: 0
R11: CHOQUE OBJETO FIJO | S11: 0 | V11: 0 | W11: 0 | X11: 0 | Y11: 0 | Z11: 0 | AA11: 0 | AB11: 0 | AC11: 0 | AD11: 0
B12: INVOLUCRADOS | F12: MORELIA | G12: JIQUILPAN | H12: ZAMORA | I12: LA PIEDAD | J12: URUAPAN | K12: APATZINGÁN | L12: HUETAMO | M12: COALCOMÁN | N12: ZITÁCUARO | O12: LÁZARO CÁRDENAS | R12: COLISIÓN POR ALCANCE | S12: 0 | V12: 0 | W12: 0 | X12: 0 | Y12: 0 | Z12: 0 | AA12: 0 | AB12: 0 | AC12: 0 | AD12: 0
B13: HOMBRES INVOLUCRADOS | C13: 14 | F13: 2 | G13: 0 | H13: 4 | I13: 0 | J13: 4 | K13: 0 | L13: 2 | M13: 0 | N13: 2 | O13: 0 | R13: COLISIÓN POR NO RESPETAR SEMÁFORO | S13: 0 | V13: 0 | W13: 0 | X13: 0 | Y13: 0 | Z13: 0 | AA13: 0 | AB13: 0 | AC13: 0 | AD13: 0
B14: MUJERES INVOLUCRADAS | C14: 1 | F14: 0 | G14: 0 | H14: 1 | I14: 0 | J14: 0 | K14: 0 | L14: 0 | M14: 0 | N14: 0 | O14: 0 | R14: COLISIÓN POR INVASIÓN DE CARRIL | S14: 1 | V14: 1 | W14: 0 | X14: 0 | Y14: 0 | Z14: 0 | AA14: 0 | AB14: 0 | AC14: 0 | AD14: 0
B15: MENORES INVOLUCRADOS | C15: 1 | F15: 0 | G15: 0 | H15: 0 | I15: 0 | J15: 1 | K15: 0 | L15: 0 | M15: 0 | N15: 0 | O15: 0 | R15: COLISIÓN POR CAMBIO DE CARRIL | S15: 0 | V15: 0 | W15: 0 | X15: 0 | Y15: 0 | Z15: 0 | AA15: 0 | AB15: 0 | AC15: 0 | AD15: 0
R16: COLISIÓN POR CORTE DE CIRCULACIÓN | S16: 0 | V16: 0 | W16: 0 | X16: 0 | Y16: 0 | Z16: 0 | AA16: 0 | AB16: 0 | AC16: 0 | AD16: 0
B17: CORRALÓN POR HECHOS DE TRANSITO | F17: MORELIA | G17: JIQUILPAN | H17: ZAMORA | I17: LA PIEDAD | J17: URUAPAN | K17: APATZINGÁN | L17: HUETAMO | M17: COALCOMÁN | N17: ZITÁCUARO | O17: LÁZARO CÁRDENAS | R17: COLISIÓN POR MANIOBRA REVERSA | S17: 0 | V17: 0 | W17: 0 | X17: 0 | Y17: 0 | Z17: 0 | AA17: 0 | AB17: 0 | AC17: 0 | AD17: 0
B18: VEHÍCULOS | C18: 8 | F18: 2 | G18: 0 | H18: 3 | I18: 0 | J18: 0 | K18: 0 | L18: 1 | M18: 0 | N18: 2 | O18: 0 | R18: CAIDA A CUNETA | S18: 0 | V18: 0 | W18: 0 | X18: 0 | Y18: 0 | Z18: 0 | AA18: 0 | AB18: 0 | AC18: 0 | AD18: 0
B19: MOTOCICLETAS | C19: 0 | F19: 0 | G19: 0 | H19: 0 | I19: 0 | J19: 0 | K19: 0 | L19: 0 | M19: 0 | N19: 0 | O19: 0 | R19: CAIDA ACUÁTICA DE VEHÍCULO | S19: 0 | V19: 0 | W19: 0 | X19: 0 | Y19: 0 | Z19: 0 | AA19: 0 | AB19: 0 | AC19: 0 | AD19: 0
B20: CAMIONES | C20: 1 | F20: 0 | G20: 0 | H20: 0 | I20: 0 | J20: 0 | K20: 0 | L20: 1 | M20: 0 | N20: 0 | O20: 0 | R20: COLISIÓN CON PEATÓN | S20: 0 | V20: 0 | W20: 0 | X20: 0 | Y20: 0 | Z20: 0 | AA20: 0 | AB20: 0 | AC20: 0 | AD20: 0
B21: OTROS | C21: 0 | F21: 0 | G21: 0 | H21: 0 | I21: 0 | J21: 0 | K21: 0 | L21: 0 | M21: 0 | N21: 0 | O21: 0
B23: PUESTOS A DISPOSICIÓN DEL MP POR SINIESTRO O HECHO DE TRÁNSITO | F23: MORELIA | G23: JIQUILPAN | H23: ZAMORA | I23: LA PIEDAD | J23: URUAPAN | K23: APATZINGÁN | L23: HUETAMO | M23: COALCOMÁN | N23: ZITÁCUARO | O23: LÁZARO CÁRDENAS | R23: CLASIFICACIÓN DE HECHO O SINIESTRO | V23: ZAMORA | AA23: LA PIEDAD
B24: VEHÍCULOS | C24: 4 | F24: 0 | G24: 0 | H24: 4 | I24: 0 | J24: 0 | K24: 0 | L24: 0 | M24: 0 | N24: 0 | O24: 0 | V24: CANTIDAD | W24: LESIONADOS | X24: DEFUNCIONES | Y24: FUERO COMÚN | AA24: CANTIDAD | AB24: LESIONADOS | AC24: DEFUNCIONES | AD24: FUERO COMÚN
B25: MOTOCICLETAS | C25: 2 | F25: 0 | G25: 0 | H25: 0 | I25: 0 | J25: 2 | K25: 0 | L25: 0 | M25: 0 | N25: 0 | O25: 0 | R25: EXPLOSIÓN | S25: 0 | V25: 0 | W25: 0 | X25: 0 | Y25: 0 | Z25: 0 | AA25: 0 | AB25: 0 | AC25: 0 | AD25: 0
B26: CAMIONES | C26: 0 | F26: 0 | G26: 0 | H26: 0 | I26: 0 | J26: 0 | K26: 0 | L26: 0 | M26: 0 | N26: 0 | O26: 0 | R26: INCENDIO | S26: 0 | V26: 0 | W26: 0 | X26: 0 | Y26: 0 | Z26: 0 | AA26: 0 | AB26: 0 | AC26: 0 | AD26: 0
B27: OTROS | C27: 0 | F27: 0 | G27: 0 | H27: 0 | I27: 0 | J27: 0 | K27: 0 | L27: 0 | M27: 0 | N27: 0 | O27: 0 | R27: DESBARRANCAMIENTO | S27: 0 | V27: 0 | W27: 0 | X27: 0 | Y27: 0 | Z27: 0 | AA27: 0 | AB27: 0 | AC27: 0 | AD27: 0
R28: VOLCADURA | S28: 1 | V28: 1 | W28: 0 | X28: 0 | Y28: 0 | Z28: 0 | AA28: 0 | AB28: 0 | AC28: 0 | AD28: 0
B29: VS INVOLUCRADOS | F29: MORELIA | G29: JIQUILPAN | H29: ZAMORA | I29: LA PIEDAD | J29: URUAPAN | K29: APATZINGÁN | L29: HUETAMO | M29: COALCOMÁN | N29: ZITÁCUARO | O29: LÁZARO CÁRDENAS | R29: SALIDA DE RODAMIENTO | S29: 0 | V29: 0 | W29: 0 | X29: 0 | Y29: 0 | Z29: 0 | AA29: 0 | AB29: 0 | AC29: 0 | AD29: 0
B30: CHOQUE ENTRE CAMIÓN Y MOTOCICLETA | C30: 0 | F30: 0 | G30: 0 | H30: 0 | I30: 0 | J30: 0 | K30: 0 | L30: 0 | M30: 0 | N30: 0 | O30: 0 | R30: SUBIDA A CAMELLÓN | S30: 0 | V30: 0 | W30: 0 | X30: 0 | Y30: 0 | Z30: 0 | AA30: 0 | AB30: 0 | AC30: 0 | AD30: 0
B31: CHOQUE ENTRE CAMIÓN Y VEHÍCULO | C31: 0 | F31: 0 | G31: 0 | H31: 0 | I31: 0 | J31: 0 | K31: 0 | L31: 0 | M31: 0 | N31: 0 | O31: 0 | R31: CAIDA DE MOTOCICLETA | S31: 0 | V31: 0 | W31: 0 | X31: 0 | Y31: 0 | Z31: 0 | AA31: 0 | AB31: 0 | AC31: 0 | AD31: 0
B32: CHOQUE ENTRE MOTOCICLETAS | C32: 1 | F32: 0 | G32: 0 | H32: 0 | I32: 0 | J32: 1 | K32: 0 | L32: 0 | M32: 0 | N32: 0 | O32: 0 | R32: CHOQUE OBJETO FIJO | S32: 0 | V32: 0 | W32: 0 | X32: 0 | Y32: 0 | Z32: 0 | AA32: 0 | AB32: 0 | AC32: 0 | AD32: 0
B33: CHOQUE ENTRE VEHÍCULOS | C33: 4 | F33: 1 | G33: 0 | H33: 2 | I33: 0 | J33: 0 | K33: 0 | L33: 0 | M33: 0 | N33: 1 | O33: 0 | R33: COLISIÓN POR ALCANCE | S33: 0 | V33: 0 | W33: 0 | X33: 0 | Y33: 0 | Z33: 0 | AA33: 0 | AB33: 0 | AC33: 0 | AD33: 0
B34: CHOQUE ENTRE MOTOCICLETA Y VEHÍCULO | C34: 0 | F34: 0 | G34: 0 | H34: 0 | I34: 0 | J34: 0 | K34: 0 | L34: 0 | M34: 0 | N34: 0 | O34: 0 | R34: COLISIÓN POR NO RESPETAR SEMÁFORO | S34: 0 | V34: 0 | W34: 0 | X34: 0 | Y34: 0 | Z34: 0 | AA34: 0 | AB34: 0 | AC34: 0 | AD34: 0
B35: CHOQUE ENTRE VEHÍCULO Y PEATÓN | C35: 0 | F35: 0 | G35: 0 | H35: 0 | I35: 0 | J35: 0 | K35: 0 | L35: 0 | M35: 0 | N35: 0 | O35: 0 | R35: COLISIÓN POR INVASIÓN DE CARRIL | S35: 0 | V35: 0 | W35: 0 | X35: 0 | Y35: 0 | Z35: 0 | AA35: 0 | AB35: 0 | AC35: 0 | AD35: 0
B36: VEHÍCULO ÚNICO | C36: 2 | F36: 0 | G36: 0 | H36: 1 | I36: 0 | J36: 0 | K36: 0 | L36: 1 | M36: 0 | N36: 0 | O36: 0 | R36: COLISIÓN POR CAMBIO DE CARRIL | S36: 2 | V36: 1 | W36: 1 | X36: 0 | Y36: 0 | Z36: 0 | AA36: 0 | AB36: 0 | AC36: 0 | AD36: 0
R37: COLISIÓN POR CORTE DE CIRCULACIÓN | S37: 2 | V37: 1 | W37: 1 | X37: 0 | Y37: 0 | Z37: 0 | AA37: 0 | AB37: 0 | AC37: 0 | AD37: 0
B38: VEHÍCULOS PARTICIPANTES | F38: MORELIA | G38: JIQUILPAN | H38: ZAMORA | I38: LA PIEDAD | J38: URUAPAN | K38: APATZINGÁN | L38: HUETAMO | M38: COALCOMÁN | N38: ZITÁCUARO | O38: LÁZARO CÁRDENAS | R38: COLISIÓN POR MANIOBRA REVERSA | S38: 0 | V38: 0 | W38: 0 | X38: 0 | Y38: 0 | Z38: 0 | AA38: 0 | AB38: 0 | AC38: 0 | AD38: 0
B39: VEHÍCULOS OFICIALES INVOL | C39: 0 | F39: 0 | G39: 0 | H39: 0 | I39: 0 | J39: 0 | K39: 0 | L39: 0 | M39: 0 | N39: 0 | O39: 0 | R39: CAIDA A CUNETA | S39: 0 | V39: 0 | W39: 0 | X39: 0 | Y39: 0 | Z39: 0 | AA39: 0 | AB39: 0 | AC39: 0 | AD39: 0
B40: SERVICIO PÚBLICO FED | C40: 0 | F40: 0 | G40: 0 | H40: 0 | I40: 0 | J40: 0 | K40: 0 | L40: 0 | M40: 0 | N40: 0 | O40: 0 | R40: CAIDA ACUÁTICA DE VEHÍCULO | S40: 0 | V40: 0 | W40: 0 | X40: 0 | Y40: 0 | Z40: 0 | AA40: 0 | AB40: 0 | AC40: 0 | AD40: 0
B41: TRANSPORTE PÚBLICO | C41: 1 | F41: 0 | G41: 0 | H41: 1 | I41: 0 | J41: 0 | K41: 0 | L41: 0 | M41: 0 | N41: 0 | O41: 0 | R41: COLISIÓN CON PEATÓN | S41: 0 | V41: 0 | W41: 0 | X41: 0 | Y41: 0 | Z41: 0 | AA41: 0 | AB41: 0 | AC41: 0 | AD41: 0
B42: AUTOMÓVIL | C42: 4 | F42: 1 | G42: 0 | H42: 2 | I42: 0 | J42: 0 | K42: 0 | L42: 0 | M42: 0 | N42: 1 | O42: 0
B43: CAMIONETA | C43: 4 | F43: 1 | G43: 0 | H43: 1 | I43: 0 | J43: 0 | K43: 0 | L43: 1 | M43: 0 | N43: 1 | O43: 0 | R43: CLASIFICACIÓN DE HECHO O SINIESTRO | V43: URUAPAN | AA43: APATZINGAN
B44: MICROBUS | C44: 0 | F44: 0 | G44: 0 | H44: 0 | I44: 0 | J44: 0 | K44: 0 | L44: 0 | M44: 0 | N44: 0 | O44: 0 | V44: CANTIDAD | W44: LESIONADOS | X44: DEFUNCIONES | Y44: FUERO COMÚN | AA44: CANTIDAD | AB44: LESIONADOS | AC44: DEFUNCIONES | AD44: FUERO COMÚN
B45: CAMIÓN URBANO DE PASAJEROS | C45: 0 | F45: 0 | G45: 0 | H45: 0 | I45: 0 | J45: 0 | K45: 0 | L45: 0 | M45: 0 | N45: 0 | O45: 0 | R45: EXPLOSIÓN | S45: 0 | V45: 0 | W45: 0 | X45: 0 | Y45: 0 | Z45: 0 | AA45: 0 | AB45: 0 | AC45: 0 | AD45: 0
B46: OMNIBUS | C46: 0 | F46: 0 | G46: 0 | H46: 0 | I46: 0 | J46: 0 | K46: 0 | L46: 0 | M46: 0 | N46: 0 | O46: 0 | R46: INCENDIO | S46: 0 | V46: 0 | W46: 0 | X46: 0 | Y46: 0 | Z46: 0 | AA46: 0 | AB46: 0 | AC46: 0 | AD46: 0
B47: CAMIONETA DE CARGA | C47: 1 | F47: 0 | G47: 0 | H47: 1 | I47: 0 | J47: 0 | K47: 0 | L47: 0 | M47: 0 | N47: 0 | O47: 0 | R47: DESBARRANCAMIENTO | S47: 0 | V47: 0 | W47: 0 | X47: 0 | Y47: 0 | Z47: 0 | AA47: 0 | AB47: 0 | AC47: 0 | AD47: 0
B48: CAMION DE CARGA | C48: 1 | F48: 0 | G48: 0 | H48: 0 | I48: 0 | J48: 0 | K48: 0 | L48: 1 | M48: 0 | N48: 0 | O48: 0 | R48: VOLCADURA | S48: 0 | V48: 0 | W48: 0 | X48: 0 | Y48: 0 | Z48: 0 | AA48: 0 | AB48: 0 | AC48: 0 | AD48: 0
B49: TRACTOR | C49: 0 | F49: 0 | G49: 0 | H49: 0 | I49: 0 | J49: 0 | K49: 0 | L49: 0 | M49: 0 | N49: 0 | O49: 0 | R49: SALIDA DE RODAMIENTO | S49: 0 | V49: 0 | W49: 0 | X49: 0 | Y49: 0 | Z49: 0 | AA49: 0 | AB49: 0 | AC49: 0 | AD49: 0
B50: FERROCARRIL | C50: 0 | F50: 0 | G50: 0 | H50: 0 | I50: 0 | J50: 0 | K50: 0 | L50: 0 | M50: 0 | N50: 0 | O50: 0 | R50: SUBIDA A CAMELLÓN | S50: 0 | V50: 0 | W50: 0 | X50: 0 | Y50: 0 | Z50: 0 | AA50: 0 | AB50: 0 | AC50: 0 | AD50: 0
B51: MOTOCICLETA | C51: 2 | F51: 0 | G51: 0 | H51: 0 | I51: 0 | J51: 2 | K51: 0 | L51: 0 | M51: 0 | N51: 0 | O51: 0 | R51: CAIDA DE MOTOCICLETA | S51: 0 | V51: 0 | W51: 0 | X51: 0 | Y51: 0 | Z51: 0 | AA51: 0 | AB51: 0 | AC51: 0 | AD51: 0
B52: BICICLETA | C52: 0 | F52: 0 | G52: 0 | H52: 0 | I52: 0 | J52: 0 | K52: 0 | L52: 0 | M52: 0 | N52: 0 | O52: 0 | R52: CHOQUE OBJETO FIJO | S52: 0 | V52: 0 | W52: 0 | X52: 0 | Y52: 0 | Z52: 0 | AA52: 0 | AB52: 0 | AC52: 0 | AD52: 0
B53: OTRO | C53: 0 | F53: 0 | G53: 0 | H53: 0 | I53: 0 | J53: 0 | K53: 0 | L53: 0 | M53: 0 | N53: 0 | O53: 0 | R53: COLISIÓN POR ALCANCE | S53: 5 | V53: 1 | W53: 2 | X53: 2 | Y53: 0 | Z53: 0 | AA53: 0 | AB53: 0 | AC53: 0 | AD53: 0
B54: SEMOVIENTE | C54: 0 | F54: 0 | G54: 0 | H54: 0 | I54: 0 | J54: 0 | K54: 0 | L54: 0 | M54: 0 | N54: 0 | O54: 0 | R54: COLISIÓN POR NO RESPETAR SEMÁFORO | S54: 0 | V54: 0 | W54: 0 | X54: 0 | Y54: 0 | Z54: 0 | AA54: 0 | AB54: 0 | AC54: 0 | AD54: 0
R55: COLISIÓN POR INVASIÓN DE CARRIL | S55: 0 | V55: 0 | W55: 0 | X55: 0 | Y55: 0 | Z55: 0 | AA55: 0 | AB55: 0 | AC55: 0 | AD55: 0
B56: PERSONAS ASEGURADAS | R56: COLISIÓN POR CAMBIO DE CARRIL | S56: 0 | V56: 0 | W56: 0 | X56: 0 | Y56: 0 | Z56: 0 | AA56: 0 | AB56: 0 | AC56: 0 | AD56: 0
B57: PERSONAS ASEGURADAS | C57: TOTAL | F57: MORELIA | G57: JIQUILPAN | H57: ZAMORA | I57: LA PIEDAD | J57: URUAPAN | K57: APATZINGÁN | L57: HUETAMO | M57: COALCOMÁN | N57: ZITÁCUARO | O57: LÁZARO CÁRDENAS | R57: COLISIÓN POR CORTE DE CIRCULACIÓN | S57: 0 | V57: 0 | W57: 0 | X57: 0 | Y57: 0 | Z57: 0 | AA57: 0 | AB57: 0 | AC57: 0 | AD57: 0
B58: CONSULTA DE ANTECEDENTES PENALES | C58: 0 | F58: 0 | G58: 0 | H58: 0 | I58: 0 | J58: 0 | K58: 0 | L58: 0 | M58: 0 | N58: 0 | O58: 0 | R58: COLISIÓN POR MANIOBRA REVERSA | S58: 0 | V58: 0 | W58: 0 | X58: 0 | Y58: 0 | Z58: 0 | AA58: 0 | AB58: 0 | AC58: 0 | AD58: 0
B59: PERSONAS A BARANDILLA | C59: 0 | F59: 0 | G59: 0 | H59: 0 | I59: 0 | J59: 0 | K59: 0 | L59: 0 | M59: 0 | N59: 0 | O59: 0 | R59: CAIDA A CUNETA | S59: 0 | V59: 0 | W59: 0 | X59: 0 | Y59: 0 | Z59: 0 | AA59: 0 | AB59: 0 | AC59: 0 | AD59: 0
B60: POR ALCOHOLEMIA | C60: 0 | F60: 0 | G60: 0 | H60: 0 | I60: 0 | J60: 0 | K60: 0 | L60: 0 | M60: 0 | N60: 0 | O60: 0 | R60: CAIDA ACUÁTICA DE VEHÍCULO | S60: 0 | V60: 0 | W60: 0 | X60: 0 | Y60: 0 | Z60: 0 | AA60: 0 | AB60: 0 | AC60: 0 | AD60: 0
B61: PERSONAS PRESENTADAS AL MP | C61: 0 | F61: 0 | G61: 0 | H61: 0 | I61: 0 | J61: 0 | K61: 0 | L61: 0 | M61: 0 | N61: 0 | O61: 0 | R61: COLISIÓN CON PEATÓN | S61: 0 | V61: 0 | W61: 0 | X61: 0 | Y61: 0 | Z61: 0 | AA61: 0 | AB61: 0 | AC61: 0 | AD61: 0
B62: POR ROBOS DIVERSOS | C62: 0 | F62: 0 | G62: 0 | H62: 0 | I62: 0 | J62: 0 | K62: 0 | L62: 0 | M62: 0 | N62: 0 | O62: 0
B63: POR LESIONES | C63: 0 | F63: 0 | G63: 0 | H63: 0 | I63: 0 | J63: 0 | K63: 0 | L63: 0 | M63: 0 | N63: 0 | O63: 0 | R63: CLASIFICACIÓN DE HECHO O SINIESTRO | V63: HUETAMO | AA63: COALCOMÁN
B64: POR HOMICIDIO CULPOSO | C64: 0 | F64: 0 | G64: 0 | H64: 0 | I64: 0 | J64: 0 | K64: 0 | L64: 0 | M64: 0 | N64: 0 | O64: 0 | V64: CANTIDAD | W64: LESIONADOS | X64: DEFUNCIONES | Y64: FUERO COMÚN | AA64: CANTIDAD | AB64: LESIONADOS | AC64: DEFUNCIONES | AD64: FUERO COMÚN
B65: POR HOMICIDIO DOLOSO | C65: 0 | F65: 0 | G65: 0 | H65: 0 | I65: 0 | J65: 0 | K65: 0 | L65: 0 | M65: 0 | N65: 0 | O65: 0 | R65: EXPLOSIÓN | S65: 0 | V65: 0 | W65: 0 | X65: 0 | Y65: 0 | Z65: 0 | AA65: 0 | AB65: 0 | AC65: 0 | AD65: 0
B66: PERSONAS AL MP POR VEHÍCULOS, MOTOS O CAMIONES ROBADOS | C66: 0 | F66: 0 | G66: 0 | H66: 0 | I66: 0 | J66: 0 | K66: 0 | L66: 0 | M66: 0 | N66: 0 | O66: 0 | R66: INCENDIO | S66: 0 | V66: 0 | W66: 0 | X66: 0 | Y66: 0 | Z66: 0 | AA66: 0 | AB66: 0 | AC66: 0 | AD66: 0
B67: PERSONAS AL MP POR PORTACION DE ARMAS | C67: 0 | F67: 0 | G67: 0 | H67: 0 | I67: 0 | J67: 0 | K67: 0 | L67: 0 | M67: 0 | N67: 0 | O67: 0 | R67: DESBARRANCAMIENTO | S67: 0 | V67: 0 | W67: 0 | X67: 0 | Y67: 0 | Z67: 0 | AA67: 0 | AB67: 0 | AC67: 0 | AD67: 0
B68: PERSONAS AL MP POR DROGA | C68: 0 | F68: 0 | G68: 0 | H68: 0 | I68: 0 | J68: 0 | K68: 0 | L68: 0 | M68: 0 | N68: 0 | O68: 0 | R68: VOLCADURA | S68: 0 | V68: 0 | W68: 0 | X68: 0 | Y68: 0 | Z68: 0 | AA68: 0 | AB68: 0 | AC68: 0 | AD68: 0
B69: OTROS DELITOS | C69: 0 | F69: 0 | G69: 0 | H69: 0 | I69: 0 | J69: 0 | K69: 0 | L69: 0 | M69: 0 | N69: 0 | O69: 0 | R69: SALIDA DE RODAMIENTO | S69: 1 | V69: 1 | W69: 0 | X69: 0 | Y69: 0 | Z69: 0 | AA69: 0 | AB69: 0 | AC69: 0 | AD69: 0
R70: SUBIDA A CAMELLÓN | S70: 0 | V70: 0 | W70: 0 | X70: 0 | Y70: 0 | Z70: 0 | AA70: 0 | AB70: 0 | AC70: 0 | AD70: 0
R71: CAIDA DE MOTOCICLETA | S71: 0 | V71: 0 | W71: 0 | X71: 0 | Y71: 0 | Z71: 0 | AA71: 0 | AB71: 0 | AC71: 0 | AD71: 0
B72: ASEGURAMIENTO / VEHICULOS | R72: CHOQUE OBJETO FIJO | S72: 0 | V72: 0 | W72: 0 | X72: 0 | Y72: 0 | Z72: 0 | AA72: 0 | AB72: 0 | AC72: 0 | AD72: 0
C73: TOTAL | F73: MORELIA | G73: JIQUILPAN | H73: ZAMORA | I73: LA PIEDAD | J73: URUAPAN | K73: APATZINGÁN | L73: HUETAMO | M73: COALCOMÁN | N73: ZITÁCUARO | O73: LÁZARO CÁRDENAS | R73: COLISIÓN POR ALCANCE | S73: 0 | V73: 0 | W73: 0 | X73: 0 | Y73: 0 | Z73: 0 | AA73: 0 | AB73: 0 | AC73: 0 | AD73: 0
B74: REVISIÓN DE ANTECEDENTES | C74: 0 | F74: 0 | G74: 0 | H74: 0 | I74: 0 | J74: 0 | K74: 0 | L74: 0 | M74: 0 | N74: 0 | O74: 0 | R74: COLISIÓN POR NO RESPETAR SEMÁFORO | S74: 0 | V74: 0 | W74: 0 | X74: 0 | Y74: 0 | Z74: 0 | AA74: 0 | AB74: 0 | AC74: 0 | AD74: 0
B75: VEHÍCULOS REVISADOS DE PROCEDENCIA EXTRANJERA | C75: 0 | F75: 0 | G75: 0 | H75: 0 | I75: 0 | J75: 0 | K75: 0 | L75: 0 | M75: 0 | N75: 0 | O75: 0 | R75: COLISIÓN POR INVASIÓN DE CARRIL | S75: 0 | V75: 0 | W75: 0 | X75: 0 | Y75: 0 | Z75: 0 | AA75: 0 | AB75: 0 | AC75: 0 | AD75: 0
B76: DESPOLARIZADO | C76: 0 | F76: 0 | G76: 0 | H76: 0 | I76: 0 | J76: 0 | K76: 0 | L76: 0 | M76: 0 | N76: 0 | O76: 0 | R76: COLISIÓN POR CAMBIO DE CARRIL | S76: 0 | V76: 0 | W76: 0 | X76: 0 | Y76: 0 | Z76: 0 | AA76: 0 | AB76: 0 | AC76: 0 | AD76: 0
B77: CORRALON POR FALTAS ADMINISTRATIVAS | C77: 0 | F77: 0 | G77: 0 | H77: 0 | I77: 0 | J77: 0 | K77: 0 | L77: 0 | M77: 0 | N77: 0 | O77: 0 | R77: COLISIÓN POR CORTE DE CIRCULACIÓN | S77: 0 | V77: 0 | W77: 0 | X77: 0 | Y77: 0 | Z77: 0 | AA77: 0 | AB77: 0 | AC77: 0 | AD77: 0
B78: PRESENTADOS AL MP | C78: 0 | F78: 0 | G78: 0 | H78: 0 | I78: 0 | J78: 0 | K78: 0 | L78: 0 | M78: 0 | N78: 0 | O78: 0 | R78: COLISIÓN POR MANIOBRA REVERSA | S78: 0 | V78: 0 | W78: 0 | X78: 0 | Y78: 0 | Z78: 0 | AA78: 0 | AB78: 0 | AC78: 0 | AD78: 0
B79: RESGUARDADOS POR ABANDONO | C79: 0 | F79: 0 | G79: 0 | H79: 0 | I79: 0 | J79: 0 | K79: 0 | L79: 0 | M79: 0 | N79: 0 | O79: 0 | R79: CAIDA A CUNETA | S79: 1 | V79: 1 | W79: 0 | X79: 0 | Y79: 0 | Z79: 0 | AA79: 0 | AB79: 0 | AC79: 0 | AD79: 0
B80: ASEGURADOS POR HECHOS DELICTIVOS | C80: 0 | F80: 0 | G80: 0 | H80: 0 | I80: 0 | J80: 0 | K80: 0 | L80: 0 | M80: 0 | N80: 0 | O80: 0 | R80: CAIDA ACUÁTICA DE VEHÍCULO | S80: 0 | V80: 0 | W80: 0 | X80: 0 | Y80: 0 | Z80: 0 | AA80: 0 | AB80: 0 | AC80: 0 | AD80: 0
B81: RECUPERADOS CON ALTERACIONES EN SUS MEDIOS DE IDENTIFICACIÓN | C81: 0 | F81: 0 | G81: 0 | H81: 0 | I81: 0 | J81: 0 | K81: 0 | L81: 0 | M81: 0 | N81: 0 | O81: 0 | R81: COLISIÓN CON PEATÓN | S81: 0 | V81: 0 | W81: 0 | X81: 0 | Y81: 0 | Z81: 0 | AA81: 0 | AB81: 0 | AC81: 0 | AD81: 0
B82: RECUPERADOS CON REPORTE DE ROBO | C82: 0 | F82: 0 | G82: 0 | H82: 0 | I82: 0 | J82: 0 | K82: 0 | L82: 0 | M82: 0 | N82: 0 | O82: 0
B83: CONOCIMIENTO DE REPORTE DE ROBO | C83: 0 | F83: 0 | G83: 0 | H83: 0 | I83: 0 | J83: 0 | K83: 0 | L83: 0 | M83: 0 | N83: 0 | O83: 0 | R83: CLASIFICACIÓN DE HECHO O SINIESTRO | V83: ZITACUARO | AA83: LAZARO CARDENAS
B84: ASEGURADOS POR OTROS MOTIVOS | C84: 0 | F84: 0 | G84: 0 | H84: 0 | I84: 0 | J84: 0 | K84: 0 | L84: 0 | M84: 0 | N84: 0 | O84: 0 | V84: CANTIDAD | W84: LESIONADOS | X84: DEFUNCIONES | Y84: FUERO COMÚN | AA84: CANTIDAD | AB84: LESIONADOS | AC84: DEFUNCIONES | AD84: FUERO COMÚN
R85: EXPLOSIÓN | S85: 0 | V85: 0 | W85: 0 | X85: 0 | Y85: 0 | Z85: 0 | AA85: 0 | AB85: 0 | AC85: 0 | AD85: 0
B86: ASEGURAMIENTO / MOTOCICLETAS | R86: INCENDIO | S86: 0 | V86: 0 | W86: 0 | X86: 0 | Y86: 0 | Z86: 0 | AA86: 0 | AB86: 0 | AC86: 0 | AD86: 0
C87: TOTAL | F87: MORELIA | G87: JIQUILPAN | H87: ZAMORA | I87: LA PIEDAD | J87: URUAPAN | K87: APATZINGÁN | L87: HUETAMO | M87: COALCOMÁN | N87: ZITÁCUARO | O87: LÁZARO CÁRDENAS | R87: DESBARRANCAMIENTO | S87: 0 | V87: 0 | W87: 0 | X87: 0 | Y87: 0 | Z87: 0 | AA87: 0 | AB87: 0 | AC87: 0 | AD87: 0
B88: REVISIÓN DE ANTECEDENTES | C88: 0 | F88: 0 | G88: 0 | H88: 0 | I88: 0 | J88: 0 | K88: 0 | L88: 0 | M88: 0 | N88: 0 | O88: 0 | R88: VOLCADURA | S88: 0 | V88: 0 | W88: 0 | X88: 0 | Y88: 0 | Z88: 0 | AA88: 0 | AB88: 0 | AC88: 0 | AD88: 0
B89: VEHÍCULOS REVISADOS DE PROCEDENCIA EXTRANJERA | C89: 0 | F89: 0 | G89: 0 | H89: 0 | I89: 0 | J89: 0 | K89: 0 | L89: 0 | M89: 0 | N89: 0 | O89: 0 | R89: SALIDA DE RODAMIENTO | S89: 0 | V89: 0 | W89: 0 | X89: 0 | Y89: 0 | Z89: 0 | AA89: 0 | AB89: 0 | AC89: 0 | AD89: 0
B90: DESPOLARIZADO | C90: 0 | F90: 0 | G90: 0 | H90: 0 | I90: 0 | J90: 0 | K90: 0 | L90: 0 | M90: 0 | N90: 0 | O90: 0 | R90: SUBIDA A CAMELLÓN | S90: 0 | V90: 0 | W90: 0 | X90: 0 | Y90: 0 | Z90: 0 | AA90: 0 | AB90: 0 | AC90: 0 | AD90: 0
B91: CORRALON POR FALTAS ADMINISTRATIVAS | C91: 0 | F91: 0 | G91: 0 | H91: 0 | I91: 0 | J91: 0 | K91: 0 | L91: 0 | M91: 0 | N91: 0 | O91: 0 | R91: CAIDA DE MOTOCICLETA | S91: 0 | V91: 0 | W91: 0 | X91: 0 | Y91: 0 | Z91: 0 | AA91: 0 | AB91: 0 | AC91: 0 | AD91: 0
B92: PRESENTADOS AL MP | C92: 0 | F92: 0 | G92: 0 | H92: 0 | I92: 0 | J92: 0 | K92: 0 | L92: 0 | M92: 0 | N92: 0 | O92: 0 | R92: CHOQUE OBJETO FIJO | S92: 0 | V92: 0 | W92: 0 | X92: 0 | Y92: 0 | Z92: 0 | AA92: 0 | AB92: 0 | AC92: 0 | AD92: 0
B93: RESGUARDADOS POR ABANDONO | C93: 0 | F93: 0 | G93: 0 | H93: 0 | I93: 0 | J93: 0 | K93: 0 | L93: 0 | M93: 0 | N93: 0 | O93: 0 | R93: COLISIÓN POR ALCANCE | S93: 0 | V93: 0 | W93: 0 | X93: 0 | Y93: 0 | Z93: 0 | AA93: 0 | AB93: 0 | AC93: 0 | AD93: 0
B94: ASEGURADOS POR HECHOS DELICTIVOS | C94: 0 | F94: 0 | G94: 0 | H94: 0 | I94: 0 | J94: 0 | K94: 0 | L94: 0 | M94: 0 | N94: 0 | O94: 0 | R94: COLISIÓN POR NO RESPETAR SEMÁFORO | S94: 0 | V94: 0 | W94: 0 | X94: 0 | Y94: 0 | Z94: 0 | AA94: 0 | AB94: 0 | AC94: 0 | AD94: 0
B95: RECUPERADOS CON ALTERACIONES EN SUS MEDIOS DE IDENTIFICACIÓN | C95: 0 | F95: 0 | G95: 0 | H95: 0 | I95: 0 | J95: 0 | K95: 0 | L95: 0 | M95: 0 | N95: 0 | O95: 0 | R95: COLISIÓN POR INVASIÓN DE CARRIL | S95: 0 | V95: 0 | W95: 0 | X95: 0 | Y95: 0 | Z95: 0 | AA95: 0 | AB95: 0 | AC95: 0 | AD95: 0
B96: RECUPERADOS CON REPORTE DE ROBO | C96: 0 | F96: 0 | G96: 0 | H96: 0 | I96: 0 | J96: 0 | K96: 0 | L96: 0 | M96: 0 | N96: 0 | O96: 0 | R96: COLISIÓN POR CAMBIO DE CARRIL | S96: 0 | V96: 0 | W96: 0 | X96: 0 | Y96: 0 | Z96: 0 | AA96: 0 | AB96: 0 | AC96: 0 | AD96: 0
B97: CONOCIMIENTO DE REPORTE DE ROBO | C97: 0 | F97: 0 | G97: 0 | H97: 0 | I97: 0 | J97: 0 | K97: 0 | L97: 0 | M97: 0 | N97: 0 | O97: 0 | R97: COLISIÓN POR CORTE DE CIRCULACIÓN | S97: 1 | V97: 1 | W97: 0 | X97: 0 | Y97: 0 | Z97: 0 | AA97: 0 | AB97: 0 | AC97: 0 | AD97: 0
B98: ASEGURADOS POR OTROS MOTIVOS | C98: 0 | F98: 0 | G98: 0 | H98: 0 | I98: 0 | J98: 0 | K98: 0 | L98: 0 | M98: 0 | N98: 0 | O98: 0 | R98: COLISIÓN POR MANIOBRA REVERSA | S98: 0 | V98: 0 | W98: 0 | X98: 0 | Y98: 0 | Z98: 0 | AA98: 0 | AB98: 0 | AC98: 0 | AD98: 0
R99: CAIDA A CUNETA | S99: 0 | V99: 0 | W99: 0 | X99: 0 | Y99: 0 | Z99: 0 | AA99: 0 | AB99: 0 | AC99: 0 | AD99: 0
B100: ASEGURAMIENTO / CAMIONES | R100: CAIDA ACUÁTICA DE VEHÍCULO | S100: 0 | V100: 0 | W100: 0 | X100: 0 | Y100: 0 | Z100: 0 | AA100: 0 | AB100: 0 | AC100: 0 | AD100: 0
C101: TOTAL | F101: MORELIA | G101: JIQUILPAN | H101: ZAMORA | I101: LA PIEDAD | J101: URUAPAN | K101: APATZINGÁN | L101: HUETAMO | M101: COALCOMÁN | N101: ZITÁCUARO | O101: LÁZARO CÁRDENAS | R101: COLISIÓN CON PEATÓN | S101: 0 | V101: 0 | W101: 0 | X101: 0 | Y101: 0 | Z101: 0 | AA101: 0 | AB101: 0 | AC101: 0 | AD101: 0
...

Sheet PANEL_CONTROL
B2: S.I.E.V.A. | CONTROL COMMAND
B4: FECHA DE INICIO | C4: 46120
B5: HORA DE INICIO | C5: 00:00
B6: FECHA DE CORTE FIN | C6: 46121
B7: HORA DE CORTE FIN | C7: 12:00
B9: ESTADO DEL MOTOR: | C9: ❌ ERROR
B11: UNIDAD DE DELEGACIONES | CLOUDVIAL AI v3.1

Sheet NOV. REL
A1: N°. | B1: HORA | C1: LUGAR | D1: ASUNTO | E1: RESOLUCIÓN | F1: VEHÍCULOS TURNADOS, PERSONAS DETENIDAS, VEHÍCULOS RECUPERADOS (CANTIDAD Y DATOS GENERALES) | G1: GRAFICA 1 | H1: GRAFICA 2 | I1: GRAFICA 3
A2: 4 | B2: 00:00 horas | C2: AMPLIACIÓN DE LA CARRETERA / CIUDAD HIDALGO, TUXPAN, MARAVATIO, ZITACUARO, TLAPUJAHUA. | D2: Se informa que, Inicia el Operativo de Seguridad Vial y Prevención del Delito, realizando recorridos, abanderamientos y resguardo de la maquinaria en la Obra de Reparación y Ampliación de la carretera Zitácuaro – Maravatio a la altura de los Municipios de Zitácuaro, Ciudad Hidalgo, Tuxpan y Maravatio, en Coordinación con el personal operativo de las Delegaciones. | E2: Con el siguiente Estado de Fuerza: Total de Elementos: 11 Totlal de Unidades: 05 | F2: Otros operativos y/o Abanderamientos.
A3: 4 | B3: 10:00 horas | C3: ALVARO OBREGON- ZINAPECUARO | D3: Se dio inicio al operativo seguridad carretera en el tramo comprendido entre ZINAPECUARO - MORELIA, en el municipio de Álvaro Obregón. Dicho operativo fue coordinado por las delegación de Zinapecuaro, con el objetivo de garantizar la seguridad vial y el orden en la zona. Al momento del inicio del operativo, no se registraron novedades relevantes. | E3: Con el siguiente Estado de Fuerza: Total de Elementos: 02 Total de Unidades: 01 | F3: OPERATIVO - SEGURIDAD EN CARRETERAS
A4: 4 | B4: 10:00 horas | C4: SALAMANCA - MORELIA | D4: Se dio inicio al operativo seguridad carretera en el tramo comprendido entre Tarímbaro y Salida Salamanca, en el municipio de Tarímbaro. Dicho operativo fue coordinado por las delegación de Tarímbaro, con el objetivo de garantizar la seguridad vial y el orden en la zona. Al momento del inicio del operativo, no se registraron novedades relevantes. | E4: Con el siguiente Estado de Fuerza: Total de Elementos: 02 Totlal de Unidades: 01 | F4: OPERATIVO - SEGURIDAD EN CARRETERAS
A5: 4 | B5: 10:00 horas | C5: 10 REGIONES | D5: La implementación del dispositivo Escuela Segura inició con el reconocimiento previo de las vialidades circundantes y la identificación de los puntos de mayor conflicto vial. Se instalaron dispositivos de control de tránsito, tales como conos y vallas, para delimitar las áreas de ascenso y descenso de pasajeros, garantizando que los accesos principales al plantel permanecieran despejados. Asimismo, se estableció una coordinación estrecha con las autoridades educativas para ordenar los flujos de ingreso, asegurando que la logística operativa se ajustara estrictamente a los horarios escolares establecidos. Durante el desarrollo del operativo, el personal abanderó de manera permanente los pasos de cebra y zonas de cruce peatonal, priorizando en todo momento la integridad física de los alumnos y padres de familia. Se gestionó activamente la circulación vehicular para evitar el estacionamiento en doble fila y se supervisó que los conductores respetaran los límites de velocidad permitidos en zona escolar. Una vez finalizada la jornada de ingreso o egreso, la vialidad quedó sin incidentes. | E5: Con el siguiente Estado de Fuerza: Total de Elementos: 132 Total de Unidades: 64 | F5: OPERATIVO - ESCUELAS SEGURAS
A6: 4 | B6: 10:00 horas | C6: 04 REGIONES | D6: El operativo de apoyo a la vialidad y seguridad ciudadana se implementó mediante recorridos estratégicos de patrullaje preventivo sobre los tramos del periférico y las principales avenidas de la ciudad. Durante estos desplazamientos, se mantuvo una presencia institucional constante con el objetivo de disuadir conductas de riesgo y brindar esquemas de vigilancia proactiva tanto para los conductores como para la población en general. De manera complementaria, se abanderaron de forma prioritaria los pasos peatonales y zonas de alta afluencia, facilitando el cruce seguro de transeúntes y fomentando la cultura de respeto al peatón por parte de los automovilistas. Asimismo, el personal operativo brindó asistencia técnica y auxilio vial a conductores que presentaron fallas mecánicas en sus unidades, agilizando su retiro de las vías de circulación para evitar congestionamientos. Al concluir el despliegue, se reportó un saldo blanco y se confirmó el restablecimiento total del orden y la fluidez en los sectores intervenidos. | E6: Con el siguiente Estado de Fuerza: Total de Elementos: 60 Totlal de Unidades: 22 | F6: OPERATIVO -GUARDIAN VIAL
A7: 4 | B7: 10:00 horas | C7: 04 REGIONES | D7: El dispositivo de monitoreo y vigilancia se desplegó de manera estratégica en los perímetros de instituciones gubernamentales, zonas bancarias y establecimientos comerciales con mayor afluencia de ciudadanos en la ciudad, la vialidad quedó sin incidentes. | E7: Con el siguiente Estado de Fuerza: Total de Elementos: 57 Total de Unidades: 22 | F7: OPERATIVO - MONITOREO INTEGRAL
A8: 4 | B8: 22:10 horas | C8: ARIO DE ROSALES | D8: Se informa que, con fecha del 16 de abril de 2026, siendo aproximadamente las 22:10 horas, se registró un siniestro vial clasificado como choque entre dos vehículos motorizados (motocicletas) sobre la carretera federal Quiroga-Tepalcatepec. El hecho tuvo lugar específicamente en el tramo carretero Santa Clara-Ario, a la altura del kilómetro 68, tomando como punto de referencia la báscula de "Los Moreno" Como consecuencia del impacto, se confirmó el saldo de dos personas fallecidas y dos personas lesionadas en el lugar de los hechos. | E8: En relación con los vehículos involucrados, el Vehículo (A) corresponde a una motocicleta marca VAJAJ, línea Pulsar, color negro con naranja, modelo desconocido, sin placas de circulación y con número de serie MDD2A36FZ7GC00857; por su parte, el Vehículo (B) es una motocicleta marca ITALIKA, tipo motocicleta, color rojo, modelo 2019, sin placas de circulación y número de serie 3SCBREE0K1002857. Respecto a los ocupantes, resultaron lesionados los ciudadanos Jonso Suriel Ortiz Reyes, de 12 años, y Gonzalo Ortiz Arreola, de 47 años, ambos con domicilio en la Col. Citlamina Manzana 14 Lote 7, quienes fueron trasladados al IMSS de esta ciudad para su valoración médica a bordo de las unidades PCM-04 y PCM-02, esta última bajo el mando de Juan Pablo Primer Orozco. Lamentablemente, perdieron la vida en el sitio los ciudadanos Jesus Hernández Ramírez, de 30 años, con domicilio en J. Trinidad Guido #74, Col. Rosales, y Genaro Castillo Gaona, de 33 años, con domicilio en Av. Manolo Escobar s/n, Col. Loma Linda; de los cuerpos se hizo cargo el perito Omar Rosales Duran en la unidad de SEMEFO. | F8: Para la remosión de los vehículos se hace cargo personal de Grúas MG.
A9: 2 | B9: 14:22 horas | C9: ZAMORA | D9: Se informa que, siendo las 13:20 horas, personal de la Guardia Civil de Seguridad Vial recibió un reporte vía telefónica referente a un siniestro vial ocurrido en el Libramiento Norte Zamora-La Barca, específicamente a la altura de "Mega Abastos" . Al arribar al lugar de los hechos, se confirmó la clasificación del siniestro como un choque por corte de circulación con resultado de una persona lesionada del sexo masculino, cuyos datos generales se desconocen al momento, ya que, según información proporcionada por testigos oculares, el lesionado fue trasladado para recibir atención médica antes del arribo de la autoridad. | E9: En el lugar se identificaron dos unidades con huellas de colisión. El Vehículo (A) corresponde a una camioneta pickup marca Toyota, línea Hi Lux 4 puertas, modelo 2022, color rojo, con placas de circulación NF8195C del Estado de Michoacán y número de serie MROBA3CD1N010693, conducida por una persona de generales desconocidas. El Vehículo (B) es un ómnibus marca Mercedes Benz, línea Onibus, modelo 2005, color blanco, sin placas de circulación, con número de serie 3MBAA2C65M010133 y propiedad de "Servicios de transportes urbanos y suburbanos SRH. 2000", cuyo conductor también se desconoce. La dinámica del evento indica que el Vehículo (A) se encontraba estático en el acotamiento e intentó incorporarse al carril izquierdo, lo que provocó que el Vehículo (B), que circulaba de norte a sur, lo impactara en su costado izquierdo; el corte de circulación derivó en que el Vehículo (B) quedara sobre el carril de circulación y el Vehículo (A) terminara en el acotamiento norte, fuera de la cinta asfáltica. | F9: Los vehículos fueron remitidos al corralón de Grúas Zamoranas.
A10: 2 | B10: 0.70972222 | C10: URUAPAN | D10: Personal adscrito a la Delegación de Seguridad Vial, se encuentra realizando labores de perifoneo y proximidad social en la calle Gonzalo Sosa y arterias aledañas a la Estación No. 01 "IMSS" (ubicada en la intersección de calle Francisco I. Madero y Avenida Wenceslao Victoria Soto, dicha acción tiene como objetivo exhortar a la ciudadanía al retiro voluntario de los vehículos estacionados en la zona, garantizando el espacio necesario para el inicio de la instalación de vallas metálicas y el confinamiento del área perimetral, previo al evento de inauguración programado para el día sábado 18 de abril. | E10: Con el siguiente Estado de Fuerza: Total de Elementos: 03 Total de Unidades: 01
A11: 2

Sheet EST. FUR
B2: FECHA | C2: 46120 | D2: ESTADO DE FUERZA DE PERSONAL
B3: UBICACCIÓN | C3: CATEGORIA | D3: PRESENTES | E3: FRANCOS | F3: FALTANDO | G3: CURSOS | H3: VACACIONES | I3: COMISIONADOS | J3: INCAPACIDAD | K3: PERMISO | L3: OTROS | M3: TOTAL, POR AGRUPAMIENTO
B4: COORDINACIÓN DE DELEGACIONES | C4: OPERATIVOS | D4: 7 | E4: 1 | F4: 0 | G4: 0 | H4: 0 | I4: 0 | J4: 0 | K4: 0 | L4: 0 | M4: 8
C5: ADMINISTRATIVOS | D5: 3 | E5: 2 | F5: 0 | G5: 0 | H5: 0 | I5: 0 | J5: 0 | K5: 0 | L5: 0 | M5: 5
B6: REGIÓN MORELIA | C6: OPERATIVOS | D6: 33 | E6: 7 | F6: 0 | G6: 1 | H6: 0 | I6: 2 | J6: 0 | K6: 0 | L6: 2 | M6: 45
C7: ADMINISTRATIVOS | D7: 11 | E7: 3 | F7: 0 | G7: 1 | H7: 0 | I7: 0 | J7: 0 | K7: 0 | L7: 0 | M7: 15
B8: REGIÓN JIQUILPAN | C8: OPERATIVOS | D8: 12 | E8: 1 | F8: 0 | G8: 0 | H8: 0 | I8: 0 | J8: 0 | K8: 0 | L8: 1 | M8: 14
C9: ADMINISTRATIVOS | D9: 6 | E9: 0 | F9: 0 | G9: 0 | H9: 0 | I9: 0 | J9: 0 | K9: 0 | L9: 0 | M9: 6
B10: REGIÓN ZAMORA | C10: OPERATIVOS | D10: 28 | E10: 11 | F10: 1 | G10: 1 | H10: 0 | I10: 0 | J10: 0 | K10: 0 | L10: 0 | M10: 41
C11: ADMINISTRATIVOS | D11: 15 | E11: 1 | F11: 0 | G11: 0 | H11: 0 | I11: 0 | J11: 0 | K11: 0 | L11: 0 | M11: 16
B12: REGIÓN LA PIEDAD | C12: OPERATIVOS | D12: 11 | E12: 4 | F12: 0 | G12: 2 | H12: 0 | I12: 0 | J12: 0 | K12: 0 | L12: 0 | M12: 17
C13: ADMINISTRATIVOS | D13: 7 | E13: 1 | F13: 0 | G13: 0 | H13: 0 | I13: 0 | J13: 0 | K13: 0 | L13: 0 | M13: 8
B14: REGIÓN URUAPAN | C14: OPERATIVOS | D14: 18 | E14: 1 | F14: 0 | G14: 0 | H14: 0 | I14: 3 | J14: 0 | K14: 0 | L14: 0 | M14: 22
C15: ADMINISTRATIVOS | D15: 19 | E15: 2 | F15: 0 | G15: 0 | H15: 0 | I15: 0 | J15: 0 | K15: 0 | L15: 1 | M15: 22
B16: REGIÓN APATZINGAN | C16: OPERATIVOS | D16: 6 | E16: 4 | F16: 0 | G16: 1 | H16: 0 | I16: 4 | J16: 0 | K16: 0 | L16: 1 | M16: 16
C17: ADMINISTRATIVOS | D17: 5 | E17: 1 | F17: 0 | G17: 0 | H17: 0 | I17: 0 | J17: 0 | K17: 0 | L17: 0 | M17: 6
B18: REGIÓN HUETAMO | C18: OPERATIVOS | D18: 6 | E18: 3 | F18: 0 | G18: 0 | H18: 0 | I18: 0 | J18: 0 | K18: 0 | L18: 0 | M18: 9
C19: ADMINISTRATIVOS | D19: 3 | E19: 0 | F19: 0 | G19: 0 | H19: 0 | I19: 0 | J19: 0 | K19: 0 | L19: 0 | M19: 3
B20: REGIÓN COALCOMAN | C20: OPERATIVOS | D20: 2 | E20: 2 | F20: 0 | G20: 0 | H20: 0 | I20: 0 | J20: 1 | K20: 0 | L20: 0 | M20: 5
C21: ADMINISTRATIVOS | D21: 3 | E21: 0 | F21: 0 | G21: 0 | H21: 0 | I21: 0 | J21: 0 | K21: 0 | L21: 0 | M21: 3
B22: REGIÓN ZITACUARO | C22: OPERATIVOS | D22: 26 | E22: 6 | F22: 0 | G22: 1 | H22: 0 | I22: 0 | J22: 1 | K22: 0 | L22: 0 | M22: 34
C23: ADMINISTRATIVOS | D23: 11 | E23: 2 | F23: 0 | G23: 0 | H23: 0 | I23: 0 | J23: 0 | K23: 0 | L23: 0 | M23: 13
B24: REGIÓN LAZARO CARDENAS | C24: OPERATIVOS | D24: 4 | E24: 4 | F24: 0 | G24: 0 | H24: 0 | I24: 4 | J24: 1 | K24: 0 | L24: 0 | M24: 13
C25: ADMINISTRATIVOS | D25: 5 | E25: 0 | F25: 0 | G25: 0 | H25: 0 | I25: 0 | J25: 0 | K25: 0 | L25: 0 | M25: 5
B26: TOTAL | C26: OPERATIVOS | D26: 153 | E26: 44 | F26: 1 | G26: 6 | H26: 0 | I26: 13 | J26: 3 | K26: 0 | L26: 4 | M26: 224
C27: ADMINISTRATIVOS | D27: 88 | E27: 12 | F27: 0 | G27: 1 | H27: 0 | I27: 0 | J27: 0 | K27: 0 | L27: 1 | M27: 102

Sheet EST. VEH
B2: FECHA | C2: 46120 | D2: ESTADO DE FUERZA VEHICULAR ACTIVO
B3: ÁREA Y/O REGIÓN | C3: CHARGER | D3: FORD 150 | E3: CAMIONETA F250 | F3: RAM DODGE 1500 | G3: JEEP PATRIOT | H3: ECO SPORT | I3: TSURU | J3: PLATINA | K3: KAWASAKY KLR650 | L3: KAWASAKY ER-6N | M3: TOTAL ACTIVAS | N3: TRUE
B4: REGIÓN MORELIA | C4: 4 | D4: 1 | E4: 0 | F4: 2 | G4: 4 | H4: 0 | I4: 2 | J4: 0 | K4: 5 | L4: 0 | M4: 18
B5: REGIÓN JÍQUILPAN | C5: 0 | D5: 0 | E5: 0 | F5: 0 | G5: 3 | H5: 0 | I5: 0 | J5: 0 | K5: 2 | L5: 0 | M5: 5
B6: REGIÓN ZAMORA | C6: 4 | D6: 1 | E6: 1 | F6: 1 | G6: 2 | H6: 0 | I6: 1 | J6: 0 | K6: 4 | L6: 0 | M6: 14
B7: REGIÓN LA PIEDAD | C7: 3 | D7: 0 | E7: 0 | F7: 1 | G7: 2 | H7: 1 | I7: 0 | J7: 0 | K7: 2 | L7: 0 | M7: 9
B8: REGIÓN URUAPAN | C8: 5 | D8: 1 | E8: 0 | F8: 1 | G8: 2 | H8: 0 | I8: 0 | J8: 0 | K8: 1 | L8: 0 | M8: 10
B9: REGIÓN APATZINGAN | C9: 2 | D9: 0 | E9: 0 | F9: 0 | G9: 3 | H9: 0 | I9: 2 | J9: 0 | K9: 4 | L9: 0 | M9: 11
B10: REGIÓN HUETAMO | C10: 0 | D10: 0 | E10: 0 | F10: 0 | G10: 0 | H10: 0 | I10: 1 | J10: 0 | K10: 0 | L10: 0 | M10: 1
B11: REGIÓN COALCOMAN | C11: 0 | D11: 0 | E11: 0 | F11: 0 | G11: 0 | H11: 0 | I11: 2 | J11: 0 | K11: 0 | L11: 0 | M11: 2
B12: REGIÓN ZITACUARO | C12: 1 | D12: 1 | E12: 0 | F12: 1 | G12: 4 | H12: 0 | I12: 1 | J12: 0 | K12: 0 | L12: 0 | M12: 8
B13: REGIÓN LÁZARO CÁRDENAS | C13: 2 | D13: 1 | E13: 0 | F13: 0 | G13: 2 | H13: 0 | I13: 0 | J13: 0 | K13: 0 | L13: 0 | M13: 5
B14: TOTAL | C14: 21 | D14: 5 | E14: 1 | F14: 6 | G14: 22 | H14: 1 | I14: 9 | J14: 0 | K14: 18 | L14: 0 | M14: 83
B16: FECHA | C16: 46120 | D16: ESTADO DE FUERZA VEHICULAR INACTIVO
B17: ÁREA Y/O REGIÓN | C17: CHARGER | D17: FORD 150 | E17: CAMIONETA F250 | F17: RAM DODGE 1500 | G17: JEEP PATRIOT | H17: ECO SPORT | I17: TSURU | J17: PLATINA | K17: KAWASAKY KLR650 | L17: KAWASAKY ER-6N | M17: TOTAL DE INACTIVAS
B18: REGIÓN MORELIA | C18: 0 | D18: 0 | E18: 0 | F18: 0 | G18: 2 | H18: 0 | I18: 0 | J18: 0 | K18: 6 | L18: 0 | M18: 8
B19: REGIÓN JÍQUILPAN | C19: 0 | D19: 0 | E19: 0 | F19: 0 | G19: 2 | H19: 0 | I19: 0 | J19: 1 | K19: 1 | L19: 0 | M19: 4
B20: REGIÓN ZAMORA | C20: 1 | D20: 0 | E20: 1 | F20: 0 | G20: 2 | H20: 0 | I20: 0 | J20: 0 | K20: 3 | L20: 0 | M20: 7
B21: REGIÓN LA PIEDAD | C21: 0 | D21: 1 | E21: 0 | F21: 0 | G21: 0 | H21: 0 | I21: 0 | J21: 0 | K21: 2 | L21: 0 | M21: 3
B22: REGIÓN URUAPAN | C22: 3 | D22: 0 | E22: 0 | F22: 0 | G22: 1 | H22: 0 | I22: 0 | J22: 0 | K22: 2 | L22: 0 | M22: 6
B23: REGIÓN APATZINGAN | C23: 0 | D23: 0 | E23: 0 | F23: 0 | G23: 0 | H23: 0 | I23: 0 | J23: 0 | K23: 0 | L23: 0 | M23: 0
B24: REGIÓN HUETAMO | C24: 1 | D24: 0 | E24: 0 | F24: 0 | G24: 0 | H24: 0 | I24: 0 | J24: 0 | K24: 1 | L24: 0 | M24: 2
B25: REGIÓN COALCOMAN | C25: 0 | D25: 0 | E25: 0 | F25: 0 | G25: 0 | H25: 0 | I25: 0 | J25: 0 | K25: 0 | L25: 0 | M25: 0
B26: REGIÓN ZITACUARO | C26: 2 | D26: 0 | E26: 0 | F26: 0 | G26: 2 | H26: 0 | I26: 0 | J26: 0 | K26: 1 | L26: 0 | M26: 5
B27: REGIÓN LÁZARO CÁRDENAS | C27: 0 | D27: 0 | E27: 0 | F27: 0 | G27: 0 | H27: 0 | I27: 0 | J27: 0 | K27: 0 | L27: 0 | M27: 0
B28: TOTAL | C28: 7 | D28: 1 | E28: 1 | F28: 0 | G28: 9 | H28: 0 | I28: 0 | J28: 1 | K28: 16 | L28: 0 | M28: 35
B30: FECHA | C30: 46120 | D30: TOTAL DE ESTADO DE FUERZA VEHICULAR
B31: ÁREA Y/O REGIÓN | C31: CHARGER | D31: FORD 150 | E31: CAMIONETA F250 | F31: RAM DODGE 1500 | G31: JEEP PATRIOT | H31: ECO SPORT | I31: TSURU | J31: PLATINA | K31: KAWASAKY KLR650 | L31: KAWASAKY ER-6N | M31: TOTAL
B32: REGIÓN MORELIA | C32: 4 | D32: 1 | E32: 0 | F32: 2 | G32: 6 | H32: 0 | I32: 2 | J32: 0 | K32: 11 | L32: 0 | M32: 26
B33: REGIÓN JÍQUILPAN | C33: 0 | D33: 0 | E33: 0 | F33: 0 | G33: 5 | H33: 0 | I33: 0 | J33: 1 | K33: 3 | L33: 0 | M33: 9
B34: REGIÓN ZAMORA | C34: 5 | D34: 1 | E34: 2 | F34: 1 | G34: 4 | H34: 0 | I34: 1 | J34: 0 | K34: 7 | L34: 0 | M34: 21
B35: REGIÓN LA PIEDAD | C35: 3 | D35: 1 | E35: 0 | F35: 1 | G35: 2 | H35: 1 | I35: 0 | J35: 0 | K35: 4 | L35: 0 | M35: 12
B36: REGIÓN URUAPAN | C36: 8 | D36: 1 | E36: 0 | F36: 1 | G36: 3 | H36: 0 | I36: 0 | J36: 0 | K36: 3 | L36: 0 | M36: 16
B37: REGIÓN APATZINGAN | C37: 2 | D37: 0 | E37: 0 | F37: 0 | G37: 3 | H37: 0 | I37: 2 | J37: 0 | K37: 4 | L37: 0 | M37: 11
B38: REGIÓN HUETAMO | C38: 1 | D38: 0 | E38: 0 | F38: 0 | G38: 0 | H38: 0 | I38: 1 | J38: 0 | K38: 1 | L38: 0 | M38: 3
B39: REGIÓN COALCOMAN | C39: 0 | D39: 0 | E39: 0 | F39: 0 | G39: 0 | H39: 0 | I39: 2 | J39: 0 | K39: 0 | L39: 0 | M39: 2
B40: REGIÓN ZITACUARO | C40: 3 | D40: 1 | E40: 0 | F40: 1 | G40: 6 | H40: 0 | I40: 1 | J40: 0 | K40: 1 | L40: 0 | M40: 13
B41: REGIÓN LÁZARO CÁRDENAS | C41: 2 | D41: 1 | E41: 0 | F41: 0 | G41: 2 | H41: 0 | I41: 0 | J41: 0 | K41: 0 | L41: 0 | M41: 5
B42: TOTAL | C42: 28 | D42: 6 | E42: 2 | F42: 6 | G42: 31 | H42: 1 | I42: 9 | J42: 1 | K42: 34 | L42: 0 | M42: 118
C43: TRUE | D43: TRUE | E43: TRUE | F43: TRUE | G43: TRUE | H43: TRUE | I43: TRUE | J43: TRUE | K43: TRUE | L43: TRUE

Sheet ARM.
B2: FECHA | C2: 46120 | D2: ESTADO DE FUERZA DE ARMAMENTO
B3: REGIÓN | C3: ARMAS | F3: MUNICIÓN | J3: DONDE SE ENCUENTRAN
C4: ARMA CORTA | D4: ARMA LARGA | E4: TOTAL | F4: CARGADORES | G4: CARTUCHOS 9mm | H4: CARTUCHOS .223 Y/O 5.56 | I4: CARTUCHOS 0.38 | J4: ASIGNADO | K4: EN DEPÓSITO | L4: TOTAL
B5: REGIÓN MORELIA | C5: 30 | D5: 26 | E5: 56 | F5: 113 | G5: 878 | H5: 1805 | I5: 54 | J5: 22 | K5: 37 | L5: 59 | M5: FALSE
B6: REGIÓN JÍQUILPAN | C6: 7 | D6: 4 | E6: 11 | F6: 26 | G6: 440 | H6: 360 | I6: 0 | J6: 9 | K6: 7 | L6: 16 | M6: FALSE
B7: REGIÓN ZAMORA | C7: 30 | D7: 27 | E7: 57 | F7: 111 | G7: 1012 | H7: 2160 | I7: 27 | J7: 38 | K7: 27 | L7: 65 | M7: FALSE
B8: REGIÓN LA PIEDAD | C8: 12 | D8: 11 | E8: 23 | F8: 50 | G8: 491 | H8: 770 | I8: 0 | J8: 14 | K8: 9 | L8: 23 | M8: TRUE
B9: REGIÓN URUAPAN | C9: 23 | D9: 21 | E9: 44 | F9: 85 | G9: 331 | H9: 1000 | I9: 25 | J9: 21 | K9: 10 | L9: 31 | M9: FALSE
B10: REGIÓN APATZINGAN | C10: 8 | D10: 5 | E10: 13 | F10: 25 | G10: 240 | H10: 380 | I10: 0 | J10: 8 | K10: 6 | L10: 14 | M10: FALSE
B11: REGIÓN HUETAMO | C11: 7 | D11: 7 | E11: 14 | F11: 14 | G11: 100 | H11: 360 | I11: 0 | J11: 8 | K11: 2 | L11: 10 | M11: FALSE
B12: REGIÓN COALCOMAN | C12: 5 | D12: 4 | E12: 9 | F12: 12 | G12: 105 | H12: 150 | I12: 6 | J12: 7 | K12: 2 | L12: 9 | M12: TRUE
B13: REGIÓN ZITACUARO | C13: 22 | D13: 10 | E13: 32 | F13: 52 | G13: 30 | H13: 610 | I13: 0 | J13: 16 | K13: 17 | L13: 33 | M13: FALSE
B14: REGIÓN LÁZARO CÁRDENAS | C14: 8 | D14: 5 | E14: 13 | F14: 21 | G14: 163 | H14: 255 | I14: 36 | J14: 4 | K14: 9 | L14: 13 | M14: TRUE
B15: TOTAL | C15: 152 | D15: 120 | E15: 272 | F15: 509 | G15: 3790 | H15: 7850 | I15: 148 | J15: 147 | K15: 126 | L15: 273

Sheet TOTAL
C1: DELEGACIONES
B2: FECHA | C2: ='SINIESTROS Y HECHOS'!R1 -> 46129
A3: No. | B3: CATEGORÍA | C3: ACTIVIDAD | D3: CANTIDAD | E3: ESTADO DE FUERZA PARTICIPANTE | F3: UNIDADES PARTICIPANTES | G3: KILOMETROS RECORRIDOS | H3: PERSONAS ALCANZADAS | I3: RECOMENDACIONES
A4: 1 | B4: INSTITUCIONES | C4: APOYO A EVENTOS PÚBLICOS | D4: =MORELIA!D4+JIQUILPAN!D4+ZAMORA!D4+'LA PIEDAD'!D4+URUAPAN!D4+APATZINGAN!D4+HUETAMO!D4+COALCOMAN!D4+ZITACUARO!D4+LAZARO!D4 -> 1 | E4: =MORELIA!E4+JIQUILPAN!E4+ZAMORA!E4+'LA PIEDAD'!E4+URUAPAN!E4+APATZINGAN!E4+HUETAMO!E4+COALCOMAN!E4+ZITACUARO!E4+LAZARO!E4 -> 1 | F4: =MORELIA!F4+JIQUILPAN!F4+ZAMORA!F4+'LA PIEDAD'!F4+URUAPAN!F4+APATZINGAN!F4+HUETAMO!F4+COALCOMAN!F4+ZITACUARO!F4+LAZARO!F4 -> 1 | G4: =MORELIA!G4+JIQUILPAN!G4+ZAMORA!G4+'LA PIEDAD'!G4+URUAPAN!G4+APATZINGAN!G4+HUETAMO!G4+COALCOMAN!G4+ZITACUARO!G4+LAZARO!G4 -> 4 | H4: =MORELIA!H4+JIQUILPAN!H4+ZAMORA!H4+'LA PIEDAD'!H4+URUAPAN!H4+APATZINGAN!H4+HUETAMO!H4+COALCOMAN!H4+ZITACUARO!H4+LAZARO!H4 -> 4 | I4: =MORELIA!I4+JIQUILPAN!I4+ZAMORA!I4+'LA PIEDAD'!I4+URUAPAN!I4+APATZINGAN!I4+HUETAMO!I4+COALCOMAN!I4+ZITACUARO!I4+LAZARO!I4 -> 0
C5: APOYO A EVENTOS DEPORTIVOS | D5: =MORELIA!D5+JIQUILPAN!D5+ZAMORA!D5+'LA PIEDAD'!D5+URUAPAN!D5+APATZINGAN!D5+HUETAMO!D5+COALCOMAN!D5+ZITACUARO!D5+LAZARO!D5 -> 0 | E5: =MORELIA!E5+JIQUILPAN!E5+ZAMORA!E5+'LA PIEDAD'!E5+URUAPAN!E5+APATZINGAN!E5+HUETAMO!E5+COALCOMAN!E5+ZITACUARO!E5+LAZARO!E5 -> 0 | F5: =MORELIA!F5+JIQUILPAN!F5+ZAMORA!F5+'LA PIEDAD'!F5+URUAPAN!F5+APATZINGAN!F5+HUETAMO!F5+COALCOMAN!F5+ZITACUARO!F5+LAZARO!F5 -> 0 | G5: =MORELIA!G5+JIQUILPAN!G5+ZAMORA!G5+'LA PIEDAD'!G5+URUAPAN!G5+APATZINGAN!G5+HUETAMO!G5+COALCOMAN!G5+ZITACUARO!G5+LAZARO!G5 -> 0 | H5: =MORELIA!H5+JIQUILPAN!H5+ZAMORA!H5+'LA PIEDAD'!H5+URUAPAN!H5+APATZINGAN!H5+HUETAMO!H5+COALCOMAN!H5+ZITACUARO!H5+LAZARO!H5 -> 0 | I5: =MORELIA!I5+JIQUILPAN!I5+ZAMORA!I5+'LA PIEDAD'!I5+URUAPAN!I5+APATZINGAN!I5+HUETAMO!I5+COALCOMAN!I5+ZITACUARO!I5+LAZARO!I5 -> 0
C6: APOYO A EVENTOS CULTURALES | D6: =MORELIA!D6+JIQUILPAN!D6+ZAMORA!D6+'LA PIEDAD'!D6+URUAPAN!D6+APATZINGAN!D6+HUETAMO!D6+COALCOMAN!D6+ZITACUARO!D6+LAZARO!D6 -> 0 | E6: =MORELIA!E6+JIQUILPAN!E6+ZAMORA!E6+'LA PIEDAD'!E6+URUAPAN!E6+APATZINGAN!E6+HUETAMO!E6+COALCOMAN!E6+ZITACUARO!E6+LAZARO!E6 -> 0 | F6: =MORELIA!F6+JIQUILPAN!F6+ZAMORA!F6+'LA PIEDAD'!F6+URUAPAN!F6+APATZINGAN!F6+HUETAMO!F6+COALCOMAN!F6+ZITACUARO!F6+LAZARO!F6 -> 0 | G6: =MORELIA!G6+JIQUILPAN!G6+ZAMORA!G6+'LA PIEDAD'!G6+URUAPAN!G6+APATZINGAN!G6+HUETAMO!G6+COALCOMAN!G6+ZITACUARO!G6+LAZARO!G6 -> 0 | H6: =MORELIA!H6+JIQUILPAN!H6+ZAMORA!H6+'LA PIEDAD'!H6+URUAPAN!H6+APATZINGAN!H6+HUETAMO!H6+COALCOMAN!H6+ZITACUARO!H6+LAZARO!H6 -> 0 | I6: =MORELIA!I6+JIQUILPAN!I6+ZAMORA!I6+'LA PIEDAD'!I6+URUAPAN!I6+APATZINGAN!I6+HUETAMO!I6+COALCOMAN!I6+ZITACUARO!I6+LAZARO!I6 -> 0
C7: APOYO A EVENTOS RELIGIOSOS | D7: =MORELIA!D7+JIQUILPAN!D7+ZAMORA!D7+'LA PIEDAD'!D7+URUAPAN!D7+APATZINGAN!D7+HUETAMO!D7+COALCOMAN!D7+ZITACUARO!D7+LAZARO!D7 -> 1 | E7: =MORELIA!E7+JIQUILPAN!E7+ZAMORA!E7+'LA PIEDAD'!E7+URUAPAN!E7+APATZINGAN!E7+HUETAMO!E7+COALCOMAN!E7+ZITACUARO!E7+LAZARO!E7 -> 1 | F7: =MORELIA!F7+JIQUILPAN!F7+ZAMORA!F7+'LA PIEDAD'!F7+URUAPAN!F7+APATZINGAN!F7+HUETAMO!F7+COALCOMAN!F7+ZITACUARO!F7+LAZARO!F7 -> 0 | G7: =MORELIA!G7+JIQUILPAN!G7+ZAMORA!G7+'LA PIEDAD'!G7+URUAPAN!G7+APATZINGAN!G7+HUETAMO!G7+COALCOMAN!G7+ZITACUARO!G7+LAZARO!G7 -> 0 | H7: =MORELIA!H7+JIQUILPAN!H7+ZAMORA!H7+'LA PIEDAD'!H7+URUAPAN!H7+APATZINGAN!H7+HUETAMO!H7+COALCOMAN!H7+ZITACUARO!H7+LAZARO!H7 -> 0 | I7: =MORELIA!I7+JIQUILPAN!I7+ZAMORA!I7+'LA PIEDAD'!I7+URUAPAN!I7+APATZINGAN!I7+HUETAMO!I7+COALCOMAN!I7+ZITACUARO!I7+LAZARO!I7 -> 0
C8: APOYOS A OTRAS DEPENDENCIAS (Publicas o privadas) | D8: =MORELIA!D8+JIQUILPAN!D8+ZAMORA!D8+'LA PIEDAD'!D8+URUAPAN!D8+APATZINGAN!D8+HUETAMO!D8+COALCOMAN!D8+ZITACUARO!D8+LAZARO!D8 -> 2 | E8: =MORELIA!E8+JIQUILPAN!E8+ZAMORA!E8+'LA PIEDAD'!E8+URUAPAN!E8+APATZINGAN!E8+HUETAMO!E8+COALCOMAN!E8+ZITACUARO!E8+LAZARO!E8 -> 8 | F8: =MORELIA!F8+JIQUILPAN!F8+ZAMORA!F8+'LA PIEDAD'!F8+URUAPAN!F8+APATZINGAN!F8+HUETAMO!F8+COALCOMAN!F8+ZITACUARO!F8+LAZARO!F8 -> 2 | G8: =MORELIA!G8+JIQUILPAN!G8+ZAMORA!G8+'LA PIEDAD'!G8+URUAPAN!G8+APATZINGAN!G8+HUETAMO!G8+COALCOMAN!G8+ZITACUARO!G8+LAZARO!G8 -> 19 | H8: =MORELIA!H8+JIQUILPAN!H8+ZAMORA!H8+'LA PIEDAD'!H8+URUAPAN!H8+APATZINGAN!H8+HUETAMO!H8+COALCOMAN!H8+ZITACUARO!H8+LAZARO!H8 -> 40 | I8: =MORELIA!I8+JIQUILPAN!I8+ZAMORA!I8+'LA PIEDAD'!I8+URUAPAN!I8+APATZINGAN!I8+HUETAMO!I8+COALCOMAN!I8+ZITACUARO!I8+LAZARO!I8 -> 0
C9: ESCUELAS | D9: =MORELIA!D9+JIQUILPAN!D9+ZAMORA!D9+'LA PIEDAD'!D9+URUAPAN!D9+APATZINGAN!D9+HUETAMO!D9+COALCOMAN!D9+ZITACUARO!D9+LAZARO!D9 -> 74 | E9: =MORELIA!E9+JIQUILPAN!E9+ZAMORA!E9+'LA PIEDAD'!E9+URUAPAN!E9+APATZINGAN!E9+HUETAMO!E9+COALCOMAN!E9+ZITACUARO!E9+LAZARO!E9 -> 132 | F9: =MORELIA!F9+JIQUILPAN!F9+ZAMORA!F9+'LA PIEDAD'!F9+URUAPAN!F9+APATZINGAN!F9+HUETAMO!F9+COALCOMAN!F9+ZITACUARO!F9+LAZARO!F9 -> 64 | G9: =MORELIA!G9+JIQUILPAN!G9+ZAMORA!G9+'LA PIEDAD'!G9+URUAPAN!G9+APATZINGAN!G9+HUETAMO!G9+COALCOMAN!G9+ZITACUARO!G9+LAZARO!G9 -> 630 | H9: =MORELIA!H9+JIQUILPAN!H9+ZAMORA!H9+'LA PIEDAD'!H9+URUAPAN!H9+APATZINGAN!H9+HUETAMO!H9+COALCOMAN!H9+ZITACUARO!H9+LAZARO!H9 -> 6730 | I9: =MORELIA!I9+JIQUILPAN!I9+ZAMORA!I9+'LA PIEDAD'!I9+URUAPAN!I9+APATZINGAN!I9+HUETAMO!I9+COALCOMAN!I9+ZITACUARO!I9+LAZARO!I9 -> 0
C10: DILIGENCIAS | D10: =MORELIA!D10+JIQUILPAN!D10+ZAMORA!D10+'LA PIEDAD'!D10+URUAPAN!D10+APATZINGAN!D10+HUETAMO!D10+COALCOMAN!D10+ZITACUARO!D10+LAZARO!D10 -> 1 | E10: =MORELIA!E10+JIQUILPAN!E10+ZAMORA!E10+'LA PIEDAD'!E10+URUAPAN!E10+APATZINGAN!E10+HUETAMO!E10+COALCOMAN!E10+ZITACUARO!E10+LAZARO!E10 -> 2 | F10: =MORELIA!F10+JIQUILPAN!F10+ZAMORA!F10+'LA PIEDAD'!F10+URUAPAN!F10+APATZINGAN!F10+HUETAMO!F10+COALCOMAN!F10+ZITACUARO!F10+LAZARO!F10 -> 1 | G10: =MORELIA!G10+JIQUILPAN!G10+ZAMORA!G10+'LA PIEDAD'!G10+URUAPAN!G10+APATZINGAN!G10+HUETAMO!G10+COALCOMAN!G10+ZITACUARO!G10+LAZARO!G10 -> 1 | H10: =MORELIA!H10+JIQUILPAN!H10+ZAMORA!H10+'LA PIEDAD'!H10+URUAPAN!H10+APATZINGAN!H10+HUETAMO!H10+COALCOMAN!H10+ZITACUARO!H10+LAZARO!H10 -> 130 | I10: =MORELIA!I10+JIQUILPAN!I10+ZAMORA!I10+'LA PIEDAD'!I10+URUAPAN!I10+APATZINGAN!I10+HUETAMO!I10+COALCOMAN!I10+ZITACUARO!I10+LAZARO!I10 -> 0
C11: OTROS TIPOS (Especificar en las novedades relevantes) | D11: =MORELIA!D11+JIQUILPAN!D11+ZAMORA!D11+'LA PIEDAD'!D11+URUAPAN!D11+APATZINGAN!D11+HUETAMO!D11+COALCOMAN!D11+ZITACUARO!D11+LAZARO!D11 -> 0 | E11: =MORELIA!E11+JIQUILPAN!E11+ZAMORA!E11+'LA PIEDAD'!E11+URUAPAN!E11+APATZINGAN!E11+HUETAMO!E11+COALCOMAN!E11+ZITACUARO!E11+LAZARO!E11 -> 0 | F11: =MORELIA!F11+JIQUILPAN!F11+ZAMORA!F11+'LA PIEDAD'!F11+URUAPAN!F11+APATZINGAN!F11+HUETAMO!F11+COALCOMAN!F11+ZITACUARO!F11+LAZARO!F11 -> 0 | G11: =MORELIA!G11+JIQUILPAN!G11+ZAMORA!G11+'LA PIEDAD'!G11+URUAPAN!G11+APATZINGAN!G11+HUETAMO!G11+COALCOMAN!G11+ZITACUARO!G11+LAZARO!G11 -> 0 | H11: =MORELIA!H11+JIQUILPAN!H11+ZAMORA!H11+'LA PIEDAD'!H11+URUAPAN!H11+APATZINGAN!H11+HUETAMO!H11+COALCOMAN!H11+ZITACUARO!H11+LAZARO!H11 -> 0 | I11: =MORELIA!I11+JIQUILPAN!I11+ZAMORA!I11+'LA PIEDAD'!I11+URUAPAN!I11+APATZINGAN!I11+HUETAMO!I11+COALCOMAN!I11+ZITACUARO!I11+LAZARO!I11 -> 0
A12: 2 | B12: REPORTES C5i | C12: OBSTRUCCIÓN DE COCHERAS | D12: =MORELIA!D12+JIQUILPAN!D12+ZAMORA!D12+'LA PIEDAD'!D12+URUAPAN!D12+APATZINGAN!D12+HUETAMO!D12+COALCOMAN!D12+ZITACUARO!D12+LAZARO!D12 -> 0 | E12: =MORELIA!E12+JIQUILPAN!E12+ZAMORA!E12+'LA PIEDAD'!E12+URUAPAN!E12+APATZINGAN!E12+HUETAMO!E12+COALCOMAN!E12+ZITACUARO!E12+LAZARO!E12 -> 0 | F12: =MORELIA!F12+JIQUILPAN!F12+ZAMORA!F12+'LA PIEDAD'!F12+URUAPAN!F12+APATZINGAN!F12+HUETAMO!F12+COALCOMAN!F12+ZITACUARO!F12+LAZARO!F12 -> 0 | G12: =MORELIA!G12+JIQUILPAN!G12+ZAMORA!G12+'LA PIEDAD'!G12+URUAPAN!G12+APATZINGAN!G12+HUETAMO!G12+COALCOMAN!G12+ZITACUARO!G12+LAZARO!G12 -> 0 | H12: =MORELIA!H12+JIQUILPAN!H12+ZAMORA!H12+'LA PIEDAD'!H12+URUAPAN!H12+APATZINGAN!H12+HUETAMO!H12+COALCOMAN!H12+ZITACUARO!H12+LAZARO!H12 -> 0 | I12: =MORELIA!I12+JIQUILPAN!I12+ZAMORA!I12+'LA PIEDAD'!I12+URUAPAN!I12+APATZINGAN!I12+HUETAMO!I12+COALCOMAN!I12+ZITACUARO!I12+LAZARO!I12 -> 0
C13: OTROS TIPOS DE OBSTRUCCIÓN | D13: =MORELIA!D13+JIQUILPAN!D13+ZAMORA!D13+'LA PIEDAD'!D13+URUAPAN!D13+APATZINGAN!D13+HUETAMO!D13+COALCOMAN!D13+ZITACUARO!D13+LAZARO!D13 -> 0 | E13: =MORELIA!E13+JIQUILPAN!E13+ZAMORA!E13+'LA PIEDAD'!E13+URUAPAN!E13+APATZINGAN!E13+HUETAMO!E13+COALCOMAN!E13+ZITACUARO!E13+LAZARO!E13 -> 0 | F13: =MORELIA!F13+JIQUILPAN!F13+ZAMORA!F13+'LA PIEDAD'!F13+URUAPAN!F13+APATZINGAN!F13+HUETAMO!F13+COALCOMAN!F13+ZITACUARO!F13+LAZARO!F13 -> 0 | G13: =MORELIA!G13+JIQUILPAN!G13+ZAMORA!G13+'LA PIEDAD'!G13+URUAPAN!G13+APATZINGAN!G13+HUETAMO!G13+COALCOMAN!G13+ZITACUARO!G13+LAZARO!G13 -> 0 | H13: =MORELIA!H13+JIQUILPAN!H13+ZAMORA!H13+'LA PIEDAD'!H13+URUAPAN!H13+APATZINGAN!H13+HUETAMO!H13+COALCOMAN!H13+ZITACUARO!H13+LAZARO!H13 -> 0 | I13: =MORELIA!I13+JIQUILPAN!I13+ZAMORA!I13+'LA PIEDAD'!I13+URUAPAN!I13+APATZINGAN!I13+HUETAMO!I13+COALCOMAN!I13+ZITACUARO!I13+LAZARO!I13 -> 0
C14: ACTOS DELICTIVOS | D14: =MORELIA!D14+JIQUILPAN!D14+ZAMORA!D14+'LA PIEDAD'!D14+URUAPAN!D14+APATZINGAN!D14+HUETAMO!D14+COALCOMAN!D14+ZITACUARO!D14+LAZARO!D14 -> 1 | E14: =MORELIA!E14+JIQUILPAN!E14+ZAMORA!E14+'LA PIEDAD'!E14+URUAPAN!E14+APATZINGAN!E14+HUETAMO!E14+COALCOMAN!E14+ZITACUARO!E14+LAZARO!E14 -> 1 | F14: =MORELIA!F14+JIQUILPAN!F14+ZAMORA!F14+'LA PIEDAD'!F14+URUAPAN!F14+APATZINGAN!F14+HUETAMO!F14+COALCOMAN!F14+ZITACUARO!F14+LAZARO!F14 -> 1 | G14: =MORELIA!G14+JIQUILPAN!G14+ZAMORA!G14+'LA PIEDAD'!G14+URUAPAN!G14+APATZINGAN!G14+HUETAMO!G14+COALCOMAN!G14+ZITACUARO!G14+LAZARO!G14 -> 30 | H14: =MORELIA!H14+JIQUILPAN!H14+ZAMORA!H14+'LA PIEDAD'!H14+URUAPAN!H14+APATZINGAN!H14+HUETAMO!H14+COALCOMAN!H14+ZITACUARO!H14+LAZARO!H14 -> 0 | I14: =MORELIA!I14+JIQUILPAN!I14+ZAMORA!I14+'LA PIEDAD'!I14+URUAPAN!I14+APATZINGAN!I14+HUETAMO!I14+COALCOMAN!I14+ZITACUARO!I14+LAZARO!I14 -> 0
C15: SINIESTROS | D15: =MORELIA!D15+JIQUILPAN!D15+ZAMORA!D15+'LA PIEDAD'!D15+URUAPAN!D15+APATZINGAN!D15+HUETAMO!D15+COALCOMAN!D15+ZITACUARO!D15+LAZARO!D15 -> 3 | E15: =MORELIA!E15+JIQUILPAN!E15+ZAMORA!E15+'LA PIEDAD'!E15+URUAPAN!E15+APATZINGAN!E15+HUETAMO!E15+COALCOMAN!E15+ZITACUARO!E15+LAZARO!E15 -> 6 | F15: =MORELIA!F15+JIQUILPAN!F15+ZAMORA!F15+'LA PIEDAD'!F15+URUAPAN!F15+APATZINGAN!F15+HUETAMO!F15+COALCOMAN!F15+ZITACUARO!F15+LAZARO!F15 -> 3 | G15: =MORELIA!G15+JIQUILPAN!G15+ZAMORA!G15+'LA PIEDAD'!G15+URUAPAN!G15+APATZINGAN!G15+HUETAMO!G15+COALCOMAN!G15+ZITACUARO!G15+LAZARO!G15 -> 25 | H15: =MORELIA!H15+JIQUILPAN!H15+ZAMORA!H15+'LA PIEDAD'!H15+URUAPAN!H15+APATZINGAN!H15+HUETAMO!H15+COALCOMAN!H15+ZITACUARO!H15+LAZARO!H15 -> 0 | I15: =MORELIA!I15+JIQUILPAN!I15+ZAMORA!I15+'LA PIEDAD'!I15+URUAPAN!I15+APATZINGAN!I15+HUETAMO!I15+COALCOMAN!I15+ZITACUARO!I15+LAZARO!I15 -> 0
C16: HECHOS DE TRÁNSITO | D16: =MORELIA!D16+JIQUILPAN!D16+ZAMORA!D16+'LA PIEDAD'!D16+URUAPAN!D16+APATZINGAN!D16+HUETAMO!D16+COALCOMAN!D16+ZITACUARO!D16+LAZARO!D16 -> 5 | E16: =MORELIA!E16+JIQUILPAN!E16+ZAMORA!E16+'LA PIEDAD'!E16+URUAPAN!E16+APATZINGAN!E16+HUETAMO!E16+COALCOMAN!E16+ZITACUARO!E16+LAZARO!E16 -> 10 | F16: =MORELIA!F16+JIQUILPAN!F16+ZAMORA!F16+'LA PIEDAD'!F16+URUAPAN!F16+APATZINGAN!F16+HUETAMO!F16+COALCOMAN!F16+ZITACUARO!F16+LAZARO!F16 -> 5 | G16: =MORELIA!G16+JIQUILPAN!G16+ZAMORA!G16+'LA PIEDAD'!G16+URUAPAN!G16+APATZINGAN!G16+HUETAMO!G16+COALCOMAN!G16+ZITACUARO!G16+LAZARO!G16 -> 45 | H16: =MORELIA!H16+JIQUILPAN!H16+ZAMORA!H16+'LA PIEDAD'!H16+URUAPAN!H16+APATZINGAN!H16+HUETAMO!H16+COALCOMAN!H16+ZITACUARO!H16+LAZARO!H16 -> 0 | I16: =MORELIA!I16+JIQUILPAN!I16+ZAMORA!I16+'LA PIEDAD'!I16+URUAPAN!I16+APATZINGAN!I16+HUETAMO!I16+COALCOMAN!I16+ZITACUARO!I16+LAZARO!I16 -> 0
C17: CONSENTRACION PERSONAS | D17: =MORELIA!D17+JIQUILPAN!D17+ZAMORA!D17+'LA PIEDAD'!D17+URUAPAN!D17+APATZINGAN!D17+HUETAMO!D17+COALCOMAN!D17+ZITACUARO!D17+LAZARO!D17 -> 0 | E17: =MORELIA!E17+JIQUILPAN!E17+ZAMORA!E17+'LA PIEDAD'!E17+URUAPAN!E17+APATZINGAN!E17+HUETAMO!E17+COALCOMAN!E17+ZITACUARO!E17+LAZARO!E17 -> 0 | F17: =MORELIA!F17+JIQUILPAN!F17+ZAMORA!F17+'LA PIEDAD'!F17+URUAPAN!F17+APATZINGAN!F17+HUETAMO!F17+COALCOMAN!F17+ZITACUARO!F17+LAZARO!F17 -> 0 | G17: =MORELIA!G17+JIQUILPAN!G17+ZAMORA!G17+'LA PIEDAD'!G17+URUAPAN!G17+APATZINGAN!G17+HUETAMO!G17+COALCOMAN!G17+ZITACUARO!G17+LAZARO!G17 -> 0 | H17: =MORELIA!H17+JIQUILPAN!H17+ZAMORA!H17+'LA PIEDAD'!H17+URUAPAN!H17+APATZINGAN!H17+HUETAMO!H17+COALCOMAN!H17+ZITACUARO!H17+LAZARO!H17 -> 0 | I17: =MORELIA!I17+JIQUILPAN!I17+ZAMORA!I17+'LA PIEDAD'!I17+URUAPAN!I17+APATZINGAN!I17+HUETAMO!I17+COALCOMAN!I17+ZITACUARO!I17+LAZARO!I17 -> 0
